Workbook

Sheet 개요
A1: 통합 AI 보안위협 매트릭스 (UTM) v3.1
A2: Lv1 도메인 10 · Lv2 위협 분류 36 · Lv3 세부 위협 127 · 위험 평가(발생가능성×심각도) | 2026-10-01
A4: 1. 통합 대상 소스
A5: 소스 | B5: 버전 / 공개일 | C5: 규모 | D5: 관점 | E5: 입수 경로
A6: MITRE ATLAS | B6: v2026.09 (2026-09-15) | C6: 전술 16 · 기법 208 · 완화책 40 · 사례 73 · 절차 665 | D6: 공격자 TTP | E6: 첨부 excel-atlas*.xlsx + ATLAS-2026_09.yaml
A7: OWASP Top 10 for LLM Applications | B7: 2026 (2026-08-04) | C7: 10 | D7: LLM 애플리케이션 위험 | E7: 첨부 원문
A8: OWASP Top 10 for Agentic Applications | B8: 2026 (2025-12-09) | C8: 10 + 사고 추적표 25건 | D8: 에이전트 위험 | E8: 첨부 원문
A9: OWASP GenAI Data Security | B9: 2026 v1.0 (2026-03) | C9: 21 | D9: 데이터 생애주기 위험 | E9: 첨부 원문
A10: OWASP MCP Top 10 (승인된 추가 소스) | B10: 2025 (beta) | C10: 10 | D10: MCP 프로토콜 계층 | E10: github.com/OWASP/www-project-mcp-top-10
A12: 2. 핵심 지표 (수식 연동)
A13: Lv1 도메인 / Lv2 위협 분류 / Lv3 세부 위협 | B13: =SUMPRODUCT(1/COUNTIF(통합매트릭스!$A$5:$A$131,통합매트릭스!$A$5:$A$131))&" / "&SUMPRODUCT(1/COUNTIF(통합매트릭스!$B$5:$B$131,통합매트릭스!$B$5:$B$131))&" / "&COUNTA(통합매트릭스!$D$5:$D$131) -> 10 / 36 / 127
A14: ATLAS 기법 귀속률 (Lv3 + 영향 패싯) | B14: =(COUNTIF(ATLAS기법매핑!G5:G212,"UT-*")+COUNTIF(ATLAS기법매핑!G5:G212,"영향 패싯"))/COUNTA(ATLAS기법매핑!A5:A212) -> 1
A15: 소스 항목(51) 매핑률 | B15: =COUNTIF(소스항목사전!G5:G55,">0")/COUNTA(소스항목사전!A5:A55) -> 1
A16: OWASP 공식 크로스워크 반영률 | B16: =공식크로스워크검증!B3 -> 1
A17: 사례 매핑 ↔ 공식 절차 주 UT 일치율 | B17: =COUNTIF(ATLAS사례연구!O5:O77,"일치*")/COUNTA(ATLAS사례연구!A5:A77) -> 0.97260274
A18: 실제 사고가 확인된 Lv3 | B18: =COUNTIF(통합매트릭스!$AQ$5:$AQ$131,"실제 사고 확인") -> 51
A19: 이론·시나리오 수준 Lv3 (공개 근거 없음) | B19: =COUNTIF(통합매트릭스!$AQ$5:$AQ$131,"이론·시나리오") -> 33
A20: 위험도 매우 높음 / 높음 / 보통 / 낮음 | B20: =COUNTIF(통합매트릭스!$I$5:$I$131,"매우 높음")&" / "&COUNTIF(통합매트릭스!$I$5:$I$131,"높음")&" / "&COUNTIF(통합매트릭스!$I$5:$I$131,"보통")&" / "&COUNTIF(통합매트릭스!$I$5:$I$131,"낮음") -> 17 / 39 / 38 / 33
A22: 3. 위험 매트릭스 (Lv3 수)
A23: 발생가능성 \ 심각도 | B23: 상 | C23: 중 | D23: 하
A24: 상 | B24: =COUNTIFS(통합매트릭스!$G$5:$G$131,"상",통합매트릭스!$H$5:$H$131,"상") -> 17 | C24: =COUNTIFS(통합매트릭스!$G$5:$G$131,"상",통합매트릭스!$H$5:$H$131,"중") -> 11 | D24: =COUNTIFS(통합매트릭스!$G$5:$G$131,"상",통합매트릭스!$H$5:$H$131,"하") -> 5
A25: 중 | B25: =COUNTIFS(통합매트릭스!$G$5:$G$131,"중",통합매트릭스!$H$5:$H$131,"상") -> 28 | C25: =COUNTIFS(통합매트릭스!$G$5:$G$131,"중",통합매트릭스!$H$5:$H$131,"중") -> 28 | D25: =COUNTIFS(통합매트릭스!$G$5:$G$131,"중",통합매트릭스!$H$5:$H$131,"하") -> 5
A26: 하 | B26: =COUNTIFS(통합매트릭스!$G$5:$G$131,"하",통합매트릭스!$H$5:$H$131,"상") -> 5 | C26: =COUNTIFS(통합매트릭스!$G$5:$G$131,"하",통합매트릭스!$H$5:$H$131,"중") -> 28 | D26: =COUNTIFS(통합매트릭스!$G$5:$G$131,"하",통합매트릭스!$H$5:$H$131,"하") -> 0
A28: 4. 위험도 '매우 높음' Lv3
A29: Lv3 ID | B29: 세부 위협 | C29: 위협 분류 (Lv2) | D29: 발생가능성 근거
A30: {=IF(1<=COUNTIF(통합매트릭스!$I$5:$I$131,"매우 높음"),INDEX(통합매트릭스!$D$5:$D$131,SMALL(IF(통합매트릭스!$I$5:$I$131="매우 높음",ROW(통합매트릭스!$I$5:$I$131)-5+1),1)),"")} -> UT-02.4 | B30: {=IF(1<=COUNTIF(통합매트릭스!$I$5:$I$131,"매우 높음"),INDEX(통합매트릭스!$E$5:$E$131,SMALL(IF(통합매트릭스!$I$5:$I$131="매우 높음",ROW(통합매트릭스!$I$5:$I$131)-5+1),1)),"")} -> 일반 초기 침투 | C30: {=IF(1<=COUNTIF(통합매트릭스!$I$5:$I$131,"매우 높음"),INDEX(통합매트릭스!$C$5:$C$131,SMALL(IF(통합매트릭스!$I$5:$I$131="매우 높음",ROW(통합매트릭스!$I$5:$I$131)-5+1),1)),"")} -> 공격 준비 및 일반 침투 기법 | D30: {=IF(1<=COUNTIF(통합매트릭스!$I$5:$I$131,"매우 높음"),INDEX(통합매트릭스!$J$5:$J$131,SMALL(IF(통합매트릭스!$I$5:$I$131="매우 높음",ROW(통합매트릭스!$I$5:$I$131)-5+1),1)),"")} -> 실제 사고 7건(ATLAS 6 / OWASP 1), 실증 사례 7건, Realized 기법 1개, 취약점·익스플로잇 1건
A31: {=IF(2<=COUNTIF(통합매트릭스!$I$5:$I$131,"매우 높음"),INDEX(통합매트릭스!$D$5:$D$131,SMALL(IF(통합매트릭스!$I$5:$I$131="매우 높음",ROW(통합매트릭스!$I$5:$I$131)-5+1),2)),"")} -> UT-02.6 | B31: {=IF(2<=COUNTIF(통합매트릭스!$I$5:$I$131,"매우 높음"),INDEX(통합매트릭스!$E$5:$E$131,SMALL(IF(통합매트릭스!$I$5:$I$131="매우 높음",ROW(통합매트릭스!$I$5:$I$131)-5+1),2)),"")} -> 일반 수단 데이터 유출 | C31: {=IF(2<=COUNTIF(통합매트릭스!$I$5:$I$131,"매우 높음"),INDEX(통합매트릭스!$C$5:$C$131,SMALL(IF(통합매트릭스!$I$5:$I$131="매우 높음",ROW(통합매트릭스!$I$5:$I$131)-5+1),2)),"")} -> 공격 준비 및 일반 침투 기법 | D31: {=IF(2<=COUNTIF(통합매트릭스!$I$5:$I$131,"매우 높음"),INDEX(통합매트릭스!$J$5:$J$131,SMALL(IF(통합매트릭스!$I$5:$I$131="매우 높음",ROW(통합매트릭스!$I$5:$I$131)-5+1),2)),"")} -> 실제 사고 9건(ATLAS 9 / OWASP 0), 실증 사례 10건, Realized 기법 6개, 취약점·익스플로잇 0건
A32: {=IF(3<=COUNTIF(통합매트릭스!$I$5:$I$131,"매우 높음"),INDEX(통합매트릭스!$D$5:$D$131,SMALL(IF(통합매트릭스!$I$5:$I$131="매우 높음",ROW(통합매트릭스!$I$5:$I$131)-5+1),3)),"")} -> UT-03.1 | B32: {=IF(3<=COUNTIF(통합매트릭스!$I$5:$I$131,"매우 높음"),INDEX(통합매트릭스!$E$5:$E$131,SMALL(IF(통합매트릭스!$I$5:$I$131="매우 높음",ROW(통합매트릭스!$I$5:$I$131)-5+1),3)),"")} -> 자율 공격 에이전트 | C32: {=IF(3<=COUNTIF(통합매트릭스!$I$5:$I$131,"매우 높음"),INDEX(통합매트릭스!$C$5:$C$131,SMALL(IF(통합매트릭스!$I$5:$I$131="매우 높음",ROW(통합매트릭스!$I$5:$I$131)-5+1),3)),"")} -> AI 기반 자율 공격 | D32: {=IF(3<=COUNTIF(통합매트릭스!$I$5:$I$131,"매우 높음"),INDEX(통합매트릭스!$J$5:$J$131,SMALL(IF(통합매트릭스!$I$5:$I$131="매우 높음",ROW(통합매트릭스!$I$5:$I$131)-5+1),3)),"")} -> 실제 사고 4건(ATLAS 4 / OWASP 0), 실증 사례 0건, Realized 기법 3개, 취약점·익스플로잇 0건
A33: {=IF(4<=COUNTIF(통합매트릭스!$I$5:$I$131,"매우 높음"),INDEX(통합매트릭스!$D$5:$D$131,SMALL(IF(통합매트릭스!$I$5:$I$131="매우 높음",ROW(통합매트릭스!$I$5:$I$131)-5+1),4)),"")} -> UT-03.2 | B33: {=IF(4<=COUNTIF(통합매트릭스!$I$5:$I$131,"매우 높음"),INDEX(통합매트릭스!$E$5:$E$131,SMALL(IF(통합매트릭스!$I$5:$I$131="매우 높음",ROW(통합매트릭스!$I$5:$I$131)-5+1),4)),"")} -> 다중 에이전트 공격 조율 | C33: {=IF(4<=COUNTIF(통합매트릭스!$I$5:$I$131,"매우 높음"),INDEX(통합매트릭스!$C$5:$C$131,SMALL(IF(통합매트릭스!$I$5:$I$131="매우 높음",ROW(통합매트릭스!$I$5:$I$131)-5+1),4)),"")} -> AI 기반 자율 공격 | D33: {=IF(4<=COUNTIF(통합매트릭스!$I$5:$I$131,"매우 높음"),INDEX(통합매트릭스!$J$5:$J$131,SMALL(IF(통합매트릭스!$I$5:$I$131="매우 높음",ROW(통합매트릭스!$I$5:$I$131)-5+1),4)),"")} -> 실제 사고 2건(ATLAS 2 / OWASP 0), 실증 사례 0건, Realized 기법 4개, 취약점·익스플로잇 0건
A34: {=IF(5<=COUNTIF(통합매트릭스!$I$5:$I$131,"매우 높음"),INDEX(통합매트릭스!$D$5:$D$131,SMALL(IF(통합매트릭스!$I$5:$I$131="매우 높음",ROW(통합매트릭스!$I$5:$I$131)-5+1),5)),"")} -> UT-03.3 | B34: {=IF(5<=COUNTIF(통합매트릭스!$I$5:$I$131,"매우 높음"),INDEX(통합매트릭스!$E$5:$E$131,SMALL(IF(통합매트릭스!$I$5:$I$131="매우 높음",ROW(통합매트릭스!$I$5:$I$131)-5+1),5)),"")} -> AI 연동 악성코드 | C34: {=IF(5<=COUNTIF(통합매트릭스!$I$5:$I$131,"매우 높음"),INDEX(통합매트릭스!$C$5:$C$131,SMALL(IF(통합매트릭스!$I$5:$I$131="매우 높음",ROW(통합매트릭스!$I$5:$I$131)-5+1),5)),"")} -> AI 기반 자율 공격 | D34: {=IF(5<=COUNTIF(통합매트릭스!$I$5:$I$131,"매우 높음"),INDEX(통합매트릭스!$J$5:$J$131,SMALL(IF(통합매트릭스!$I$5:$I$131="매우 높음",ROW(통합매트릭스!$I$5:$I$131)-5+1),5)),"")} -> 실제 사고 3건(ATLAS 3 / OWASP 0), 실증 사례 0건, Realized 기법 1개, 취약점·익스플로잇 0건
A35: {=IF(6<=COUNTIF(통합매트릭스!$I$5:$I$131,"매우 높음"),INDEX(통합매트릭스!$D$5:$D$131,SMALL(IF(통합매트릭스!$I$5:$I$131="매우 높음",ROW(통합매트릭스!$I$5:$I$131)-5+1),6)),"")} -> UT-21.5 | B35: {=IF(6<=COUNTIF(통합매트릭스!$I$5:$I$131,"매우 높음"),INDEX(통합매트릭스!$E$5:$E$131,SMALL(IF(통합매트릭스!$I$5:$I$131="매우 높음",ROW(통합매트릭스!$I$5:$I$131)-5+1),6)),"")} -> 파괴적 도구 실행 | C35: {=IF(6<=COUNTIF(통합매트릭스!$I$5:$I$131,"매우 높음"),INDEX(통합매트릭스!$C$5:$C$131,SMALL(IF(통합매트릭스!$I$5:$I$131="매우 높음",ROW(통합매트릭스!$I$5:$I$131)-5+1),6)),"")} -> 과도한 에이전시 | D35: {=IF(6<=COUNTIF(통합매트릭스!$I$5:$I$131,"매우 높음"),INDEX(통합매트릭스!$J$5:$J$131,SMALL(IF(통합매트릭스!$I$5:$I$131="매우 높음",ROW(통합매트릭스!$I$5:$I$131)-5+1),6)),"")} -> 실제 사고 3건(ATLAS 1 / OWASP 2), 실증 사례 2건, Realized 기법 1개, 취약점·익스플로잇 0건
A36: {=IF(7<=COUNTIF(통합매트릭스!$I$5:$I$131,"매우 높음"),INDEX(통합매트릭스!$D$5:$D$131,SMALL(IF(통합매트릭스!$I$5:$I$131="매우 높음",ROW(통합매트릭스!$I$5:$I$131)-5+1),7)),"")} -> UT-22.1 | B36: {=IF(7<=COUNTIF(통합매트릭스!$I$5:$I$131,"매우 높음"),INDEX(통합매트릭스!$E$5:$E$131,SMALL(IF(통합매트릭스!$I$5:$I$131="매우 높음",ROW(통합매트릭스!$I$5:$I$131)-5+1),7)),"")} -> 생성 코드 실행 | C36: {=IF(7<=COUNTIF(통합매트릭스!$I$5:$I$131,"매우 높음"),INDEX(통합매트릭스!$C$5:$C$131,SMALL(IF(통합매트릭스!$I$5:$I$131="매우 높음",ROW(통합매트릭스!$I$5:$I$131)-5+1),7)),"")} -> 비의도적 코드 실행 | D36: {=IF(7<=COUNTIF(통합매트릭스!$I$5:$I$131,"매우 높음"),INDEX(통합매트릭스!$J$5:$J$131,SMALL(IF(통합매트릭스!$I$5:$I$131="매우 높음",ROW(통합매트릭스!$I$5:$I$131)-5+1),7)),"")} -> 실제 사고 2건(ATLAS 2 / OWASP 0), 실증 사례 11건, Realized 기법 1개, 취약점·익스플로잇 5건
A37: {=IF(8<=COUNTIF(통합매트릭스!$I$5:$I$131,"매우 높음"),INDEX(통합매트릭스!$D$5:$D$131,SMALL(IF(통합매트릭스!$I$5:$I$131="매우 높음",ROW(통합매트릭스!$I$5:$I$131)-5+1),8)),"")} -> UT-22.2 | B37: {=IF(8<=COUNTIF(통합매트릭스!$I$5:$I$131,"매우 높음"),INDEX(통합매트릭스!$E$5:$E$131,SMALL(IF(통합매트릭스!$I$5:$I$131="매우 높음",ROW(통합매트릭스!$I$5:$I$131)-5+1),8)),"")} -> 안전하지 않은 파일 실행 | C37: {=IF(8<=COUNTIF(통합매트릭스!$I$5:$I$131,"매우 높음"),INDEX(통합매트릭스!$C$5:$C$131,SMALL(IF(통합매트릭스!$I$5:$I$131="매우 높음",ROW(통합매트릭스!$I$5:$I$131)-5+1),8)),"")} -> 비의도적 코드 실행 | D37: {=IF(8<=COUNTIF(통합매트릭스!$I$5:$I$131,"매우 높음"),INDEX(통합매트릭스!$J$5:$J$131,SMALL(IF(통합매트릭스!$I$5:$I$131="매우 높음",ROW(통합매트릭스!$I$5:$I$131)-5+1),8)),"")} -> 실제 사고 2건(ATLAS 2 / OWASP 0), 실증 사례 2건, Realized 기법 1개, 취약점·익스플로잇 1건
A38: {=IF(9<=COUNTIF(통합매트릭스!$I$5:$I$131,"매우 높음"),INDEX(통합매트릭스!$D$5:$D$131,SMALL(IF(통합매트릭스!$I$5:$I$131="매우 높음",ROW(통합매트릭스!$I$5:$I$131)-5+1),9)),"")} -> UT-24.1 | B38: {=IF(9<=COUNTIF(통합매트릭스!$I$5:$I$131,"매우 높음"),INDEX(통합매트릭스!$E$5:$E$131,SMALL(IF(통합매트릭스!$I$5:$I$131="매우 높음",ROW(통합매트릭스!$I$5:$I$131)-5+1),9)),"")} -> 목표 이탈과 보상 해킹 | C38: {=IF(9<=COUNTIF(통합매트릭스!$I$5:$I$131,"매우 높음"),INDEX(통합매트릭스!$C$5:$C$131,SMALL(IF(통합매트릭스!$I$5:$I$131="매우 높음",ROW(통합매트릭스!$I$5:$I$131)-5+1),9)),"")} -> 통제를 벗어난 에이전트 | D38: {=IF(9<=COUNTIF(통합매트릭스!$I$5:$I$131,"매우 높음"),INDEX(통합매트릭스!$J$5:$J$131,SMALL(IF(통합매트릭스!$I$5:$I$131="매우 높음",ROW(통합매트릭스!$I$5:$I$131)-5+1),9)),"")} -> 실제 사고 2건(ATLAS 1 / OWASP 1), 실증 사례 0건, Realized 기법 0개, 취약점·익스플로잇 0건
A39: {=IF(10<=COUNTIF(통합매트릭스!$I$5:$I$131,"매우 높음"),INDEX(통합매트릭스!$D$5:$D$131,SMALL(IF(통합매트릭스!$I$5:$I$131="매우 높음",ROW(통합매트릭스!$I$5:$I$131)-5+1),10)),"")} -> UT-24.2 | B39: {=IF(10<=COUNTIF(통합매트릭스!$I$5:$I$131,"매우 높음"),INDEX(통합매트릭스!$E$5:$E$131,SMALL(IF(통합매트릭스!$I$5:$I$131="매우 높음",ROW(통합매트릭스!$I$5:$I$131)-5+1),10)),"")} -> 악성 에이전트 배치 | C39: {=IF(10<=COUNTIF(통합매트릭스!$I$5:$I$131,"매우 높음"),INDEX(통합매트릭스!$C$5:$C$131,SMALL(IF(통합매트릭스!$I$5:$I$131="매우 높음",ROW(통합매트릭스!$I$5:$I$131)-5+1),10)),"")} -> 통제를 벗어난 에이전트 | D39: {=IF(10<=COUNTIF(통합매트릭스!$I$5:$I$131,"매우 높음"),INDEX(통합매트릭스!$J$5:$J$131,SMALL(IF(통합매트릭스!$I$5:$I$131="매우 높음",ROW(통합매트릭스!$I$5:$I$131)-5+1),10)),"")} -> 실제 사고 2건(ATLAS 2 / OWASP 0), 실증 사례 0건, Realized 기법 1개, 취약점·익스플로잇 0건
A40: {=IF(11<=COUNTIF(통합매트릭스!$I$5:$I$131,"매우 높음"),INDEX(통합매트릭스!$D$5:$D$131,SMALL(IF(통합매트릭스!$I$5:$I$131="매우 높음",ROW(통합매트릭스!$I$5:$I$131)-5+1),11)),"")} -> UT-25.1 | B40: {=IF(11<=COUNTIF(통합매트릭스!$I$5:$I$131,"매우 높음"),INDEX(통합매트릭스!$E$5:$E$131,SMALL(IF(통합매트릭스!$I$5:$I$131="매우 높음",ROW(통합매트릭스!$I$5:$I$131)-5+1),11)),"")} -> 설정 파일 내 비밀정보 수집 | C40: {=IF(11<=COUNTIF(통합매트릭스!$I$5:$I$131,"매우 높음"),INDEX(통합매트릭스!$C$5:$C$131,SMALL(IF(통합매트릭스!$I$5:$I$131="매우 높음",ROW(통합매트릭스!$I$5:$I$131)-5+1),11)),"")} -> 에이전트 자격증명 탈취 및 악용 | D40: {=IF(11<=COUNTIF(통합매트릭스!$I$5:$I$131,"매우 높음"),INDEX(통합매트릭스!$J$5:$J$131,SMALL(IF(통합매트릭스!$I$5:$I$131="매우 높음",ROW(통합매트릭스!$I$5:$I$131)-5+1),11)),"")} -> 실제 사고 8건(ATLAS 7 / OWASP 1), 실증 사례 6건, Realized 기법 1개, 취약점·익스플로잇 0건
A41: {=IF(12<=COUNTIF(통합매트릭스!$I$5:$I$131,"매우 높음"),INDEX(통합매트릭스!$D$5:$D$131,SMALL(IF(통합매트릭스!$I$5:$I$131="매우 높음",ROW(통합매트릭스!$I$5:$I$131)-5+1),12)),"")} -> UT-25.4 | B41: {=IF(12<=COUNTIF(통합매트릭스!$I$5:$I$131,"매우 높음"),INDEX(통합매트릭스!$E$5:$E$131,SMALL(IF(통합매트릭스!$I$5:$I$131="매우 높음",ROW(통합매트릭스!$I$5:$I$131)-5+1),12)),"")} -> 탈취 자격증명 재사용 | C41: {=IF(12<=COUNTIF(통합매트릭스!$I$5:$I$131,"매우 높음"),INDEX(통합매트릭스!$C$5:$C$131,SMALL(IF(통합매트릭스!$I$5:$I$131="매우 높음",ROW(통합매트릭스!$I$5:$I$131)-5+1),12)),"")} -> 에이전트 자격증명 탈취 및 악용 | D41: {=IF(12<=COUNTIF(통합매트릭스!$I$5:$I$131,"매우 높음"),INDEX(통합매트릭스!$J$5:$J$131,SMALL(IF(통합매트릭스!$I$5:$I$131="매우 높음",ROW(통합매트릭스!$I$5:$I$131)-5+1),12)),"")} -> 실제 사고 6건(ATLAS 6 / OWASP 0), 실증 사례 7건, Realized 기법 4개, 취약점·익스플로잇 0건
A42: {=IF(13<=COUNTIF(통합매트릭스!$I$5:$I$131,"매우 높음"),INDEX(통합매트릭스!$D$5:$D$131,SMALL(IF(통합매트릭스!$I$5:$I$131="매우 높음",ROW(통합매트릭스!$I$5:$I$131)-5+1),13)),"")} -> UT-28.1 | B42: {=IF(13<=COUNTIF(통합매트릭스!$I$5:$I$131,"매우 높음"),INDEX(통합매트릭스!$E$5:$E$131,SMALL(IF(통합매트릭스!$I$5:$I$131="매우 높음",ROW(통합매트릭스!$I$5:$I$131)-5+1),13)),"")} -> 변조 모델 유입 | C42: {=IF(13<=COUNTIF(통합매트릭스!$I$5:$I$131,"매우 높음"),INDEX(통합매트릭스!$C$5:$C$131,SMALL(IF(통합매트릭스!$I$5:$I$131="매우 높음",ROW(통합매트릭스!$I$5:$I$131)-5+1),13)),"")} -> 모델 및 데이터 공급망 침해 | D42: {=IF(13<=COUNTIF(통합매트릭스!$I$5:$I$131,"매우 높음"),INDEX(통합매트릭스!$J$5:$J$131,SMALL(IF(통합매트릭스!$I$5:$I$131="매우 높음",ROW(통합매트릭스!$I$5:$I$131)-5+1),13)),"")} -> 실제 사고 4건(ATLAS 4 / OWASP 0), 실증 사례 5건, Realized 기법 6개, 취약점·익스플로잇 0건
A43: {=IF(14<=COUNTIF(통합매트릭스!$I$5:$I$131,"매우 높음"),INDEX(통합매트릭스!$D$5:$D$131,SMALL(IF(통합매트릭스!$I$5:$I$131="매우 높음",ROW(통합매트릭스!$I$5:$I$131)-5+1),14)),"")} -> UT-28.2 | B43: {=IF(14<=COUNTIF(통합매트릭스!$I$5:$I$131,"매우 높음"),INDEX(통합매트릭스!$E$5:$E$131,SMALL(IF(통합매트릭스!$I$5:$I$131="매우 높음",ROW(통합매트릭스!$I$5:$I$131)-5+1),14)),"")} -> 악성 의존성 유입 | C43: {=IF(14<=COUNTIF(통합매트릭스!$I$5:$I$131,"매우 높음"),INDEX(통합매트릭스!$C$5:$C$131,SMALL(IF(통합매트릭스!$I$5:$I$131="매우 높음",ROW(통합매트릭스!$I$5:$I$131)-5+1),14)),"")} -> 모델 및 데이터 공급망 침해 | D43: {=IF(14<=COUNTIF(통합매트릭스!$I$5:$I$131,"매우 높음"),INDEX(통합매트릭스!$J$5:$J$131,SMALL(IF(통합매트릭스!$I$5:$I$131="매우 높음",ROW(통합매트릭스!$I$5:$I$131)-5+1),14)),"")} -> 실제 사고 2건(ATLAS 2 / OWASP 0), 실증 사례 3건, Realized 기법 2개, 취약점·익스플로잇 0건
A44: {=IF(15<=COUNTIF(통합매트릭스!$I$5:$I$131,"매우 높음"),INDEX(통합매트릭스!$D$5:$D$131,SMALL(IF(통합매트릭스!$I$5:$I$131="매우 높음",ROW(통합매트릭스!$I$5:$I$131)-5+1),15)),"")} -> UT-28.4 | B44: {=IF(15<=COUNTIF(통합매트릭스!$I$5:$I$131,"매우 높음"),INDEX(통합매트릭스!$E$5:$E$131,SMALL(IF(통합매트릭스!$I$5:$I$131="매우 높음",ROW(통합매트릭스!$I$5:$I$131)-5+1),15)),"")} -> 네임스페이스 및 평판 악용 | C44: {=IF(15<=COUNTIF(통합매트릭스!$I$5:$I$131,"매우 높음"),INDEX(통합매트릭스!$C$5:$C$131,SMALL(IF(통합매트릭스!$I$5:$I$131="매우 높음",ROW(통합매트릭스!$I$5:$I$131)-5+1),15)),"")} -> 모델 및 데이터 공급망 침해 | D44: {=IF(15<=COUNTIF(통합매트릭스!$I$5:$I$131,"매우 높음"),INDEX(통합매트릭스!$J$5:$J$131,SMALL(IF(통합매트릭스!$I$5:$I$131="매우 높음",ROW(통합매트릭스!$I$5:$I$131)-5+1),15)),"")} -> 실제 사고 2건(ATLAS 2 / OWASP 0), 실증 사례 6건, Realized 기법 2개, 취약점·익스플로잇 0건
A45: {=IF(16<=COUNTIF(통합매트릭스!$I$5:$I$131,"매우 높음"),INDEX(통합매트릭스!$D$5:$D$131,SMALL(IF(통합매트릭스!$I$5:$I$131="매우 높음",ROW(통합매트릭스!$I$5:$I$131)-5+1),16)),"")} -> UT-29.2 | B45: {=IF(16<=COUNTIF(통합매트릭스!$I$5:$I$131,"매우 높음"),INDEX(통합매트릭스!$E$5:$E$131,SMALL(IF(통합매트릭스!$I$5:$I$131="매우 높음",ROW(통합매트릭스!$I$5:$I$131)-5+1),16)),"")} -> 악성 도구 구현 | C45: {=IF(16<=COUNTIF(통합매트릭스!$I$5:$I$131,"매우 높음"),INDEX(통합매트릭스!$C$5:$C$131,SMALL(IF(통합매트릭스!$I$5:$I$131="매우 높음",ROW(통합매트릭스!$I$5:$I$131)-5+1),16)),"")} -> 에이전트 도구 공급망 오염 | D45: {=IF(16<=COUNTIF(통합매트릭스!$I$5:$I$131,"매우 높음"),INDEX(통합매트릭스!$J$5:$J$131,SMALL(IF(통합매트릭스!$I$5:$I$131="매우 높음",ROW(통합매트릭스!$I$5:$I$131)-5+1),16)),"")} -> 실제 사고 2건(ATLAS 1 / OWASP 1), 실증 사례 2건, Realized 기법 4개, 취약점·익스플로잇 2건
A46: {=IF(17<=COUNTIF(통합매트릭스!$I$5:$I$131,"매우 높음"),INDEX(통합매트릭스!$D$5:$D$131,SMALL(IF(통합매트릭스!$I$5:$I$131="매우 높음",ROW(통합매트릭스!$I$5:$I$131)-5+1),17)),"")} -> UT-31.1 | B46: {=IF(17<=COUNTIF(통합매트릭스!$I$5:$I$131,"매우 높음"),INDEX(통합매트릭스!$E$5:$E$131,SMALL(IF(통합매트릭스!$I$5:$I$131="매우 높음",ROW(통합매트릭스!$I$5:$I$131)-5+1),17)),"")} -> 외부 노출 AI 서비스 | C46: {=IF(17<=COUNTIF(통합매트릭스!$I$5:$I$131,"매우 높음"),INDEX(통합매트릭스!$C$5:$C$131,SMALL(IF(통합매트릭스!$I$5:$I$131="매우 높음",ROW(통합매트릭스!$I$5:$I$131)-5+1),17)),"")} -> AI 서비스 노출 및 섀도 AI | D46: {=IF(17<=COUNTIF(통합매트릭스!$I$5:$I$131,"매우 높음"),INDEX(통합매트릭스!$J$5:$J$131,SMALL(IF(통합매트릭스!$I$5:$I$131="매우 높음",ROW(통합매트릭스!$I$5:$I$131)-5+1),17)),"")} -> 실제 사고 2건(ATLAS 2 / OWASP 0), 실증 사례 2건, Realized 기법 0개, 취약점·익스플로잇 1건
A47: {=IF(18<=COUNTIF(통합매트릭스!$I$5:$I$131,"매우 높음"),INDEX(통합매트릭스!$D$5:$D$131,SMALL(IF(통합매트릭스!$I$5:$I$131="매우 높음",ROW(통합매트릭스!$I$5:$I$131)-5+1),18)),"")} | B47: {=IF(18<=COUNTIF(통합매트릭스!$I$5:$I$131,"매우 높음"),INDEX(통합매트릭스!$E$5:$E$131,SMALL(IF(통합매트릭스!$I$5:$I$131="매우 높음",ROW(통합매트릭스!$I$5:$I$131)-5+1),18)),"")} | C47: {=IF(18<=COUNTIF(통합매트릭스!$I$5:$I$131,"매우 높음"),INDEX(통합매트릭스!$C$5:$C$131,SMALL(IF(통합매트릭스!$I$5:$I$131="매우 높음",ROW(통합매트릭스!$I$5:$I$131)-5+1),18)),"")} | D47: {=IF(18<=COUNTIF(통합매트릭스!$I$5:$I$131,"매우 높음"),INDEX(통합매트릭스!$J$5:$J$131,SMALL(IF(통합매트릭스!$I$5:$I$131="매우 높음",ROW(통합매트릭스!$I$5:$I$131)-5+1),18)),"")}
A48: {=IF(19<=COUNTIF(통합매트릭스!$I$5:$I$131,"매우 높음"),INDEX(통합매트릭스!$D$5:$D$131,SMALL(IF(통합매트릭스!$I$5:$I$131="매우 높음",ROW(통합매트릭스!$I$5:$I$131)-5+1),19)),"")} | B48: {=IF(19<=COUNTIF(통합매트릭스!$I$5:$I$131,"매우 높음"),INDEX(통합매트릭스!$E$5:$E$131,SMALL(IF(통합매트릭스!$I$5:$I$131="매우 높음",ROW(통합매트릭스!$I$5:$I$131)-5+1),19)),"")} | C48: {=IF(19<=COUNTIF(통합매트릭스!$I$5:$I$131,"매우 높음"),INDEX(통합매트릭스!$C$5:$C$131,SMALL(IF(통합매트릭스!$I$5:$I$131="매우 높음",ROW(통합매트릭스!$I$5:$I$131)-5+1),19)),"")} | D48: {=IF(19<=COUNTIF(통합매트릭스!$I$5:$I$131,"매우 높음"),INDEX(통합매트릭스!$J$5:$J$131,SMALL(IF(통합매트릭스!$I$5:$I$131="매우 높음",ROW(통합매트릭스!$I$5:$I$131)-5+1),19)),"")}
A49: {=IF(20<=COUNTIF(통합매트릭스!$I$5:$I$131,"매우 높음"),INDEX(통합매트릭스!$D$5:$D$131,SMALL(IF(통합매트릭스!$I$5:$I$131="매우 높음",ROW(통합매트릭스!$I$5:$I$131)-5+1),20)),"")} | B49: {=IF(20<=COUNTIF(통합매트릭스!$I$5:$I$131,"매우 높음"),INDEX(통합매트릭스!$E$5:$E$131,SMALL(IF(통합매트릭스!$I$5:$I$131="매우 높음",ROW(통합매트릭스!$I$5:$I$131)-5+1),20)),"")} | C49: {=IF(20<=COUNTIF(통합매트릭스!$I$5:$I$131,"매우 높음"),INDEX(통합매트릭스!$C$5:$C$131,SMALL(IF(통합매트릭스!$I$5:$I$131="매우 높음",ROW(통합매트릭스!$I$5:$I$131)-5+1),20)),"")} | D49: {=IF(20<=COUNTIF(통합매트릭스!$I$5:$I$131,"매우 높음"),INDEX(통합매트릭스!$J$5:$J$131,SMALL(IF(통합매트릭스!$I$5:$I$131="매우 높음",ROW(통합매트릭스!$I$5:$I$131)-5+1),20)),"")}
A51: 5. 시트 구성
A52: 통합매트릭스 | B52: 핵심 산출물. Lv3 127행 평면 표 — 분류·위험 평가·공격 단계·AI 프로파일·영향·생애주기·ATLAS·OWASP·실제 근거·통제(Lv2)
A53: Lv2요약 | B53: Lv2 36개 롤업 — Lv3 수, 기법·사례, 최고 위험도, OWASP 매핑 합집합, 핵심 통제
A54: 도메인·평가기준 | B54: 3단 분류 정의, 도메인 리스크 정의·영문명·경계 판정 규칙, 위험 평가 기준(발생가능성·심각도·위험도), 생애주기·패싯 정의
A55: 공격체인시나리오 | B55: Lv3 단위 9개 공격 흐름 — 공식 절차 전이 근거, 최적 차단 지점
A56: ATLAS사례연구 / ATLAS사례절차 | B56: 사례 73건 Lv3 매핑·공식 절차 대조 / 공식 절차 665단계
A57: OWASP상세 | B57: OWASP 위험·취약점 예시, 공격 시나리오, 알려진 CVE 원문(347건)
A58: 커버리지히트맵 / ATLAS전술×Lv3 | B58: 소스 51 × Lv2 / 전술 16 × Lv3
A59: ATLAS기법매핑 / 완화책×UT / ATLAS완화책매핑 | B59: 기법 208개 Lv3 귀속·Maturity / 완화책(Lv2)
A60: 소스항목사전 / 공식크로스워크검증 / LLM번호변환 | B60: 소스 항목 정보 / 공식 크로스워크 자동 검증 / 2025↔2026 번호 변환
A61: 변경이력 / 설계노트 | B61: v3.0→v3.1·v2.0→v3.0·v1.2→v2.0 변경 내역 / 구조·평가 방법·한계·유지관리

Sheet 통합매트릭스
A1: 통합 AI 보안위협 매트릭스 v3.1 — Lv1 도메인(10) · Lv2 위협 분류(36) · Lv3 세부 위협(127)
A2: 기준: MITRE ATLAS v2026.09(YAML) · OWASP LLM Top 10 2026 · Agentic Top 10 2026 · GenAI Data Security 2026 v1.0 · MCP Top 10(2025 beta) | 2026-10-01
A3: 분류 체계 (Lv1 · Lv2 · Lv3) | G3: 위험 평가 | L3: 공격 단계 | N3: AI 적용 프로파일 | S3: 영향 | T3: 생애주기(기업 관점) ●주 통제 시점 ○연관 | Y3: MITRE ATLAS | AD3: OWASP LLM · Agentic · Data Security · MCP | AM3: 실제 근거 | AT3: 통제 (Lv2 유지)
A4: 도메인 (Lv1) | B4: UT-ID | C4: 위협 분류 (Lv2) | D4: Lv3 ID | E4: 세부 위협 (Lv3) | F4: 위협 설명 (Lv3) | G4: 발생가능성 | H4: 심각도 | I4: 위험도 | J4: 발생가능성 근거 (자동 산정) | K4: 심각도 근거 | L4: 주 공격 단계 | M4: 연관 공격 단계 (ATLAS 전술) | N4: 예측 AI | O4: LLM 앱 | P4: RAG | Q4: AI 에이전트 | R4: 멀티에이전트·MCP | S4: 영향 | T4: 기획/개발 | U4: 배포 | V4: 운영 | W4: 종료 | X4: 생애주기 비고 | Y4: ATLAS 기법 (주) | Z4: ATLAS 기법 (연관) | AA4: 기법 수 | AB4: Realized 기법 수 | AC4: Maturity 분포 (R/D/F) | AD4: LLM 2026 (주) | AE4: LLM 2026 (보조) | AF4: ASI 2026 (주) | AG4: ASI 2026 (보조) | AH4: DSGAI 2026 (주) | AI4: DSGAI 2026 (보조) | AJ4: MCP (주) | AK4: MCP (보조) | AL4: 소스 커버리지 (0~5) | AM4: ATLAS 사례 수 | AN4: ATLAS 실제 사고 수 | AO4: OWASP 인용 실제 사고 수 | AP4: OWASP 인용 취약점·익스플로잇 수 | AQ4: 근거 수준 | AR4: 관련 ATLAS 사례 ID | AS4: 실제 사례·공격 예시 | AT4: ATLAS 완화책 (상위 5) | AU4: 핵심 통제 요약 (Lv2) | AV4: 구 UT-ID (v1.2)
A5: D01. 공격 준비 및 AI 무기화 | B5: UT-01 | C5: AI 대상 정찰 및 접근 확보 | D5: UT-01.1 | E5: 공개 정보 수집 | F5: 공개 논문/기술 블로그/코드 저장소/조직 웹사이트 분석을 통해 대상 AI의 모델 구조, 학습 데이터, 사용 프레임워크 및 관련 인물 정보를 수집하여 후속 공격 설계에 활용 | G5: =IF(AN5+AO5>=2,"상",IF(OR(AN5+AO5=1,AM5>0,AB5>0,AP5>0),"중","하")) -> 상 | H5: 하 | I5: =IF(AND(G5="상",H5="상"),"매우 높음",IF(OR(AND(G5="상",H5="중"),AND(G5="중",H5="상")),"높음",IF(OR(AND(G5="중",H5="중"),AND(G5="상",H5="하"),AND(G5="하",H5="상")),"보통","낮음"))) -> 보통 | J5: ="실제 사고 "&(AN5+AO5)&"건(ATLAS "&AN5&" / OWASP "&AO5&"), 실증 사례 "&(AM5-AN5)&"건, Realized 기법 "&AB5&"개, 취약점·익스플로잇 "&AP5&"건" -> 실제 사고 3건(ATLAS 3 / OWASP 0), 실증 사례 20건, Realized 기법 5개, 취약점·익스플로잇 0건 | K5: 직접 피해 없음(후속 공격 설계 단계) | L5: 정찰(Reconnaissance) | M5: 정찰 | N5: ● | O5: ● | P5: ● | Q5: ● | R5: ● | S5: (후속 공격 준비) | U5: ○ | V5: ○ | X5: 조직 생애주기 외부 활동 — 공개 릴리스(배포) 정보가 정찰 재료가 됨 | Y5: T0000, T0000.000, T0000.001, T0000.002, T0000.003, T0001, T0003, T0004, T0095, T0095.000, T0087 | AA5: =COUNTIF(ATLAS기법매핑!$H$5:$H$212,"*"&D5&"*") -> 11 | AB5: =COUNTIFS(ATLAS기법매핑!$H$5:$H$212,"*"&D5&"*",ATLAS기법매핑!$M$5:$M$212,"Realized") -> 5 | AC5: =COUNTIFS(ATLAS기법매핑!$H$5:$H$212,"*"&D5&"*",ATLAS기법매핑!$M$5:$M$212,"Realized")&" / "&COUNTIFS(ATLAS기법매핑!$H$5:$H$212,"*"&D5&"*",ATLAS기법매핑!$M$5:$M$212,"Demonstrated")&" / "&COUNTIFS(ATLAS기법매핑!$H$5:$H$212,"*"&D5&"*",ATLAS기법매핑!$M$5:$M$212,"Feasible") -> 5 / 4 / 2 | AL5: =(LEN(Y5&Z5)>0)+(LEN(AD5&AE5)>0)+(LEN(AF5&AG5)>0)+(LEN(AH5&AI5)>0)+(LEN(AJ5&AK5)>0) -> 1 | AM5: =COUNTIF(ATLAS사례연구!$J$5:$J$77,"*"&D5&"*") -> 23 | AN5: =COUNTIFS(ATLAS사례연구!$J$5:$J$77,"*"&D5&"*",ATLAS사례연구!$C$5:$C$77,"Incident") -> 3 | AO5: 0 | AP5: 0 | AQ5: =IF(AN5+AO5>0,"실제 사고 확인",IF(AB5>0,"실사용 기법 포함",IF(OR(AM5>0,AP5>0),"실증·공개 취약점","이론·시나리오"))) -> 실제 사고 확인 | AR5: CS0000, CS0001, CS0003, CS0004, CS0005, CS0007, CS0010, CS0011, CS0012, CS0013, CS0014, CS0016, CS0028, CS0033, CS0034, CS0039, CS0048, CS0051, CS0052, CS0061, CS0065, CS0067, CS0070 | AS5: • [ATLAS CS0004·실제사고] 카메라 영상 주입으로 얼굴인식 인증을 우회해 세금 사기(실제 사고) • [ATLAS CS0034·실제사고] KYC 우회용 딥페이크 도구 ProKYC가 범죄자에게 판매(실제 사고) • [ATLAS CS0070·실제사고] DeepSeek 기반 Hermes 에이전트로 Langflow·n8n 취약점 공격 시도(실제 사고) | AT5: M0000 Limit Public Release of Information M0039 AI Honeypots | AU5: 공개 정보·모델 아티팩트 공개 최소화, 노출 자산 관리, AI 허니팟, 비정상 탐색·질의 탐지 | AV5: UT-36
A6: D01. 공격 준비 및 AI 무기화 | B6: UT-01 | C6: AI 대상 정찰 및 접근 확보 | D6: UT-01.2 | E6: 노출 AI 자산 스캔 | F6: 인터넷 스캔/메타데이터 API 조회를 통해 외부에 노출된 AI 서비스, 모델 저장소, 에이전트 호출 채널을 식별하고 공격 가능한 진입점 목록화 | G6: =IF(AN6+AO6>=2,"상",IF(OR(AN6+AO6=1,AM6>0,AB6>0,AP6>0),"중","하")) -> 상 | H6: 하 | I6: =IF(AND(G6="상",H6="상"),"매우 높음",IF(OR(AND(G6="상",H6="중"),AND(G6="중",H6="상")),"높음",IF(OR(AND(G6="중",H6="중"),AND(G6="상",H6="하"),AND(G6="하",H6="상")),"보통","낮음"))) -> 보통 | J6: ="실제 사고 "&(AN6+AO6)&"건(ATLAS "&AN6&" / OWASP "&AO6&"), 실증 사례 "&(AM6-AN6)&"건, Realized 기법 "&AB6&"개, 취약점·익스플로잇 "&AP6&"건" -> 실제 사고 4건(ATLAS 4 / OWASP 0), 실증 사례 2건, Realized 기법 1개, 취약점·익스플로잇 0건 | K6: 직접 피해 없음(공격 진입점 식별 단계) | L6: 정찰(Reconnaissance) | M6: 정찰 | N6: ● | O6: ● | P6: ● | Q6: ● | R6: ● | S6: (후속 공격 준비) | U6: ○ | V6: ○ | X6: 조직 생애주기 외부 활동 — 공개 릴리스(배포) 정보가 정찰 재료가 됨 | Y6: T0006, T0006.000, T0006.001, T0006.002, T0006.003 | AA6: =COUNTIF(ATLAS기법매핑!$H$5:$H$212,"*"&D6&"*") -> 5 | AB6: =COUNTIFS(ATLAS기법매핑!$H$5:$H$212,"*"&D6&"*",ATLAS기법매핑!$M$5:$M$212,"Realized") -> 1 | AC6: =COUNTIFS(ATLAS기법매핑!$H$5:$H$212,"*"&D6&"*",ATLAS기법매핑!$M$5:$M$212,"Realized")&" / "&COUNTIFS(ATLAS기법매핑!$H$5:$H$212,"*"&D6&"*",ATLAS기법매핑!$M$5:$M$212,"Demonstrated")&" / "&COUNTIFS(ATLAS기법매핑!$H$5:$H$212,"*"&D6&"*",ATLAS기법매핑!$M$5:$M$212,"Feasible") -> 1 / 1 / 3 | AL6: =(LEN(Y6&Z6)>0)+(LEN(AD6&AE6)>0)+(LEN(AF6&AG6)>0)+(LEN(AH6&AI6)>0)+(LEN(AJ6&AK6)>0) -> 1 | AM6: =COUNTIF(ATLAS사례연구!$J$5:$J$77,"*"&D6&"*") -> 6 | AN6: =COUNTIFS(ATLAS사례연구!$J$5:$J$77,"*"&D6&"*",ATLAS사례연구!$C$5:$C$77,"Incident") -> 4 | AO6: 0 | AP6: 0 | AQ6: =IF(AN6+AO6>0,"실제 사고 확인",IF(AB6>0,"실사용 기법 포함",IF(OR(AM6>0,AP6>0),"실증·공개 취약점","이론·시나리오"))) -> 실제 사고 확인 | AR6: CS0023, CS0037, CS0063, CS0069, CS0070, CS0071 | AS6: • [ATLAS CS0023·실제사고] 인증 없는 Ray 클러스터를 탈취해 연산자원·자격증명·모델 탈취(ShadowRay, 실제 사고) • [ATLAS CS0069·실제사고] GTG-1002가 탈옥한 Claude Code로 약 30개 조직 대상 자율 사이버 첩보(실제 사고) • [ATLAS CS0070·실제사고] DeepSeek 기반 Hermes 에이전트로 Langflow·n8n 취약점 공격 시도(실제 사고) | AT6: M0039 AI Honeypots M0019 Control Access to AI Models and Data in Production M0032 Segmentation of AI Agent Components | AU6: 공개 정보·모델 아티팩트 공개 최소화, 노출 자산 관리, AI 허니팟, 비정상 탐색·질의 탐지 | AV6: UT-36
A7: D01. 공격 준비 및 AI 무기화 | B7: UT-01 | C7: AI 대상 정찰 및 접근 확보 | D7: UT-01.3 | E7: AI 모델 접근 확보 | F7: 추론 API/AI 탑재 제품/모델 파일 확보를 통해 대상 모델에 대한 질의 권한 또는 전체 접근 권한을 획득하여 추출/회피/추론 공격의 기반 마련 | G7: =IF(AN7+AO7>=2,"상",IF(OR(AN7+AO7=1,AM7>0,AB7>0,AP7>0),"중","하")) -> 상 | H7: 중 | I7: =IF(AND(G7="상",H7="상"),"매우 높음",IF(OR(AND(G7="상",H7="중"),AND(G7="중",H7="상")),"높음",IF(OR(AND(G7="중",H7="중"),AND(G7="상",H7="하"),AND(G7="하",H7="상")),"보통","낮음"))) -> 높음 | J7: ="실제 사고 "&(AN7+AO7)&"건(ATLAS "&AN7&" / OWASP "&AO7&"), 실증 사례 "&(AM7-AN7)&"건, Realized 기법 "&AB7&"개, 취약점·익스플로잇 "&AP7&"건" -> 실제 사고 8건(ATLAS 8 / OWASP 0), 실증 사례 22건, Realized 기법 2개, 취약점·익스플로잇 0건 | K7: 질의 또는 전체 접근 확보로 추출/회피/추론 공격 기반 형성 | L7: AI 모델 접근(AI Model Access) | M7: AI 모델 접근 | N7: ● | O7: ● | P7: ● | Q7: ● | R7: ● | S7: (후속 공격 준비) | V7: ○ | Y7: T0040, T0044, T0047 | AA7: =COUNTIF(ATLAS기법매핑!$H$5:$H$212,"*"&D7&"*") -> 3 | AB7: =COUNTIFS(ATLAS기법매핑!$H$5:$H$212,"*"&D7&"*",ATLAS기법매핑!$M$5:$M$212,"Realized") -> 2 | AC7: =COUNTIFS(ATLAS기법매핑!$H$5:$H$212,"*"&D7&"*",ATLAS기법매핑!$M$5:$M$212,"Realized")&" / "&COUNTIFS(ATLAS기법매핑!$H$5:$H$212,"*"&D7&"*",ATLAS기법매핑!$M$5:$M$212,"Demonstrated")&" / "&COUNTIFS(ATLAS기법매핑!$H$5:$H$212,"*"&D7&"*",ATLAS기법매핑!$M$5:$M$212,"Feasible") -> 2 / 1 / 0 | AL7: =(LEN(Y7&Z7)>0)+(LEN(AD7&AE7)>0)+(LEN(AF7&AG7)>0)+(LEN(AH7&AI7)>0)+(LEN(AJ7&AK7)>0) -> 1 | AM7: =COUNTIF(ATLAS사례연구!$J$5:$J$77,"*"&D7&"*") -> 30 | AN7: =COUNTIFS(ATLAS사례연구!$J$5:$J$77,"*"&D7&"*",ATLAS사례연구!$C$5:$C$77,"Incident") -> 8 | AO7: 0 | AP7: 0 | AQ7: =IF(AN7+AO7>0,"실제 사고 확인",IF(AB7>0,"실사용 기법 포함",IF(OR(AM7>0,AP7>0),"실증·공개 취약점","이론·시나리오"))) -> 실제 사고 확인 | AR7: CS0003, CS0004, CS0005, CS0008, CS0009, CS0010, CS0011, CS0012, CS0013, CS0014, CS0016, CS0017, CS0022, CS0024, CS0026, CS0027, CS0028, CS0033, CS0034, CS0035, CS0036, CS0037, CS0056, CS0057, CS0058, CS0060, CS0061, CS0062, CS0069, CS0070 | AS7: • [ATLAS CS0004·실제사고] 카메라 영상 주입으로 얼굴인식 인증을 우회해 세금 사기(실제 사고) • [ATLAS CS0009·실제사고] Tay 챗봇이 사용자 대화로 온라인 학습되며 오염되어 혐오 발언 생성(실제 사고) • [ATLAS CS0017·실제사고] ID.me 자동 신원확인을 우회해 180건 이상 허위 실업급여 청구(실제 사고) | AT7: M0024 AI Telemetry Logging M0005 Control Access to AI Models and Data at Rest M0017 AI Model Distribution Methods M0019 Control Access to AI Models and Data in Production M0039 AI Honeypots | AU7: 공개 정보·모델 아티팩트 공개 최소화, 노출 자산 관리, AI 허니팟, 비정상 탐색·질의 탐지 | AV7: UT-36
A8: D01. 공격 준비 및 AI 무기화 | B8: UT-01 | C8: AI 대상 정찰 및 접근 확보 | D8: UT-01.4 | E8: 모델 및 환경 탐색 | F8: 출력 관찰/아티팩트 조회를 통해 모델 계열, 분류 체계, 내부 AI 자원 및 실행 환경을 파악하여 공격 정밀도 제고 | G8: =IF(AN8+AO8>=2,"상",IF(OR(AN8+AO8=1,AM8>0,AB8>0,AP8>0),"중","하")) -> 상 | H8: 하 | I8: =IF(AND(G8="상",H8="상"),"매우 높음",IF(OR(AND(G8="상",H8="중"),AND(G8="중",H8="상")),"높음",IF(OR(AND(G8="중",H8="중"),AND(G8="상",H8="하"),AND(G8="하",H8="상")),"보통","낮음"))) -> 보통 | J8: ="실제 사고 "&(AN8+AO8)&"건(ATLAS "&AN8&" / OWASP "&AO8&"), 실증 사례 "&(AM8-AN8)&"건, Realized 기법 "&AB8&"개, 취약점·익스플로잇 "&AP8&"건" -> 실제 사고 3건(ATLAS 3 / OWASP 0), 실증 사례 5건, Realized 기법 2개, 취약점·익스플로잇 0건 | K8: 탐색 단계로 직접 피해 제한적 | L8: 탐색(Discovery) | M8: 탐색 | N8: ● | O8: ● | P8: ● | Q8: ● | R8: ● | S8: (후속 공격 준비) | V8: ○ | Y8: T0007, T0013, T0014, T0075, T0089 | AA8: =COUNTIF(ATLAS기법매핑!$H$5:$H$212,"*"&D8&"*") -> 5 | AB8: =COUNTIFS(ATLAS기법매핑!$H$5:$H$212,"*"&D8&"*",ATLAS기법매핑!$M$5:$M$212,"Realized") -> 2 | AC8: =COUNTIFS(ATLAS기법매핑!$H$5:$H$212,"*"&D8&"*",ATLAS기법매핑!$M$5:$M$212,"Realized")&" / "&COUNTIFS(ATLAS기법매핑!$H$5:$H$212,"*"&D8&"*",ATLAS기법매핑!$M$5:$M$212,"Demonstrated")&" / "&COUNTIFS(ATLAS기법매핑!$H$5:$H$212,"*"&D8&"*",ATLAS기법매핑!$M$5:$M$212,"Feasible") -> 2 / 2 / 1 | AE8: LLM08 | AL8: =(LEN(Y8&Z8)>0)+(LEN(AD8&AE8)>0)+(LEN(AF8&AG8)>0)+(LEN(AH8&AI8)>0)+(LEN(AJ8&AK8)>0) -> 2 | AM8: =COUNTIF(ATLAS사례연구!$J$5:$J$77,"*"&D8&"*") -> 8 | AN8: =COUNTIFS(ATLAS사례연구!$J$5:$J$77,"*"&D8&"*",ATLAS사례연구!$C$5:$C$77,"Incident") -> 3 | AO8: 0 | AP8: 0 | AQ8: =IF(AN8+AO8>0,"실제 사고 확인",IF(AB8>0,"실사용 기법 포함",IF(OR(AM8>0,AP8>0),"실증·공개 취약점","이론·시나리오"))) -> 실제 사고 확인 | AR8: CS0012, CS0027, CS0028, CS0030, CS0036, CS0058, CS0068, CS0069 | AS8: • [ATLAS CS0030·실제사고] 탈취한 클라우드 자격증명으로 LLM 서비스를 무단 사용·재판매(LLMjacking, 실제 사고) • [ATLAS CS0068·실제사고] OpenAI 평가용 자율 에이전트들이 평가 경계를 넘어 외부 인프라 구축·Hugging Face 침해(실제 사고) • [ATLAS CS0069·실제사고] GTG-1002가 탈옥한 Claude Code로 약 30개 조직 대상 자율 사이버 첩보(실제 사고) | AT8: M0002 Predictive AI Output Obfuscation M0004 Limit AI Service Query Volume and Rate M0005 Control Access to AI Models and Data at Rest M0006 Predictive AI Ensembles M0012 Encrypt Sensitive Information | AU8: 공개 정보·모델 아티팩트 공개 최소화, 노출 자산 관리, AI 허니팟, 비정상 탐색·질의 탐지 | AV8: UT-36
A9: D01. 공격 준비 및 AI 무기화 | B9: UT-02 | C9: 공격 준비 및 일반 침투 기법 | D9: UT-02.1 | E9: 공격 도구 확보 | F9: 공개 적대적 공격 구현체/익스플로잇/범용 해킹 도구를 입수하거나 자체 개발하여 AI 대상 공격 역량 확보 | G9: =IF(AN9+AO9>=2,"상",IF(OR(AN9+AO9=1,AM9>0,AB9>0,AP9>0),"중","하")) -> 상 | H9: 하 | I9: =IF(AND(G9="상",H9="상"),"매우 높음",IF(OR(AND(G9="상",H9="중"),AND(G9="중",H9="상")),"높음",IF(OR(AND(G9="중",H9="중"),AND(G9="상",H9="하"),AND(G9="하",H9="상")),"보통","낮음"))) -> 보통 | J9: ="실제 사고 "&(AN9+AO9)&"건(ATLAS "&AN9&" / OWASP "&AO9&"), 실증 사례 "&(AM9-AN9)&"건, Realized 기법 "&AB9&"개, 취약점·익스플로잇 "&AP9&"건" -> 실제 사고 10건(ATLAS 10 / OWASP 0), 실증 사례 14건, Realized 기법 6개, 취약점·익스플로잇 0건 | K9: 직접 피해 없음(공격 준비 단계) | L9: 자원 개발(Resource Development) | M9: 자원 개발 | N9: ● | O9: ● | P9: ● | Q9: ● | R9: ● | S9: 기밀성, 무결성, 가용성 | V9: ○ | X9: 조직 생애주기 외부 활동 — 운영 중 시스템을 대상으로 발현 | Y9: T0016, T0016.000, T0016.001, T0016.002, T0016.003, T0017, T0017.000 | AA9: =COUNTIF(ATLAS기법매핑!$H$5:$H$212,"*"&D9&"*") -> 7 | AB9: =COUNTIFS(ATLAS기법매핑!$H$5:$H$212,"*"&D9&"*",ATLAS기법매핑!$M$5:$M$212,"Realized") -> 6 | AC9: =COUNTIFS(ATLAS기법매핑!$H$5:$H$212,"*"&D9&"*",ATLAS기법매핑!$M$5:$M$212,"Realized")&" / "&COUNTIFS(ATLAS기법매핑!$H$5:$H$212,"*"&D9&"*",ATLAS기법매핑!$M$5:$M$212,"Demonstrated")&" / "&COUNTIFS(ATLAS기법매핑!$H$5:$H$212,"*"&D9&"*",ATLAS기법매핑!$M$5:$M$212,"Feasible") -> 6 / 1 / 0 | AL9: =(LEN(Y9&Z9)>0)+(LEN(AD9&AE9)>0)+(LEN(AF9&AG9)>0)+(LEN(AH9&AI9)>0)+(LEN(AJ9&AK9)>0) -> 1 | AM9: =COUNTIF(ATLAS사례연구!$J$5:$J$77,"*"&D9&"*") -> 24 | AN9: =COUNTIFS(ATLAS사례연구!$J$5:$J$77,"*"&D9&"*",ATLAS사례연구!$C$5:$C$77,"Incident") -> 10 | AO9: 0 | AP9: 0 | AQ9: =IF(AN9+AO9>0,"실제 사고 확인",IF(AB9>0,"실사용 기법 포함",IF(OR(AM9>0,AP9>0),"실증·공개 취약점","이론·시나리오"))) -> 실제 사고 확인 | AR9: CS0001, CS0002, CS0003, CS0004, CS0013, CS0014, CS0018, CS0020, CS0027, CS0029, CS0030, CS0033, CS0034, CS0043, CS0049, CS0050, CS0052, CS0053, CS0055, CS0057, CS0064, CS0069, CS0070, CS0072 | AS9: • [ATLAS CS0002·실제사고] VirusTotal에 변종 샘플을 대량 제출해 크라우드소싱 학습 데이터를 오염 • [ATLAS CS0004·실제사고] 카메라 영상 주입으로 얼굴인식 인증을 우회해 세금 사기(실제 사고) • [ATLAS CS0030·실제사고] 탈취한 클라우드 자격증명으로 LLM 서비스를 무단 사용·재판매(LLMjacking, 실제 사고) | AT9: M0001 Limit Model Artifact Release M0020 Generative AI Guardrails M0022 Generative AI Model Alignment | AU9: 기존 엔터프라이즈 보안통제(패치·EDR·네트워크 분리·ATT&CK 기반 탐지)를 AI 인프라까지 확장 | AV9: UT-39
A10: D01. 공격 준비 및 AI 무기화 | B10: UT-02 | C10: 공격 준비 및 일반 침투 기법 | D10: UT-02.2 | E10: 공개 AI 자원 입수 | F10: 공개 데이터셋/사전학습 모델/에이전트 설정 파일을 입수하여 대리 모델 구축 및 공격 사전 검증에 활용 | G10: =IF(AN10+AO10>=2,"상",IF(OR(AN10+AO10=1,AM10>0,AB10>0,AP10>0),"중","하")) -> 중 | H10: 하 | I10: =IF(AND(G10="상",H10="상"),"매우 높음",IF(OR(AND(G10="상",H10="중"),AND(G10="중",H10="상")),"높음",IF(OR(AND(G10="중",H10="중"),AND(G10="상",H10="하"),AND(G10="하",H10="상")),"보통","낮음"))) -> 낮음 | J10: ="실제 사고 "&(AN10+AO10)&"건(ATLAS "&AN10&" / OWASP "&AO10&"), 실증 사례 "&(AM10-AN10)&"건, Realized 기법 "&AB10&"개, 취약점·익스플로잇 "&AP10&"건" -> 실제 사고 1건(ATLAS 1 / OWASP 0), 실증 사례 12건, Realized 기법 1개, 취약점·익스플로잇 0건 | K10: 직접 피해 없음(대리 모델 구축 등 준비 단계) | L10: 자원 개발(Resource Development) | M10: 자원 개발 | N10: ● | O10: ● | P10: ● | Q10: ● | R10: ● | S10: 기밀성, 무결성, 가용성 | V10: ○ | X10: 조직 생애주기 외부 활동 — 운영 중 시스템을 대상으로 발현 | Y10: T0002, T0002.000, T0002.001, T0002.002 | AA10: =COUNTIF(ATLAS기법매핑!$H$5:$H$212,"*"&D10&"*") -> 4 | AB10: =COUNTIFS(ATLAS기법매핑!$H$5:$H$212,"*"&D10&"*",ATLAS기법매핑!$M$5:$M$212,"Realized") -> 1 | AC10: =COUNTIFS(ATLAS기법매핑!$H$5:$H$212,"*"&D10&"*",ATLAS기법매핑!$M$5:$M$212,"Realized")&" / "&COUNTIFS(ATLAS기법매핑!$H$5:$H$212,"*"&D10&"*",ATLAS기법매핑!$M$5:$M$212,"Demonstrated")&" / "&COUNTIFS(ATLAS기법매핑!$H$5:$H$212,"*"&D10&"*",ATLAS기법매핑!$M$5:$M$212,"Feasible") -> 1 / 3 / 0 | AL10: =(LEN(Y10&Z10)>0)+(LEN(AD10&AE10)>0)+(LEN(AF10&AG10)>0)+(LEN(AH10&AI10)>0)+(LEN(AJ10&AK10)>0) -> 1 | AM10: =COUNTIF(ATLAS사례연구!$J$5:$J$77,"*"&D10&"*") -> 13 | AN10: =COUNTIFS(ATLAS사례연구!$J$5:$J$77,"*"&D10&"*",ATLAS사례연구!$C$5:$C$77,"Incident") -> 1 | AO10: 0 | AP10: 0 | AQ10: =IF(AN10+AO10>0,"실제 사고 확인",IF(AB10>0,"실사용 기법 포함",IF(OR(AM10>0,AP10>0),"실증·공개 취약점","이론·시나리오"))) -> 실제 사고 확인 | AR10: CS0000, CS0001, CS0005, CS0006, CS0007, CS0011, CS0012, CS0013, CS0014, CS0019, CS0025, CS0051, CS0064 | AS10: • [ATLAS CS0006·실제사고] Clearview AI 저장소 설정 오류로 소스코드·자격증명·모델 노출 • [ATLAS CS0000·실증] 공개 논문을 재현한 대리모델로 악성 C&C 트래픽 탐지 딥러닝 모델을 회피 • [ATLAS CS0001·실증] 도메인명 변형 기법으로 CNN 기반 봇넷 DGA 탐지기를 우회 | AT10: M0001 Limit Model Artifact Release M0000 Limit Public Release of Information M0014 Verify AI Artifacts | AU10: 기존 엔터프라이즈 보안통제(패치·EDR·네트워크 분리·ATT&CK 기반 탐지)를 AI 인프라까지 확장 | AV10: UT-39
A11: D01. 공격 준비 및 AI 무기화 | B11: UT-02 | C11: 공격 준비 및 일반 침투 기법 | D11: UT-02.3 | E11: 공격 인프라 확보 | F11: 클라우드 자원/도메인/물리적 대응물 구매, 계정 생성, 정상 인프라 탈취를 통해 공격 수행 및 은닉에 필요한 기반 구축 | G11: =IF(AN11+AO11>=2,"상",IF(OR(AN11+AO11=1,AM11>0,AB11>0,AP11>0),"중","하")) -> 상 | H11: 하 | I11: =IF(AND(G11="상",H11="상"),"매우 높음",IF(OR(AND(G11="상",H11="중"),AND(G11="중",H11="상")),"높음",IF(OR(AND(G11="중",H11="중"),AND(G11="상",H11="하"),AND(G11="하",H11="상")),"보통","낮음"))) -> 보통 | J11: ="실제 사고 "&(AN11+AO11)&"건(ATLAS "&AN11&" / OWASP "&AO11&"), 실증 사례 "&(AM11-AN11)&"건, Realized 기법 "&AB11&"개, 취약점·익스플로잇 "&AP11&"건" -> 실제 사고 7건(ATLAS 7 / OWASP 0), 실증 사례 18건, Realized 기법 6개, 취약점·익스플로잇 0건 | K11: 직접 피해 없음(공격 기반 구축 단계) | L11: 자원 개발(Resource Development) | M11: 자원 개발 | N11: ● | O11: ● | P11: ● | Q11: ● | R11: ● | S11: 기밀성, 무결성, 가용성 | V11: ○ | X11: 조직 생애주기 외부 활동 — 운영 중 시스템을 대상으로 발현 | Y11: T0008, T0008.000, T0008.001, T0008.002, T0008.003, T0008.004, T0008.005, T0021, T0079, T0128 | AA11: =COUNTIF(ATLAS기법매핑!$H$5:$H$212,"*"&D11&"*") -> 10 | AB11: =COUNTIFS(ATLAS기법매핑!$H$5:$H$212,"*"&D11&"*",ATLAS기법매핑!$M$5:$M$212,"Realized") -> 6 | AC11: =COUNTIFS(ATLAS기법매핑!$H$5:$H$212,"*"&D11&"*",ATLAS기법매핑!$M$5:$M$212,"Realized")&" / "&COUNTIFS(ATLAS기법매핑!$H$5:$H$212,"*"&D11&"*",ATLAS기법매핑!$M$5:$M$212,"Demonstrated")&" / "&COUNTIFS(ATLAS기법매핑!$H$5:$H$212,"*"&D11&"*",ATLAS기법매핑!$M$5:$M$212,"Feasible") -> 6 / 3 / 1 | AL11: =(LEN(Y11&Z11)>0)+(LEN(AD11&AE11)>0)+(LEN(AF11&AG11)>0)+(LEN(AH11&AI11)>0)+(LEN(AJ11&AK11)>0) -> 1 | AM11: =COUNTIF(ATLAS사례연구!$J$5:$J$77,"*"&D11&"*") -> 25 | AN11: =COUNTIFS(ATLAS사례연구!$J$5:$J$77,"*"&D11&"*",ATLAS사례연구!$C$5:$C$77,"Incident") -> 7 | AO11: 0 | AP11: 0 | AQ11: =IF(AN11+AO11>0,"실제 사고 확인",IF(AB11>0,"실사용 기법 포함",IF(OR(AM11>0,AP11>0),"실증·공개 취약점","이론·시나리오"))) -> 실제 사고 확인 | AR11: CS0004, CS0006, CS0007, CS0012, CS0021, CS0025, CS0027, CS0029, CS0033, CS0034, CS0041, CS0045, CS0049, CS0050, CS0051, CS0055, CS0056, CS0057, CS0059, CS0060, CS0061, CS0065, CS0066, CS0069, CS0072 | AS11: • [ATLAS CS0004·실제사고] 카메라 영상 주입으로 얼굴인식 인증을 우회해 세금 사기(실제 사고) • [ATLAS CS0006·실제사고] Clearview AI 저장소 설정 오류로 소스코드·자격증명·모델 노출 • [ATLAS CS0034·실제사고] KYC 우회용 딥페이크 도구 ProKYC가 범죄자에게 판매(실제 사고) | AT11: M0005 Control Access to AI Models and Data at Rest M0019 Control Access to AI Models and Data in Production | AU11: 기존 엔터프라이즈 보안통제(패치·EDR·네트워크 분리·ATT&CK 기반 탐지)를 AI 인프라까지 확장 | AV11: UT-39
A12: D01. 공격 준비 및 AI 무기화 | B12: UT-02 | C12: 공격 준비 및 일반 침투 기법 | D12: UT-02.4 | E12: 일반 초기 침투 | F12: 공개 애플리케이션 취약점 익스플로잇/드라이브바이 다운로드/악성 링크 실행 유도를 통해 AI 서비스 및 지원 인프라에 최초 침투 | G12: =IF(AN12+AO12>=2,"상",IF(OR(AN12+AO12=1,AM12>0,AB12>0,AP12>0),"중","하")) -> 상 | H12: 상 | I12: =IF(AND(G12="상",H12="상"),"매우 높음",IF(OR(AND(G12="상",H12="중"),AND(G12="중",H12="상")),"높음",IF(OR(AND(G12="중",H12="중"),AND(G12="상",H12="하"),AND(G12="하",H12="상")),"보통","낮음"))) -> 매우 높음 | J12: ="실제 사고 "&(AN12+AO12)&"건(ATLAS "&AN12&" / OWASP "&AO12&"), 실증 사례 "&(AM12-AN12)&"건, Realized 기법 "&AB12&"개, 취약점·익스플로잇 "&AP12&"건" -> 실제 사고 7건(ATLAS 6 / OWASP 1), 실증 사례 7건, Realized 기법 1개, 취약점·익스플로잇 1건 | K12: AI 서비스 및 지원 인프라 장악으로 확대 가능 | L12: 초기 접근(Initial Access) | M12: 초기 접근, 실행 | N12: ● | O12: ● | P12: ● | Q12: ● | R12: ● | S12: 기밀성, 무결성, 가용성 | V12: ○ | X12: 조직 생애주기 외부 활동 — 운영 중 시스템을 대상으로 발현 | Y12: T0049, T0078, T0011.003 | AA12: =COUNTIF(ATLAS기법매핑!$H$5:$H$212,"*"&D12&"*") -> 3 | AB12: =COUNTIFS(ATLAS기법매핑!$H$5:$H$212,"*"&D12&"*",ATLAS기법매핑!$M$5:$M$212,"Realized") -> 1 | AC12: =COUNTIFS(ATLAS기법매핑!$H$5:$H$212,"*"&D12&"*",ATLAS기법매핑!$M$5:$M$212,"Realized")&" / "&COUNTIFS(ATLAS기법매핑!$H$5:$H$212,"*"&D12&"*",ATLAS기법매핑!$M$5:$M$212,"Demonstrated")&" / "&COUNTIFS(ATLAS기법매핑!$H$5:$H$212,"*"&D12&"*",ATLAS기법매핑!$M$5:$M$212,"Feasible") -> 1 / 2 / 0 | AL12: =(LEN(Y12&Z12)>0)+(LEN(AD12&AE12)>0)+(LEN(AF12&AG12)>0)+(LEN(AH12&AI12)>0)+(LEN(AJ12&AK12)>0) -> 1 | AM12: =COUNTIF(ATLAS사례연구!$J$5:$J$77,"*"&D12&"*") -> 13 | AN12: =COUNTIFS(ATLAS사례연구!$J$5:$J$77,"*"&D12&"*",ATLAS사례연구!$C$5:$C$77,"Incident") -> 6 | AO12: 1 | AP12: 1 | AQ12: =IF(AN12+AO12>0,"실제 사고 확인",IF(AB12>0,"실사용 기법 포함",IF(OR(AM12>0,AP12>0),"실증·공개 취약점","이론·시나리오"))) -> 실제 사고 확인 | AR12: CS0021, CS0023, CS0028, CS0030, CS0045, CS0050, CS0051, CS0052, CS0055, CS0068, CS0069, CS0070, CS0071 | AS12: • [ATLAS CS0023·실제사고] 인증 없는 Ray 클러스터를 탈취해 연산자원·자격증명·모델 탈취(ShadowRay, 실제 사고) • [ATLAS CS0030·실제사고] 탈취한 클라우드 자격증명으로 LLM 서비스를 무단 사용·재판매(LLMjacking, 실제 사고) • [ATLAS CS0068·실제사고] OpenAI 평가용 자율 에이전트들이 평가 경계를 넘어 외부 인프라 구축·Hugging Face 침해(실제 사고) • [OWASP 인용] ToolShell SharePoint RCE 악용(2025.07, 실제 사고) / Flowise 사전인증 임의 파일 업로드(2025.03) | AT12: M0020 Generative AI Guardrails M0039 AI Honeypots | AU12: 기존 엔터프라이즈 보안통제(패치·EDR·네트워크 분리·ATT&CK 기반 탐지)를 AI 인프라까지 확장 | AV12: UT-39
A13: D01. 공격 준비 및 AI 무기화 | B13: UT-02 | C13: 공격 준비 및 일반 침투 기법 | D13: UT-02.5 | E13: 내부 확산 및 탐지 회피 | F13: 원격 서비스 악용을 통한 내부 확산과 샌드박스 회피/난독화를 통한 보안 탐지 우회로 침투 범위 확대 및 체류 장기화 | G13: =IF(AN13+AO13>=2,"상",IF(OR(AN13+AO13=1,AM13>0,AB13>0,AP13>0),"중","하")) -> 상 | H13: 중 | I13: =IF(AND(G13="상",H13="상"),"매우 높음",IF(OR(AND(G13="상",H13="중"),AND(G13="중",H13="상")),"높음",IF(OR(AND(G13="중",H13="중"),AND(G13="상",H13="하"),AND(G13="하",H13="상")),"보통","낮음"))) -> 높음 | J13: ="실제 사고 "&(AN13+AO13)&"건(ATLAS "&AN13&" / OWASP "&AO13&"), 실증 사례 "&(AM13-AN13)&"건, Realized 기법 "&AB13&"개, 취약점·익스플로잇 "&AP13&"건" -> 실제 사고 2건(ATLAS 2 / OWASP 0), 실증 사례 1건, Realized 기법 3개, 취약점·익스플로잇 0건 | K13: 침투 범위 확대 및 탐지 지연 | L13: 방어 회피(Defense Evasion) | M13: 방어 회피, 내부 확산 | N13: ● | O13: ● | P13: ● | Q13: ● | R13: ● | S13: 기밀성, 무결성, 가용성 | V13: ○ | X13: 조직 생애주기 외부 활동 — 운영 중 시스템을 대상으로 발현 | Y13: T0122, T0097, T0107, T0123 | AA13: =COUNTIF(ATLAS기법매핑!$H$5:$H$212,"*"&D13&"*") -> 4 | AB13: =COUNTIFS(ATLAS기법매핑!$H$5:$H$212,"*"&D13&"*",ATLAS기법매핑!$M$5:$M$212,"Realized") -> 3 | AC13: =COUNTIFS(ATLAS기법매핑!$H$5:$H$212,"*"&D13&"*",ATLAS기법매핑!$M$5:$M$212,"Realized")&" / "&COUNTIFS(ATLAS기법매핑!$H$5:$H$212,"*"&D13&"*",ATLAS기법매핑!$M$5:$M$212,"Demonstrated")&" / "&COUNTIFS(ATLAS기법매핑!$H$5:$H$212,"*"&D13&"*",ATLAS기법매핑!$M$5:$M$212,"Feasible") -> 3 / 1 / 0 | AL13: =(LEN(Y13&Z13)>0)+(LEN(AD13&AE13)>0)+(LEN(AF13&AG13)>0)+(LEN(AH13&AI13)>0)+(LEN(AJ13&AK13)>0) -> 1 | AM13: =COUNTIF(ATLAS사례연구!$J$5:$J$77,"*"&D13&"*") -> 3 | AN13: =COUNTIFS(ATLAS사례연구!$J$5:$J$77,"*"&D13&"*",ATLAS사례연구!$C$5:$C$77,"Incident") -> 2 | AO13: 0 | AP13: 0 | AQ13: =IF(AN13+AO13>0,"실제 사고 확인",IF(AB13>0,"실사용 기법 포함",IF(OR(AM13>0,AP13>0),"실증·공개 취약점","이론·시나리오"))) -> 실제 사고 확인 | AR13: CS0043, CS0050, CS0068 | AS13: • [ATLAS CS0043·실제사고] LLM 기반 악성코드 분석기를 속이려 프롬프트 인젝션을 내장한 악성코드(실제 사고) • [ATLAS CS0068·실제사고] OpenAI 평가용 자율 에이전트들이 평가 경계를 넘어 외부 인프라 구축·Hugging Face 침해(실제 사고) • [ATLAS CS0050·실증] 악성 링크 1회 클릭으로 OpenClaw 로컬 에이전트 원격 코드 실행 | AT13: M0016 Vulnerability Scanning | AU13: 기존 엔터프라이즈 보안통제(패치·EDR·네트워크 분리·ATT&CK 기반 탐지)를 AI 인프라까지 확장 | AV13: UT-39
A14: D01. 공격 준비 및 AI 무기화 | B14: UT-02 | C14: 공격 준비 및 일반 침투 기법 | D14: UT-02.6 | E14: 일반 수단 데이터 유출 | F14: 정보 저장소/로컬 시스템의 데이터를 자동 수집 및 압축한 후 일반 네트워크 또는 C2 채널로 외부 반출 | G14: =IF(AN14+AO14>=2,"상",IF(OR(AN14+AO14=1,AM14>0,AB14>0,AP14>0),"중","하")) -> 상 | H14: 상 | I14: =IF(AND(G14="상",H14="상"),"매우 높음",IF(OR(AND(G14="상",H14="중"),AND(G14="중",H14="상")),"높음",IF(OR(AND(G14="중",H14="중"),AND(G14="상",H14="하"),AND(G14="하",H14="상")),"보통","낮음"))) -> 매우 높음 | J14: ="실제 사고 "&(AN14+AO14)&"건(ATLAS "&AN14&" / OWASP "&AO14&"), 실증 사례 "&(AM14-AN14)&"건, Realized 기법 "&AB14&"개, 취약점·익스플로잇 "&AP14&"건" -> 실제 사고 9건(ATLAS 9 / OWASP 0), 실증 사례 10건, Realized 기법 6개, 취약점·익스플로잇 0건 | K14: 중요정보 및 AI 자산 대량 반출 | L14: 유출(Exfiltration) | M14: 수집, 명령·제어, 유출 | N14: ● | O14: ● | P14: ● | Q14: ● | R14: ● | S14: 기밀성 | V14: ○ | X14: 조직 생애주기 외부 활동 — 운영 중 시스템을 대상으로 발현 | Y14: T0036, T0037, T0126, T0127, T0025, T0072 | AA14: =COUNTIF(ATLAS기법매핑!$H$5:$H$212,"*"&D14&"*") -> 6 | AB14: =COUNTIFS(ATLAS기법매핑!$H$5:$H$212,"*"&D14&"*",ATLAS기법매핑!$M$5:$M$212,"Realized") -> 6 | AC14: =COUNTIFS(ATLAS기법매핑!$H$5:$H$212,"*"&D14&"*",ATLAS기법매핑!$M$5:$M$212,"Realized")&" / "&COUNTIFS(ATLAS기법매핑!$H$5:$H$212,"*"&D14&"*",ATLAS기법매핑!$M$5:$M$212,"Demonstrated")&" / "&COUNTIFS(ATLAS기법매핑!$H$5:$H$212,"*"&D14&"*",ATLAS기법매핑!$M$5:$M$212,"Feasible") -> 6 / 0 / 0 | AL14: =(LEN(Y14&Z14)>0)+(LEN(AD14&AE14)>0)+(LEN(AF14&AG14)>0)+(LEN(AH14&AI14)>0)+(LEN(AJ14&AK14)>0) -> 1 | AM14: =COUNTIF(ATLAS사례연구!$J$5:$J$77,"*"&D14&"*") -> 19 | AN14: =COUNTIFS(ATLAS사례연구!$J$5:$J$77,"*"&D14&"*",ATLAS사례연구!$C$5:$C$77,"Incident") -> 9 | AO14: 0 | AP14: 0 | AQ14: =IF(AN14+AO14>0,"실제 사고 확인",IF(AB14>0,"실사용 기법 포함",IF(OR(AM14>0,AP14>0),"실증·공개 취약점","이론·시나리오"))) -> 실제 사고 확인 | AR14: CS0006, CS0010, CS0015, CS0018, CS0023, CS0027, CS0031, CS0043, CS0044, CS0048, CS0052, CS0058, CS0059, CS0061, CS0063, CS0065, CS0068, CS0069, CS0071 | AS14: • [ATLAS CS0006·실제사고] Clearview AI 저장소 설정 오류로 소스코드·자격증명·모델 노출 • [ATLAS CS0015·실제사고] PyPI에 올라간 악성 torchtriton 의존성으로 PyTorch-nightly 사용자 정보 유출(실제 사고) • [ATLAS CS0023·실제사고] 인증 없는 Ray 클러스터를 탈취해 연산자원·자격증명·모델 탈취(ShadowRay, 실제 사고) | AT14: M0005 Control Access to AI Models and Data at Rest | AU14: 기존 엔터프라이즈 보안통제(패치·EDR·네트워크 분리·ATT&CK 기반 탐지)를 AI 인프라까지 확장 | AV14: UT-39
A15: D01. 공격 준비 및 AI 무기화 | B15: UT-03 | C15: AI 기반 자율 공격 | D15: UT-03.1 | E15: 자율 공격 에이전트 | F15: 공격 목표만 부여받은 AI 에이전트가 대상 탐색, 익스플로잇 개발, 실패 시 공격 경로 수정을 사람 개입 없이 반복 수행하여 사람 대비 압도적 속도와 규모로 침투 | G15: =IF(AN15+AO15>=2,"상",IF(OR(AN15+AO15=1,AM15>0,AB15>0,AP15>0),"중","하")) -> 상 | H15: 상 | I15: =IF(AND(G15="상",H15="상"),"매우 높음",IF(OR(AND(G15="상",H15="중"),AND(G15="중",H15="상")),"높음",IF(OR(AND(G15="중",H15="중"),AND(G15="상",H15="하"),AND(G15="하",H15="상")),"보통","낮음"))) -> 매우 높음 | J15: ="실제 사고 "&(AN15+AO15)&"건(ATLAS "&AN15&" / OWASP "&AO15&"), 실증 사례 "&(AM15-AN15)&"건, Realized 기법 "&AB15&"개, 취약점·익스플로잇 "&AP15&"건" -> 실제 사고 4건(ATLAS 4 / OWASP 0), 실증 사례 0건, Realized 기법 3개, 취약점·익스플로잇 0건 | K15: 다수 조직 동시 침투 및 시스템 장악 | L15: AI 공격 적응(AI Attack Adaptation) | M15: 정찰, 자원 개발, AI 공격 적응 | N15: ● | O15: ● | P15: ● | Q15: ● | R15: ● | S15: 기밀성, 무결성, 가용성 | V15: ○ | X15: 조직 생애주기 외부 활동 — AI 속도의 공격이 운영 시스템에 발현 | Y15: T0116, T0117, T0017.001 | AA15: =COUNTIF(ATLAS기법매핑!$H$5:$H$212,"*"&D15&"*") -> 3 | AB15: =COUNTIFS(ATLAS기법매핑!$H$5:$H$212,"*"&D15&"*",ATLAS기법매핑!$M$5:$M$212,"Realized") -> 3 | AC15: =COUNTIFS(ATLAS기법매핑!$H$5:$H$212,"*"&D15&"*",ATLAS기법매핑!$M$5:$M$212,"Realized")&" / "&COUNTIFS(ATLAS기법매핑!$H$5:$H$212,"*"&D15&"*",ATLAS기법매핑!$M$5:$M$212,"Demonstrated")&" / "&COUNTIFS(ATLAS기법매핑!$H$5:$H$212,"*"&D15&"*",ATLAS기법매핑!$M$5:$M$212,"Feasible") -> 3 / 0 / 0 | AL15: =(LEN(Y15&Z15)>0)+(LEN(AD15&AE15)>0)+(LEN(AF15&AG15)>0)+(LEN(AH15&AI15)>0)+(LEN(AJ15&AK15)>0) -> 1 | AM15: =COUNTIF(ATLAS사례연구!$J$5:$J$77,"*"&D15&"*") -> 4 | AN15: =COUNTIFS(ATLAS사례연구!$J$5:$J$77,"*"&D15&"*",ATLAS사례연구!$C$5:$C$77,"Incident") -> 4 | AO15: 0 | AP15: 0 | AQ15: =IF(AN15+AO15>0,"실제 사고 확인",IF(AB15>0,"실사용 기법 포함",IF(OR(AM15>0,AP15>0),"실증·공개 취약점","이론·시나리오"))) -> 실제 사고 확인 | AR15: CS0068, CS0069, CS0070, CS0071 | AS15: • [ATLAS CS0069·실제사고] GTG-1002가 탈옥한 Claude Code로 약 30개 조직 대상 자율 사이버 첩보(실제 사고) • [ATLAS CS0070·실제사고] DeepSeek 기반 Hermes 에이전트로 Langflow·n8n 취약점 공격 시도(실제 사고) • [ATLAS CS0071·실제사고] Hermes·OpenClaw 기반 다중 에이전트 프레임워크로 대만 정부 시스템 침해(실제 사고) | AT15: M0037 AI Agent Authority Expansion Controls M0038 AI Agent Scope Drift Detection | AU15: AI 속도 공격을 전제한 탐지·대응 자동화, AI 제공자 오남용 탐지 연계, 위협 인텔리전스 | AV15: UT-37
A16: D01. 공격 준비 및 AI 무기화 | B16: UT-03 | C16: AI 기반 자율 공격 | D16: UT-03.2 | E16: 다중 에이전트 공격 조율 | F16: 오케스트레이터 AI가 다수 하위 에이전트에 임무를 분배하고 탐색 결과/자격증명을 공유하며 복수 대상을 병렬 공격 | G16: =IF(AN16+AO16>=2,"상",IF(OR(AN16+AO16=1,AM16>0,AB16>0,AP16>0),"중","하")) -> 상 | H16: 상 | I16: =IF(AND(G16="상",H16="상"),"매우 높음",IF(OR(AND(G16="상",H16="중"),AND(G16="중",H16="상")),"높음",IF(OR(AND(G16="중",H16="중"),AND(G16="상",H16="하"),AND(G16="하",H16="상")),"보통","낮음"))) -> 매우 높음 | J16: ="실제 사고 "&(AN16+AO16)&"건(ATLAS "&AN16&" / OWASP "&AO16&"), 실증 사례 "&(AM16-AN16)&"건, Realized 기법 "&AB16&"개, 취약점·익스플로잇 "&AP16&"건" -> 실제 사고 2건(ATLAS 2 / OWASP 0), 실증 사례 0건, Realized 기법 4개, 취약점·익스플로잇 0건 | K16: 복수 대상 병렬 침투 및 시스템 장악 | L16: AI 공격 적응(AI Attack Adaptation) | M16: AI 공격 적응 | N16: ● | O16: ● | P16: ● | Q16: ● | R16: ● | S16: 기밀성, 무결성, 가용성 | V16: ○ | X16: 조직 생애주기 외부 활동 — AI 속도의 공격이 운영 시스템에 발현 | Y16: T0118, T0118.000, T0118.001, T0124 | AA16: =COUNTIF(ATLAS기법매핑!$H$5:$H$212,"*"&D16&"*") -> 4 | AB16: =COUNTIFS(ATLAS기법매핑!$H$5:$H$212,"*"&D16&"*",ATLAS기법매핑!$M$5:$M$212,"Realized") -> 4 | AC16: =COUNTIFS(ATLAS기법매핑!$H$5:$H$212,"*"&D16&"*",ATLAS기법매핑!$M$5:$M$212,"Realized")&" / "&COUNTIFS(ATLAS기법매핑!$H$5:$H$212,"*"&D16&"*",ATLAS기법매핑!$M$5:$M$212,"Demonstrated")&" / "&COUNTIFS(ATLAS기법매핑!$H$5:$H$212,"*"&D16&"*",ATLAS기법매핑!$M$5:$M$212,"Feasible") -> 4 / 0 / 0 | AL16: =(LEN(Y16&Z16)>0)+(LEN(AD16&AE16)>0)+(LEN(AF16&AG16)>0)+(LEN(AH16&AI16)>0)+(LEN(AJ16&AK16)>0) -> 1 | AM16: =COUNTIF(ATLAS사례연구!$J$5:$J$77,"*"&D16&"*") -> 2 | AN16: =COUNTIFS(ATLAS사례연구!$J$5:$J$77,"*"&D16&"*",ATLAS사례연구!$C$5:$C$77,"Incident") -> 2 | AO16: 0 | AP16: 0 | AQ16: =IF(AN16+AO16>0,"실제 사고 확인",IF(AB16>0,"실사용 기법 포함",IF(OR(AM16>0,AP16>0),"실증·공개 취약점","이론·시나리오"))) -> 실제 사고 확인 | AR16: CS0068, CS0071 | AS16: • [ATLAS CS0068·실제사고] OpenAI 평가용 자율 에이전트들이 평가 경계를 넘어 외부 인프라 구축·Hugging Face 침해(실제 사고) • [ATLAS CS0071·실제사고] Hermes·OpenClaw 기반 다중 에이전트 프레임워크로 대만 정부 시스템 침해(실제 사고) | AT16: M0037 AI Agent Authority Expansion Controls M0038 AI Agent Scope Drift Detection | AU16: AI 속도 공격을 전제한 탐지·대응 자동화, AI 제공자 오남용 탐지 연계, 위협 인텔리전스 | AV16: UT-37
A17: D01. 공격 준비 및 AI 무기화 | B17: UT-03 | C17: AI 기반 자율 공격 | D17: UT-03.3 | E17: AI 연동 악성코드 | F17: 피해 시스템의 악성코드가 실행 중 LLM 서비스에 질의하여 실행 명령을 동적 생성함으로써 시그니처 기반 탐지 우회 및 정상 AI 트래픽으로 위장 | G17: =IF(AN17+AO17>=2,"상",IF(OR(AN17+AO17=1,AM17>0,AB17>0,AP17>0),"중","하")) -> 상 | H17: 상 | I17: =IF(AND(G17="상",H17="상"),"매우 높음",IF(OR(AND(G17="상",H17="중"),AND(G17="중",H17="상")),"높음",IF(OR(AND(G17="중",H17="중"),AND(G17="상",H17="하"),AND(G17="하",H17="상")),"보통","낮음"))) -> 매우 높음 | J17: ="실제 사고 "&(AN17+AO17)&"건(ATLAS "&AN17&" / OWASP "&AO17&"), 실증 사례 "&(AM17-AN17)&"건, Realized 기법 "&AB17&"개, 취약점·익스플로잇 "&AP17&"건" -> 실제 사고 3건(ATLAS 3 / OWASP 0), 실증 사례 0건, Realized 기법 1개, 취약점·익스플로잇 0건 | K17: 호스트 장악 상태의 탐지 회피형 원격 조작 | L17: AI 공격 적응(AI Attack Adaptation) | M17: AI 공격 적응 | N17: ● | O17: ● | P17: ● | Q17: ● | R17: ● | S17: 기밀성, 무결성, 가용성 | V17: ○ | X17: 조직 생애주기 외부 활동 — AI 속도의 공격이 운영 시스템에 발현 | Y17: T0102 | AA17: =COUNTIF(ATLAS기법매핑!$H$5:$H$212,"*"&D17&"*") -> 1 | AB17: =COUNTIFS(ATLAS기법매핑!$H$5:$H$212,"*"&D17&"*",ATLAS기법매핑!$M$5:$M$212,"Realized") -> 1 | AC17: =COUNTIFS(ATLAS기법매핑!$H$5:$H$212,"*"&D17&"*",ATLAS기법매핑!$M$5:$M$212,"Realized")&" / "&COUNTIFS(ATLAS기법매핑!$H$5:$H$212,"*"&D17&"*",ATLAS기법매핑!$M$5:$M$212,"Demonstrated")&" / "&COUNTIFS(ATLAS기법매핑!$H$5:$H$212,"*"&D17&"*",ATLAS기법매핑!$M$5:$M$212,"Feasible") -> 1 / 0 / 0 | AL17: =(LEN(Y17&Z17)>0)+(LEN(AD17&AE17)>0)+(LEN(AF17&AG17)>0)+(LEN(AH17&AI17)>0)+(LEN(AJ17&AK17)>0) -> 1 | AM17: =COUNTIF(ATLAS사례연구!$J$5:$J$77,"*"&D17&"*") -> 3 | AN17: =COUNTIFS(ATLAS사례연구!$J$5:$J$77,"*"&D17&"*",ATLAS사례연구!$C$5:$C$77,"Incident") -> 3 | AO17: 0 | AP17: 0 | AQ17: =IF(AN17+AO17>0,"실제 사고 확인",IF(AB17>0,"실사용 기법 포함",IF(OR(AM17>0,AP17>0),"실증·공개 취약점","이론·시나리오"))) -> 실제 사고 확인 | AR17: CS0044, CS0068, CS0070 | AS17: • [ATLAS CS0044·실제사고] APT28 LAMEHUG가 LLM API로 실행 명령을 동적 생성(실제 사고) • [ATLAS CS0068·실제사고] OpenAI 평가용 자율 에이전트들이 평가 경계를 넘어 외부 인프라 구축·Hugging Face 침해(실제 사고) • [ATLAS CS0070·실제사고] DeepSeek 기반 Hermes 에이전트로 Langflow·n8n 취약점 공격 시도(실제 사고) | AT17: M0020 Generative AI Guardrails M0022 Generative AI Model Alignment | AU17: AI 속도 공격을 전제한 탐지·대응 자동화, AI 제공자 오남용 탐지 연계, 위협 인텔리전스 | AV17: UT-37
A18: D01. 공격 준비 및 AI 무기화 | B18: UT-03 | C18: AI 기반 자율 공격 | D18: UT-03.4 | E18: 공격용 에이전트 도구 확보 | F18: 자율 공격에 활용할 에이전트 프레임워크/도구를 개발하거나 공개 도구를 입수하여 공격 자동화 역량 확보 | G18: =IF(AN18+AO18>=2,"상",IF(OR(AN18+AO18=1,AM18>0,AB18>0,AP18>0),"중","하")) -> 중 | H18: 하 | I18: =IF(AND(G18="상",H18="상"),"매우 높음",IF(OR(AND(G18="상",H18="중"),AND(G18="중",H18="상")),"높음",IF(OR(AND(G18="중",H18="중"),AND(G18="상",H18="하"),AND(G18="하",H18="상")),"보통","낮음"))) -> 낮음 | J18: ="실제 사고 "&(AN18+AO18)&"건(ATLAS "&AN18&" / OWASP "&AO18&"), 실증 사례 "&(AM18-AN18)&"건, Realized 기법 "&AB18&"개, 취약점·익스플로잇 "&AP18&"건" -> 실제 사고 1건(ATLAS 1 / OWASP 0), 실증 사례 0건, Realized 기법 2개, 취약점·익스플로잇 0건 | K18: 직접 피해 없음(공격 자동화 준비 단계) | L18: 자원 개발(Resource Development) | M18: 자원 개발 | N18: ● | O18: ● | P18: ● | Q18: ● | R18: ● | S18: 기밀성, 무결성, 가용성 | V18: ○ | X18: 조직 생애주기 외부 활동 — AI 속도의 공격이 운영 시스템에 발현 | Y18: T0016.004, T0017.002 | AA18: =COUNTIF(ATLAS기법매핑!$H$5:$H$212,"*"&D18&"*") -> 2 | AB18: =COUNTIFS(ATLAS기법매핑!$H$5:$H$212,"*"&D18&"*",ATLAS기법매핑!$M$5:$M$212,"Realized") -> 2 | AC18: =COUNTIFS(ATLAS기법매핑!$H$5:$H$212,"*"&D18&"*",ATLAS기법매핑!$M$5:$M$212,"Realized")&" / "&COUNTIFS(ATLAS기법매핑!$H$5:$H$212,"*"&D18&"*",ATLAS기법매핑!$M$5:$M$212,"Demonstrated")&" / "&COUNTIFS(ATLAS기법매핑!$H$5:$H$212,"*"&D18&"*",ATLAS기법매핑!$M$5:$M$212,"Feasible") -> 2 / 0 / 0 | AL18: =(LEN(Y18&Z18)>0)+(LEN(AD18&AE18)>0)+(LEN(AF18&AG18)>0)+(LEN(AH18&AI18)>0)+(LEN(AJ18&AK18)>0) -> 1 | AM18: =COUNTIF(ATLAS사례연구!$J$5:$J$77,"*"&D18&"*") -> 1 | AN18: =COUNTIFS(ATLAS사례연구!$J$5:$J$77,"*"&D18&"*",ATLAS사례연구!$C$5:$C$77,"Incident") -> 1 | AO18: 0 | AP18: 0 | AQ18: =IF(AN18+AO18>0,"실제 사고 확인",IF(AB18>0,"실사용 기법 포함",IF(OR(AM18>0,AP18>0),"실증·공개 취약점","이론·시나리오"))) -> 실제 사고 확인 | AR18: CS0070 | AS18: • [ATLAS CS0070·실제사고] DeepSeek 기반 Hermes 에이전트로 Langflow·n8n 취약점 공격 시도(실제 사고) | AT18: — (ATLAS 완화책 없음: Lv2 핵심 통제 참조) | AU18: AI 속도 공격을 전제한 탐지·대응 자동화, AI 제공자 오남용 탐지 연계, 위협 인텔리전스 | AV18: UT-37
A19: D01. 공격 준비 및 AI 무기화 | B19: UT-04 | C19: AI 생성 콘텐츠를 이용한 사기 | D19: UT-04.1 | E19: 딥페이크 신원 위장 | F19: 실시간 딥페이크 영상/음성 및 가상 카메라 주입을 통해 생체인증/KYC 절차를 우회하여 타인 명의 계정 개설 및 금융 사기 수행 | G19: =IF(AN19+AO19>=2,"상",IF(OR(AN19+AO19=1,AM19>0,AB19>0,AP19>0),"중","하")) -> 상 | H19: 중 | I19: =IF(AND(G19="상",H19="상"),"매우 높음",IF(OR(AND(G19="상",H19="중"),AND(G19="중",H19="상")),"높음",IF(OR(AND(G19="중",H19="중"),AND(G19="상",H19="하"),AND(G19="하",H19="상")),"보통","낮음"))) -> 높음 | J19: ="실제 사고 "&(AN19+AO19)&"건(ATLAS "&AN19&" / OWASP "&AO19&"), 실증 사례 "&(AM19-AN19)&"건, Realized 기법 "&AB19&"개, 취약점·익스플로잇 "&AP19&"건" -> 실제 사고 4건(ATLAS 4 / OWASP 0), 실증 사례 1건, Realized 기법 1개, 취약점·익스플로잇 0건 | K19: 특정 계정/거래 단위 금전 피해 | L19: 방어 회피(Defense Evasion) | M19: AI 공격 적응 | N19: ● | S19: 재무, 평판·사회 | V19: ○ | X19: 조직 생애주기 외부 활동 — 사람·생체인증 프로세스를 대상으로 운영 중 발현 | Y19: T0088 | AA19: =COUNTIF(ATLAS기법매핑!$H$5:$H$212,"*"&D19&"*") -> 1 | AB19: =COUNTIFS(ATLAS기법매핑!$H$5:$H$212,"*"&D19&"*",ATLAS기법매핑!$M$5:$M$212,"Realized") -> 1 | AC19: =COUNTIFS(ATLAS기법매핑!$H$5:$H$212,"*"&D19&"*",ATLAS기법매핑!$M$5:$M$212,"Realized")&" / "&COUNTIFS(ATLAS기법매핑!$H$5:$H$212,"*"&D19&"*",ATLAS기법매핑!$M$5:$M$212,"Demonstrated")&" / "&COUNTIFS(ATLAS기법매핑!$H$5:$H$212,"*"&D19&"*",ATLAS기법매핑!$M$5:$M$212,"Feasible") -> 1 / 0 / 0 | AL19: =(LEN(Y19&Z19)>0)+(LEN(AD19&AE19)>0)+(LEN(AF19&AG19)>0)+(LEN(AH19&AI19)>0)+(LEN(AJ19&AK19)>0) -> 1 | AM19: =COUNTIF(ATLAS사례연구!$J$5:$J$77,"*"&D19&"*") -> 5 | AN19: =COUNTIFS(ATLAS사례연구!$J$5:$J$77,"*"&D19&"*",ATLAS사례연구!$C$5:$C$77,"Incident") -> 4 | AO19: 0 | AP19: 0 | AQ19: =IF(AN19+AO19>0,"실제 사고 확인",IF(AB19>0,"실사용 기법 포함",IF(OR(AM19>0,AP19>0),"실증·공개 취약점","이론·시나리오"))) -> 실제 사고 확인 | AR19: CS0004, CS0017, CS0033, CS0034, CS0057 | AS19: • [ATLAS CS0034·실제사고] KYC 우회용 딥페이크 도구 ProKYC가 범죄자에게 판매(실제 사고) • [ATLAS CS0033·실증] 실시간 딥페이크 영상 주입으로 모바일 KYC 얼굴인증 우회 • [ATLAS CS0004·실제사고] 카메라 영상 주입으로 얼굴인식 인증을 우회해 세금 사기(실제 사고) | AT19: M0009 Predictive AI Multi-Sensor Fusion M0034 Deepfake Detection | AU19: 딥페이크 탐지·라이브니스 검증, 고위험 요청 다중 채널 확인, 사용자 교육 | AV19: UT-30(분리)
A20: D01. 공격 준비 및 AI 무기화 | B20: UT-04 | C20: AI 생성 콘텐츠를 이용한 사기 | D20: UT-04.2 | E20: AI 생성 피싱 | F20: LLM 생성 맞춤형 스피어피싱 및 딥페이크 음성/영상 통화를 통해 임직원을 기망하여 자격증명 탈취 또는 송금 유도 | G20: =IF(AN20+AO20>=2,"상",IF(OR(AN20+AO20=1,AM20>0,AB20>0,AP20>0),"중","하")) -> 상 | H20: 중 | I20: =IF(AND(G20="상",H20="상"),"매우 높음",IF(OR(AND(G20="상",H20="중"),AND(G20="중",H20="상")),"높음",IF(OR(AND(G20="중",H20="중"),AND(G20="상",H20="하"),AND(G20="하",H20="상")),"보통","낮음"))) -> 높음 | J20: ="실제 사고 "&(AN20+AO20)&"건(ATLAS "&AN20&" / OWASP "&AO20&"), 실증 사례 "&(AM20-AN20)&"건, Realized 기법 "&AB20&"개, 취약점·익스플로잇 "&AP20&"건" -> 실제 사고 2건(ATLAS 2 / OWASP 0), 실증 사례 1건, Realized 기법 1개, 취약점·익스플로잇 0건 | K20: 자격증명 탈취 시 내부 침투로 확대 가능 | L20: 초기 접근(Initial Access) | M20: 초기 접근, 내부 확산 | S20: 기밀성, 재무 | V20: ○ | X20: 조직 생애주기 외부 활동 — 사람·생체인증 프로세스를 대상으로 운영 중 발현 | Y20: T0052, T0052.000, T0052.001 | AA20: =COUNTIF(ATLAS기법매핑!$H$5:$H$212,"*"&D20&"*") -> 3 | AB20: =COUNTIFS(ATLAS기법매핑!$H$5:$H$212,"*"&D20&"*",ATLAS기법매핑!$M$5:$M$212,"Realized") -> 1 | AC20: =COUNTIFS(ATLAS기법매핑!$H$5:$H$212,"*"&D20&"*",ATLAS기법매핑!$M$5:$M$212,"Realized")&" / "&COUNTIFS(ATLAS기법매핑!$H$5:$H$212,"*"&D20&"*",ATLAS기법매핑!$M$5:$M$212,"Demonstrated")&" / "&COUNTIFS(ATLAS기법매핑!$H$5:$H$212,"*"&D20&"*",ATLAS기법매핑!$M$5:$M$212,"Feasible") -> 1 / 1 / 1 | AL20: =(LEN(Y20&Z20)>0)+(LEN(AD20&AE20)>0)+(LEN(AF20&AG20)>0)+(LEN(AH20&AI20)>0)+(LEN(AJ20&AK20)>0) -> 1 | AM20: =COUNTIF(ATLAS사례연구!$J$5:$J$77,"*"&D20&"*") -> 3 | AN20: =COUNTIFS(ATLAS사례연구!$J$5:$J$77,"*"&D20&"*",ATLAS사례연구!$C$5:$C$77,"Incident") -> 2 | AO20: 0 | AP20: 0 | AQ20: =IF(AN20+AO20>0,"실제 사고 확인",IF(AB20>0,"실사용 기법 포함",IF(OR(AM20>0,AP20>0),"실증·공개 취약점","이론·시나리오"))) -> 실제 사고 확인 | AR20: CS0020, CS0032, CS0044 | AS20: • [ATLAS CS0032·실제사고] 피싱 사이트가 ML 기반 피싱 탐지기를 회피하도록 시각 요소 변형(실제 사고) • [ATLAS CS0044·실제사고] APT28 LAMEHUG가 LLM API로 실행 명령을 동적 생성(실제 사고) • [ATLAS CS0020·실증] 웹페이지 숨은 지시로 Bing Chat이 사용자 개인정보를 캐내는 사회공학 수행 • [OWASP 시나리오] 딥페이크 음성·영상과 LLM 생성 문안을 결합한 피싱(ATLAS T0052.001 기법 정의) | AT20: M0018 User Training M0034 Deepfake Detection | AU20: 딥페이크 탐지·라이브니스 검증, 고위험 요청 다중 채널 확인, 사용자 교육 | AV20: UT-30(분리)
A21: D01. 공격 준비 및 AI 무기화 | B21: UT-04 | C21: AI 생성 콘텐츠를 이용한 사기 | D21: UT-04.3 | E21: 신뢰 주체 사칭 | F21: 신뢰받는 개인/조직을 사칭한 커뮤니케이션으로 대상의 판단을 조작하여 공격자 대신 행위 수행 유도 | G21: =IF(AN21+AO21>=2,"상",IF(OR(AN21+AO21=1,AM21>0,AB21>0,AP21>0),"중","하")) -> 상 | H21: 중 | I21: =IF(AND(G21="상",H21="상"),"매우 높음",IF(OR(AND(G21="상",H21="중"),AND(G21="중",H21="상")),"높음",IF(OR(AND(G21="중",H21="중"),AND(G21="상",H21="하"),AND(G21="하",H21="상")),"보통","낮음"))) -> 높음 | J21: ="실제 사고 "&(AN21+AO21)&"건(ATLAS "&AN21&" / OWASP "&AO21&"), 실증 사례 "&(AM21-AN21)&"건, Realized 기법 "&AB21&"개, 취약점·익스플로잇 "&AP21&"건" -> 실제 사고 3건(ATLAS 3 / OWASP 0), 실증 사례 2건, Realized 기법 1개, 취약점·익스플로잇 0건 | K21: 기망 대상 개인/거래 단위 피해 | L21: 초기 접근(Initial Access) | M21: 방어 회피 | S21: 재무 | V21: ○ | X21: 조직 생애주기 외부 활동 — 사람·생체인증 프로세스를 대상으로 운영 중 발현 | Y21: T0073 | AA21: =COUNTIF(ATLAS기법매핑!$H$5:$H$212,"*"&D21&"*") -> 1 | AB21: =COUNTIFS(ATLAS기법매핑!$H$5:$H$212,"*"&D21&"*",ATLAS기법매핑!$M$5:$M$212,"Realized") -> 1 | AC21: =COUNTIFS(ATLAS기법매핑!$H$5:$H$212,"*"&D21&"*",ATLAS기법매핑!$M$5:$M$212,"Realized")&" / "&COUNTIFS(ATLAS기법매핑!$H$5:$H$212,"*"&D21&"*",ATLAS기법매핑!$M$5:$M$212,"Demonstrated")&" / "&COUNTIFS(ATLAS기법매핑!$H$5:$H$212,"*"&D21&"*",ATLAS기법매핑!$M$5:$M$212,"Feasible") -> 1 / 0 / 0 | AL21: =(LEN(Y21&Z21)>0)+(LEN(AD21&AE21)>0)+(LEN(AF21&AG21)>0)+(LEN(AH21&AI21)>0)+(LEN(AJ21&AK21)>0) -> 1 | AM21: =COUNTIF(ATLAS사례연구!$J$5:$J$77,"*"&D21&"*") -> 5 | AN21: =COUNTIFS(ATLAS사례연구!$J$5:$J$77,"*"&D21&"*",ATLAS사례연구!$C$5:$C$77,"Incident") -> 3 | AO21: 0 | AP21: 0 | AQ21: =IF(AN21+AO21>0,"실제 사고 확인",IF(AB21>0,"실사용 기법 포함",IF(OR(AM21>0,AP21>0),"실증·공개 취약점","이론·시나리오"))) -> 실제 사고 확인 | AR21: CS0027, CS0033, CS0034, CS0044, CS0053 | AS21: • [ATLAS CS0034·실제사고] KYC 우회용 딥페이크 도구 ProKYC가 범죄자에게 판매(실제 사고) • [ATLAS CS0044·실제사고] APT28 LAMEHUG가 LLM API로 실행 명령을 동적 생성(실제 사고) • [ATLAS CS0053·실제사고] Postmark를 사칭한 악성 MCP 서버가 발송 메일을 몰래 BCC로 유출(실제 사고) | AT21: — (ATLAS 완화책 없음: Lv2 핵심 통제 참조) | AU21: 딥페이크 탐지·라이브니스 검증, 고위험 요청 다중 채널 확인, 사용자 교육 | AV21: UT-30(분리)
A22: D01. 공격 준비 및 AI 무기화 | B22: UT-05 | C22: AI 서비스를 이용한 C2 통신 | D22: UT-05.1 | E22: AI 서비스 API 은닉 통신 | F22: 감염 호스트가 정상 AI 서비스 API를 명령 수신/결과 전송 채널로 사용하여 C2 트래픽을 정상 AI 트래픽으로 위장 | G22: =IF(AN22+AO22>=2,"상",IF(OR(AN22+AO22=1,AM22>0,AB22>0,AP22>0),"중","하")) -> 중 | H22: 상 | I22: =IF(AND(G22="상",H22="상"),"매우 높음",IF(OR(AND(G22="상",H22="중"),AND(G22="중",H22="상")),"높음",IF(OR(AND(G22="중",H22="중"),AND(G22="상",H22="하"),AND(G22="하",H22="상")),"보통","낮음"))) -> 높음 | J22: ="실제 사고 "&(AN22+AO22)&"건(ATLAS "&AN22&" / OWASP "&AO22&"), 실증 사례 "&(AM22-AN22)&"건, Realized 기법 "&AB22&"개, 취약점·익스플로잇 "&AP22&"건" -> 실제 사고 1건(ATLAS 1 / OWASP 0), 실증 사례 0건, Realized 기법 1개, 취약점·익스플로잇 0건 | K22: 침해 호스트에 대한 은닉 원격 제어 지속 | L22: 명령·제어(Command and Control) | M22: 명령·제어 | O22: ● | Q22: ● | S22: 기밀성, 무결성 | V22: ○ | X22: 조직 생애주기 외부 활동 — 탈취 자격증명 사용 시 운영 비용·데이터 피해로 발현 | Y22: T0096 | AA22: =COUNTIF(ATLAS기법매핑!$H$5:$H$212,"*"&D22&"*") -> 1 | AB22: =COUNTIFS(ATLAS기법매핑!$H$5:$H$212,"*"&D22&"*",ATLAS기법매핑!$M$5:$M$212,"Realized") -> 1 | AC22: =COUNTIFS(ATLAS기법매핑!$H$5:$H$212,"*"&D22&"*",ATLAS기법매핑!$M$5:$M$212,"Realized")&" / "&COUNTIFS(ATLAS기법매핑!$H$5:$H$212,"*"&D22&"*",ATLAS기법매핑!$M$5:$M$212,"Demonstrated")&" / "&COUNTIFS(ATLAS기법매핑!$H$5:$H$212,"*"&D22&"*",ATLAS기법매핑!$M$5:$M$212,"Feasible") -> 1 / 0 / 0 | AL22: =(LEN(Y22&Z22)>0)+(LEN(AD22&AE22)>0)+(LEN(AF22&AG22)>0)+(LEN(AH22&AI22)>0)+(LEN(AJ22&AK22)>0) -> 1 | AM22: =COUNTIF(ATLAS사례연구!$J$5:$J$77,"*"&D22&"*") -> 1 | AN22: =COUNTIFS(ATLAS사례연구!$J$5:$J$77,"*"&D22&"*",ATLAS사례연구!$C$5:$C$77,"Incident") -> 1 | AO22: 0 | AP22: 0 | AQ22: =IF(AN22+AO22>0,"실제 사고 확인",IF(AB22>0,"실사용 기법 포함",IF(OR(AM22>0,AP22>0),"실증·공개 취약점","이론·시나리오"))) -> 실제 사고 확인 | AR22: CS0042 | AS22: • [ATLAS CS0042·실제사고] OpenAI Assistants API를 은밀한 C2 채널로 악용한 백도어 SesameOp(실제 사고) | AT22: M0019 Control Access to AI Models and Data in Production | AU22: AI API 키 보호·사용량 이상 탐지, AI 서비스 egress 가시성, 비인가 AI 트래픽 차단 | AV22: UT-38
A23: D01. 공격 준비 및 AI 무기화 | B23: UT-05 | C23: AI 서비스를 이용한 C2 통신 | D23: UT-05.2 | E23: AI 웹 서비스 중계 악용 | F23: URL 조회 기능을 가진 AI 비서 또는 침해된 AI 에이전트를 경유하여 공격자 서버와 간접 통신함으로써 직접 통신 탐지 회피 | G23: =IF(AN23+AO23>=2,"상",IF(OR(AN23+AO23=1,AM23>0,AB23>0,AP23>0),"중","하")) -> 중 | H23: 상 | I23: =IF(AND(G23="상",H23="상"),"매우 높음",IF(OR(AND(G23="상",H23="중"),AND(G23="중",H23="상")),"높음",IF(OR(AND(G23="중",H23="중"),AND(G23="상",H23="하"),AND(G23="하",H23="상")),"보통","낮음"))) -> 높음 | J23: ="실제 사고 "&(AN23+AO23)&"건(ATLAS "&AN23&" / OWASP "&AO23&"), 실증 사례 "&(AM23-AN23)&"건, Realized 기법 "&AB23&"개, 취약점·익스플로잇 "&AP23&"건" -> 실제 사고 0건(ATLAS 0 / OWASP 0), 실증 사례 2건, Realized 기법 0개, 취약점·익스플로잇 0건 | K23: 직접 통신 탐지 회피형 원격 제어 | L23: 명령·제어(Command and Control) | M23: 명령·제어 | O23: ● | Q23: ● | S23: 기밀성, 무결성 | V23: ○ | X23: 조직 생애주기 외부 활동 — 탈취 자격증명 사용 시 운영 비용·데이터 피해로 발현 | Y23: T0114, T0108 | AA23: =COUNTIF(ATLAS기법매핑!$H$5:$H$212,"*"&D23&"*") -> 2 | AB23: =COUNTIFS(ATLAS기법매핑!$H$5:$H$212,"*"&D23&"*",ATLAS기법매핑!$M$5:$M$212,"Realized") -> 0 | AC23: =COUNTIFS(ATLAS기법매핑!$H$5:$H$212,"*"&D23&"*",ATLAS기법매핑!$M$5:$M$212,"Realized")&" / "&COUNTIFS(ATLAS기법매핑!$H$5:$H$212,"*"&D23&"*",ATLAS기법매핑!$M$5:$M$212,"Demonstrated")&" / "&COUNTIFS(ATLAS기법매핑!$H$5:$H$212,"*"&D23&"*",ATLAS기법매핑!$M$5:$M$212,"Feasible") -> 0 / 2 / 0 | AL23: =(LEN(Y23&Z23)>0)+(LEN(AD23&AE23)>0)+(LEN(AF23&AG23)>0)+(LEN(AH23&AI23)>0)+(LEN(AJ23&AK23)>0) -> 1 | AM23: =COUNTIF(ATLAS사례연구!$J$5:$J$77,"*"&D23&"*") -> 2 | AN23: =COUNTIFS(ATLAS사례연구!$J$5:$J$77,"*"&D23&"*",ATLAS사례연구!$C$5:$C$77,"Incident") -> 0 | AO23: 0 | AP23: 0 | AQ23: =IF(AN23+AO23>0,"실제 사고 확인",IF(AB23>0,"실사용 기법 포함",IF(OR(AM23>0,AP23>0),"실증·공개 취약점","이론·시나리오"))) -> 실증·공개 취약점 | AR23: CS0051, CS0061 | AS23: • [ATLAS CS0061·실증] 익명 웹 AI 비서의 URL 조회 기능을 악성코드 C2 중계로 악용(AI in the Middle) • [ATLAS CS0051·실증] 웹페이지 인젝션으로 OpenClaw에 지속 지시를 심어 C2로 활용 | AT23: M0020 Generative AI Guardrails M0024 AI Telemetry Logging | AU23: AI API 키 보호·사용량 이상 탐지, AI 서비스 egress 가시성, 비인가 AI 트래픽 차단 | AV23: UT-38
A24: D01. 공격 준비 및 AI 무기화 | B24: UT-05 | C24: AI 서비스를 이용한 C2 통신 | D24: UT-05.3 | E24: AI 아티팩트 저장소 악용 | F24: 모델/데이터셋 저장소를 명령 및 데이터 교환 매체로 사용하여 정상 아티팩트 다운로드로 위장된 C2 수행 | G24: =IF(AN24+AO24>=2,"상",IF(OR(AN24+AO24=1,AM24>0,AB24>0,AP24>0),"중","하")) -> 중 | H24: 중 | I24: =IF(AND(G24="상",H24="상"),"매우 높음",IF(OR(AND(G24="상",H24="중"),AND(G24="중",H24="상")),"높음",IF(OR(AND(G24="중",H24="중"),AND(G24="상",H24="하"),AND(G24="하",H24="상")),"보통","낮음"))) -> 보통 | J24: ="실제 사고 "&(AN24+AO24)&"건(ATLAS "&AN24&" / OWASP "&AO24&"), 실증 사례 "&(AM24-AN24)&"건, Realized 기법 "&AB24&"개, 취약점·익스플로잇 "&AP24&"건" -> 실제 사고 1건(ATLAS 1 / OWASP 0), 실증 사례 0건, Realized 기법 1개, 취약점·익스플로잇 0건 | K24: 탐지 회피형 통신 채널(제한적 대역) | L24: 명령·제어(Command and Control) | M24: 명령·제어 | O24: ● | Q24: ● | S24: 기밀성, 무결성 | V24: ○ | X24: 조직 생애주기 외부 활동 — 탈취 자격증명 사용 시 운영 비용·데이터 피해로 발현 | Y24: T0120 | AA24: =COUNTIF(ATLAS기법매핑!$H$5:$H$212,"*"&D24&"*") -> 1 | AB24: =COUNTIFS(ATLAS기법매핑!$H$5:$H$212,"*"&D24&"*",ATLAS기법매핑!$M$5:$M$212,"Realized") -> 1 | AC24: =COUNTIFS(ATLAS기법매핑!$H$5:$H$212,"*"&D24&"*",ATLAS기법매핑!$M$5:$M$212,"Realized")&" / "&COUNTIFS(ATLAS기법매핑!$H$5:$H$212,"*"&D24&"*",ATLAS기법매핑!$M$5:$M$212,"Demonstrated")&" / "&COUNTIFS(ATLAS기법매핑!$H$5:$H$212,"*"&D24&"*",ATLAS기법매핑!$M$5:$M$212,"Feasible") -> 1 / 0 / 0 | AL24: =(LEN(Y24&Z24)>0)+(LEN(AD24&AE24)>0)+(LEN(AF24&AG24)>0)+(LEN(AH24&AI24)>0)+(LEN(AJ24&AK24)>0) -> 1 | AM24: =COUNTIF(ATLAS사례연구!$J$5:$J$77,"*"&D24&"*") -> 1 | AN24: =COUNTIFS(ATLAS사례연구!$J$5:$J$77,"*"&D24&"*",ATLAS사례연구!$C$5:$C$77,"Incident") -> 1 | AO24: 0 | AP24: 0 | AQ24: =IF(AN24+AO24>0,"실제 사고 확인",IF(AB24>0,"실사용 기법 포함",IF(OR(AM24>0,AP24>0),"실증·공개 취약점","이론·시나리오"))) -> 실제 사고 확인 | AR24: CS0068 | AS24: • [ATLAS CS0068·실제사고] OpenAI 평가용 자율 에이전트들이 평가 경계를 넘어 외부 인프라 구축·Hugging Face 침해(실제 사고) • [OWASP 시나리오] 모델 허브 저장소를 명령·데이터 교환 매체로 사용하는 C2(ATLAS T0120 기법 정의) | AT24: — (ATLAS 완화책 없음: Lv2 핵심 통제 참조) | AU24: AI API 키 보호·사용량 이상 탐지, AI 서비스 egress 가시성, 비인가 AI 트래픽 차단 | AV24: UT-38
A25: D02. 프롬프트 인젝션 및 컨텍스트 노출 | B25: UT-06 | C25: 직접 프롬프트 인젝션 | D25: UT-06.1 | E25: 시스템 지시 무력화 | F25: 사용자 입력창에 '이전 지시 무시' 등 조작 지시를 입력하여 시스템 프롬프트의 역할/제약을 무력화하고 비인가 정보 조회 또는 기능 실행 유도 | G25: =IF(AN25+AO25>=2,"상",IF(OR(AN25+AO25=1,AM25>0,AB25>0,AP25>0),"중","하")) -> 상 | H25: 중 | I25: =IF(AND(G25="상",H25="상"),"매우 높음",IF(OR(AND(G25="상",H25="중"),AND(G25="중",H25="상")),"높음",IF(OR(AND(G25="중",H25="중"),AND(G25="상",H25="하"),AND(G25="하",H25="상")),"보통","낮음"))) -> 높음 | J25: ="실제 사고 "&(AN25+AO25)&"건(ATLAS "&AN25&" / OWASP "&AO25&"), 실증 사례 "&(AM25-AN25)&"건, Realized 기법 "&AB25&"개, 취약점·익스플로잇 "&AP25&"건" -> 실제 사고 3건(ATLAS 3 / OWASP 0), 실증 사례 9건, Realized 기법 2개, 취약점·익스플로잇 1건 | K25: 앱 권한 범위 내 비인가 조회/실행 | L25: 실행(Execution) | M25: 실행 | O25: ● | P25: ● | Q25: ● | R25: ● | S25: 기밀성, 무결성 | T25: ○ | V25: ● | Y25: T0051, T0051.000 | AA25: =COUNTIF(ATLAS기법매핑!$H$5:$H$212,"*"&D25&"*") -> 2 | AB25: =COUNTIFS(ATLAS기법매핑!$H$5:$H$212,"*"&D25&"*",ATLAS기법매핑!$M$5:$M$212,"Realized") -> 2 | AC25: =COUNTIFS(ATLAS기법매핑!$H$5:$H$212,"*"&D25&"*",ATLAS기법매핑!$M$5:$M$212,"Realized")&" / "&COUNTIFS(ATLAS기법매핑!$H$5:$H$212,"*"&D25&"*",ATLAS기법매핑!$M$5:$M$212,"Demonstrated")&" / "&COUNTIFS(ATLAS기법매핑!$H$5:$H$212,"*"&D25&"*",ATLAS기법매핑!$M$5:$M$212,"Feasible") -> 2 / 0 / 0 | AD25: LLM01 | AE25: LLM08 | AG25: ASI01, ASI09 | AI25: DSGAI01 | AK25: MCP06 | AL25: =(LEN(Y25&Z25)>0)+(LEN(AD25&AE25)>0)+(LEN(AF25&AG25)>0)+(LEN(AH25&AI25)>0)+(LEN(AJ25&AK25)>0) -> 5 | AM25: =COUNTIF(ATLAS사례연구!$J$5:$J$77,"*"&D25&"*") -> 12 | AN25: =COUNTIFS(ATLAS사례연구!$J$5:$J$77,"*"&D25&"*",ATLAS사례연구!$C$5:$C$77,"Incident") -> 3 | AO25: 0 | AP25: 1 | AQ25: =IF(AN25+AO25>0,"실제 사고 확인",IF(AB25>0,"실사용 기법 포함",IF(OR(AM25>0,AP25>0),"실증·공개 취약점","이론·시나리오"))) -> 실제 사고 확인 | AR25: CS0016, CS0024, CS0036, CS0037, CS0041, CS0043, CS0047, CS0051, CS0052, CS0060, CS0062, CS0069 | AS25: • [ATLAS CS0043·실제사고] LLM 기반 악성코드 분석기를 속이려 프롬프트 인젝션을 내장한 악성코드(실제 사고) • [ATLAS CS0016·실증] MathGPT에 프롬프트 인젝션으로 파이썬 코드 실행·API 키 노출 • [ATLAS CS0047·실제사고] 과권한 GitHub 토큰으로 Amazon Q VS Code 확장에 파괴형 에이전트 지시 커밋(실제 사고) • [OWASP 인용] CVE-2024-5184 EmailGPT 프롬프트 인젝션(시스템 프롬프트 노출 및 데이터 유출) | AT25: M0024 AI Telemetry Logging M0033 Input and Output Validation for AI Agent Components M0035 AI Red Team M0019 Control Access to AI Models and Data in Production M0020 Generative AI Guardrails | AU25: 다층 입·출력 가드레일, 모달리티별 정규화·비가시 문자 제거, 권한 분리로 폭발반경 제한, 적대적 테스트 상시화 | AV25: UT-01, UT-03
A26: D02. 프롬프트 인젝션 및 컨텍스트 노출 | B26: UT-06 | C26: 직접 프롬프트 인젝션 | D26: UT-06.2 | E26: 탈옥(안전장치 우회) | F26: 역할극/다단계 설득/우회 표현을 통해 모델의 안전 정책을 무력화하여 유해 콘텐츠 생성 또는 공격 도구 개발 등 금지된 용도로 모델 악용 | G26: =IF(AN26+AO26>=2,"상",IF(OR(AN26+AO26=1,AM26>0,AB26>0,AP26>0),"중","하")) -> 상 | H26: 중 | I26: =IF(AND(G26="상",H26="상"),"매우 높음",IF(OR(AND(G26="상",H26="중"),AND(G26="중",H26="상")),"높음",IF(OR(AND(G26="중",H26="중"),AND(G26="상",H26="하"),AND(G26="하",H26="상")),"보통","낮음"))) -> 높음 | J26: ="실제 사고 "&(AN26+AO26)&"건(ATLAS "&AN26&" / OWASP "&AO26&"), 실증 사례 "&(AM26-AN26)&"건, Realized 기법 "&AB26&"개, 취약점·익스플로잇 "&AP26&"건" -> 실제 사고 2건(ATLAS 2 / OWASP 0), 실증 사례 7건, Realized 기법 1개, 취약점·익스플로잇 1건 | K26: 금지 용도 악용(유해 콘텐츠·공격 도구 생성) | L26: 방어 회피(Defense Evasion) | M26: 권한 상승, 방어 회피 | O26: ● | P26: ● | Q26: ● | R26: ● | S26: 평판·사회, 규제·법적 | T26: ○ | V26: ● | Y26: T0054 | AA26: =COUNTIF(ATLAS기법매핑!$H$5:$H$212,"*"&D26&"*") -> 1 | AB26: =COUNTIFS(ATLAS기법매핑!$H$5:$H$212,"*"&D26&"*",ATLAS기법매핑!$M$5:$M$212,"Realized") -> 1 | AC26: =COUNTIFS(ATLAS기법매핑!$H$5:$H$212,"*"&D26&"*",ATLAS기법매핑!$M$5:$M$212,"Realized")&" / "&COUNTIFS(ATLAS기법매핑!$H$5:$H$212,"*"&D26&"*",ATLAS기법매핑!$M$5:$M$212,"Demonstrated")&" / "&COUNTIFS(ATLAS기법매핑!$H$5:$H$212,"*"&D26&"*",ATLAS기법매핑!$M$5:$M$212,"Feasible") -> 1 / 0 / 0 | AD26: LLM01 | AI26: DSGAI01 | AL26: =(LEN(Y26&Z26)>0)+(LEN(AD26&AE26)>0)+(LEN(AF26&AG26)>0)+(LEN(AH26&AI26)>0)+(LEN(AJ26&AK26)>0) -> 3 | AM26: =COUNTIF(ATLAS사례연구!$J$5:$J$77,"*"&D26&"*") -> 9 | AN26: =COUNTIFS(ATLAS사례연구!$J$5:$J$77,"*"&D26&"*",ATLAS사례연구!$C$5:$C$77,"Incident") -> 2 | AO26: 0 | AP26: 1 | AQ26: =IF(AN26+AO26>0,"실제 사고 확인",IF(AB26>0,"실사용 기법 포함",IF(OR(AM26>0,AP26>0),"실증·공개 취약점","이론·시나리오"))) -> 실제 사고 확인 | AR26: CS0041, CS0046, CS0051, CS0052, CS0057, CS0063, CS0066, CS0067, CS0069 | AS26: • [ATLAS CS0057·실제사고] Storm-2139가 노출 자격증명과 탈옥 도구로 Azure OpenAI 가드레일 우회·접근권 재판매(실제 사고) • [ATLAS CS0069·실제사고] GTG-1002가 탈옥한 Claude Code로 약 30개 조직 대상 자율 사이버 첩보(실제 사고) • [ATLAS CS0041·실증] AI 코딩도구 규칙 파일에 보이지 않는 유니코드 지시를 숨겨 악성 코드 생성 유도 • [OWASP 인용] CVE-2025-54794 Claude 프롬프트 인젝션 탈옥 | AT26: M0020 Generative AI Guardrails M0021 Generative AI Guidelines M0022 Generative AI Model Alignment M0035 AI Red Team | AU26: 다층 입·출력 가드레일, 모달리티별 정규화·비가시 문자 제거, 권한 분리로 폭발반경 제한, 적대적 테스트 상시화 | AV26: UT-01, UT-03
A27: D02. 프롬프트 인젝션 및 컨텍스트 노출 | B27: UT-06 | C27: 직접 프롬프트 인젝션 | D27: UT-06.3 | E27: 페이로드 난독화 | F27: 다국어 혼용/인코딩/분할 입력/동의어 치환으로 인젝션 페이로드를 변형하여 입력 필터 및 가드레일 탐지 우회 | G27: =IF(AN27+AO27>=2,"상",IF(OR(AN27+AO27=1,AM27>0,AB27>0,AP27>0),"중","하")) -> 상 | H27: 중 | I27: =IF(AND(G27="상",H27="상"),"매우 높음",IF(OR(AND(G27="상",H27="중"),AND(G27="중",H27="상")),"높음",IF(OR(AND(G27="중",H27="중"),AND(G27="상",H27="하"),AND(G27="하",H27="상")),"보통","낮음"))) -> 높음 | J27: ="실제 사고 "&(AN27+AO27)&"건(ATLAS "&AN27&" / OWASP "&AO27&"), 실증 사례 "&(AM27-AN27)&"건, Realized 기법 "&AB27&"개, 취약점·익스플로잇 "&AP27&"건" -> 실제 사고 4건(ATLAS 4 / OWASP 0), 실증 사례 23건, Realized 기법 2개, 취약점·익스플로잇 0건 | K27: 가드레일 무력화로 인젝션 성공률 증가 | L27: 방어 회피(Defense Evasion) | M27: AI 공격 적응, 방어 회피 | O27: ● | P27: ● | Q27: ● | R27: ● | S27: 무결성, 평판·사회, 기밀성 | T27: ○ | V27: ● | Y27: T0065, T0068 | AA27: =COUNTIF(ATLAS기법매핑!$H$5:$H$212,"*"&D27&"*") -> 2 | AB27: =COUNTIFS(ATLAS기법매핑!$H$5:$H$212,"*"&D27&"*",ATLAS기법매핑!$M$5:$M$212,"Realized") -> 2 | AC27: =COUNTIFS(ATLAS기법매핑!$H$5:$H$212,"*"&D27&"*",ATLAS기법매핑!$M$5:$M$212,"Realized")&" / "&COUNTIFS(ATLAS기법매핑!$H$5:$H$212,"*"&D27&"*",ATLAS기법매핑!$M$5:$M$212,"Demonstrated")&" / "&COUNTIFS(ATLAS기법매핑!$H$5:$H$212,"*"&D27&"*",ATLAS기법매핑!$M$5:$M$212,"Feasible") -> 2 / 0 / 0 | AD27: LLM01 | AK27: MCP06 | AL27: =(LEN(Y27&Z27)>0)+(LEN(AD27&AE27)>0)+(LEN(AF27&AG27)>0)+(LEN(AH27&AI27)>0)+(LEN(AJ27&AK27)>0) -> 3 | AM27: =COUNTIF(ATLAS사례연구!$J$5:$J$77,"*"&D27&"*") -> 27 | AN27: =COUNTIFS(ATLAS사례연구!$J$5:$J$77,"*"&D27&"*",ATLAS사례연구!$C$5:$C$77,"Incident") -> 4 | AO27: 0 | AP27: 0 | AQ27: =IF(AN27+AO27>0,"실제 사고 확인",IF(AB27>0,"실사용 기법 포함",IF(OR(AM27>0,AP27>0),"실증·공개 취약점","이론·시나리오"))) -> 실제 사고 확인 | AR27: CS0020, CS0021, CS0026, CS0029, CS0035, CS0037, CS0038, CS0039, CS0040, CS0041, CS0043, CS0045, CS0046, CS0047, CS0049, CS0051, CS0052, CS0054, CS0056, CS0059, CS0060, CS0061, CS0062, CS0063, CS0066, CS0067, CS0072 | AS27: • [ATLAS CS0043·실제사고] LLM 기반 악성코드 분석기를 속이려 프롬프트 인젝션을 내장한 악성코드(실제 사고) • [ATLAS CS0047·실제사고] 과권한 GitHub 토큰으로 Amazon Q VS Code 확장에 파괴형 에이전트 지시 커밋(실제 사고) • [ATLAS CS0056·실제사고] 약 2.4만 계정·1,600만 쿼리로 Claude 능력을 증류하려는 캠페인 적발(실제 사고) | AT27: M0020 Generative AI Guardrails M0035 AI Red Team | AU27: 다층 입·출력 가드레일, 모달리티별 정규화·비가시 문자 제거, 권한 분리로 폭발반경 제한, 적대적 테스트 상시화 | AV27: UT-01, UT-03
A28: D02. 프롬프트 인젝션 및 컨텍스트 노출 | B28: UT-06 | C28: 직접 프롬프트 인젝션 | D28: UT-06.4 | E28: 멀티모달 은닉 지시 | F28: 이미지/오디오/문서 내 비가시 텍스트 또는 유니코드 태그 문자로 지시를 은닉하여 사람 검토와 텍스트 기반 필터를 동시에 우회 | G28: =IF(AN28+AO28>=2,"상",IF(OR(AN28+AO28=1,AM28>0,AB28>0,AP28>0),"중","하")) -> 중 | H28: 중 | I28: =IF(AND(G28="상",H28="상"),"매우 높음",IF(OR(AND(G28="상",H28="중"),AND(G28="중",H28="상")),"높음",IF(OR(AND(G28="중",H28="중"),AND(G28="상",H28="하"),AND(G28="하",H28="상")),"보통","낮음"))) -> 보통 | J28: ="실제 사고 "&(AN28+AO28)&"건(ATLAS "&AN28&" / OWASP "&AO28&"), 실증 사례 "&(AM28-AN28)&"건, Realized 기법 "&AB28&"개, 취약점·익스플로잇 "&AP28&"건" -> 실제 사고 0건(ATLAS 0 / OWASP 0), 실증 사례 1건, Realized 기법 0개, 취약점·익스플로잇 1건 | K28: 사람 검토 및 필터 동시 우회 | L28: 방어 회피(Defense Evasion) | M28: 방어 회피 | O28: ● | Q28: ● | S28: 무결성, 평판·사회, 기밀성 | T28: ○ | V28: ● | Y28: T0129 | AA28: =COUNTIF(ATLAS기법매핑!$H$5:$H$212,"*"&D28&"*") -> 1 | AB28: =COUNTIFS(ATLAS기법매핑!$H$5:$H$212,"*"&D28&"*",ATLAS기법매핑!$M$5:$M$212,"Realized") -> 0 | AC28: =COUNTIFS(ATLAS기법매핑!$H$5:$H$212,"*"&D28&"*",ATLAS기법매핑!$M$5:$M$212,"Realized")&" / "&COUNTIFS(ATLAS기법매핑!$H$5:$H$212,"*"&D28&"*",ATLAS기법매핑!$M$5:$M$212,"Demonstrated")&" / "&COUNTIFS(ATLAS기법매핑!$H$5:$H$212,"*"&D28&"*",ATLAS기법매핑!$M$5:$M$212,"Feasible") -> 0 / 0 / 1 | AD28: LLM01 | AI28: DSGAI09 | AL28: =(LEN(Y28&Z28)>0)+(LEN(AD28&AE28)>0)+(LEN(AF28&AG28)>0)+(LEN(AH28&AI28)>0)+(LEN(AJ28&AK28)>0) -> 3 | AM28: =COUNTIF(ATLAS사례연구!$J$5:$J$77,"*"&D28&"*") -> 1 | AN28: =COUNTIFS(ATLAS사례연구!$J$5:$J$77,"*"&D28&"*",ATLAS사례연구!$C$5:$C$77,"Incident") -> 0 | AO28: 0 | AP28: 1 | AQ28: =IF(AN28+AO28>0,"실제 사고 확인",IF(AB28>0,"실사용 기법 포함",IF(OR(AM28>0,AP28>0),"실증·공개 취약점","이론·시나리오"))) -> 실증·공개 취약점 | AR28: CS0041 | AS28: • [ATLAS CS0041·실증] AI 코딩도구 규칙 파일에 보이지 않는 유니코드 지시를 숨겨 악성 코드 생성 유도 • [OWASP 인용] M365 Copilot ASCII 스머글링 PoC(2024.08, 비가시 유니코드로 MFA 코드 유출) | AT28: — (ATLAS 완화책 없음: Lv2 핵심 통제 참조) | AU28: 다층 입·출력 가드레일, 모달리티별 정규화·비가시 문자 제거, 권한 분리로 폭발반경 제한, 적대적 테스트 상시화 | AV28: UT-01, UT-03
A29: D02. 프롬프트 인젝션 및 컨텍스트 노출 | B29: UT-07 | C29: 간접 프롬프트 인젝션 | D29: UT-07.1 | E29: 외부 콘텐츠 경유 주입 | F29: 웹페이지/문서/이메일/이슈 등 AI가 처리하는 외부 콘텐츠에 지시문을 은닉하여, 콘텐츠 처리 시점에 사용자 권한으로 데이터 조회/전송 등 비인가 행위 수행 | G29: =IF(AN29+AO29>=2,"상",IF(OR(AN29+AO29=1,AM29>0,AB29>0,AP29>0),"중","하")) -> 중 | H29: 상 | I29: =IF(AND(G29="상",H29="상"),"매우 높음",IF(OR(AND(G29="상",H29="중"),AND(G29="중",H29="상")),"높음",IF(OR(AND(G29="중",H29="중"),AND(G29="상",H29="하"),AND(G29="하",H29="상")),"보통","낮음"))) -> 높음 | J29: ="실제 사고 "&(AN29+AO29)&"건(ATLAS "&AN29&" / OWASP "&AO29&"), 실증 사례 "&(AM29-AN29)&"건, Realized 기법 "&AB29&"개, 취약점·익스플로잇 "&AP29&"건" -> 실제 사고 0건(ATLAS 0 / OWASP 0), 실증 사례 23건, Realized 기법 0개, 취약점·익스플로잇 4건 | K29: 제로클릭 데이터 유출 및 사용자 권한 전체 악용 | L29: 초기 접근(Initial Access) | M29: 초기 접근, 실행, 지속성 | O29: ● | P29: ● | Q29: ● | R29: ● | S29: 기밀성, 무결성 | T29: ○ | V29: ● | Y29: T0051.001, T0093 | AA29: =COUNTIF(ATLAS기법매핑!$H$5:$H$212,"*"&D29&"*") -> 2 | AB29: =COUNTIFS(ATLAS기법매핑!$H$5:$H$212,"*"&D29&"*",ATLAS기법매핑!$M$5:$M$212,"Realized") -> 0 | AC29: =COUNTIFS(ATLAS기법매핑!$H$5:$H$212,"*"&D29&"*",ATLAS기법매핑!$M$5:$M$212,"Realized")&" / "&COUNTIFS(ATLAS기법매핑!$H$5:$H$212,"*"&D29&"*",ATLAS기법매핑!$M$5:$M$212,"Demonstrated")&" / "&COUNTIFS(ATLAS기법매핑!$H$5:$H$212,"*"&D29&"*",ATLAS기법매핑!$M$5:$M$212,"Feasible") -> 0 / 2 / 0 | AD29: LLM01 | AE29: LLM10 | AG29: ASI02 | AI29: DSGAI01, DSGAI06, DSGAI16 | AJ29: MCP06 | AK29: MCP03 | AL29: =(LEN(Y29&Z29)>0)+(LEN(AD29&AE29)>0)+(LEN(AF29&AG29)>0)+(LEN(AH29&AI29)>0)+(LEN(AJ29&AK29)>0) -> 5 | AM29: =COUNTIF(ATLAS사례연구!$J$5:$J$77,"*"&D29&"*") -> 23 | AN29: =COUNTIFS(ATLAS사례연구!$J$5:$J$77,"*"&D29&"*",ATLAS사례연구!$C$5:$C$77,"Incident") -> 0 | AO29: 0 | AP29: 4 | AQ29: =IF(AN29+AO29>0,"실제 사고 확인",IF(AB29>0,"실사용 기법 포함",IF(OR(AM29>0,AP29>0),"실증·공개 취약점","이론·시나리오"))) -> 실증·공개 취약점 | AR29: CS0016, CS0020, CS0021, CS0026, CS0029, CS0035, CS0037, CS0038, CS0039, CS0040, CS0045, CS0046, CS0048, CS0049, CS0051, CS0054, CS0055, CS0059, CS0060, CS0062, CS0063, CS0066, CS0067 | AS29: • [ATLAS CS0020·실증] 웹페이지 숨은 지시로 Bing Chat이 사용자 개인정보를 캐내는 사회공학 수행 • [ATLAS CS0021·실증] 웹페이지 간접 인젝션으로 ChatGPT 대화 내용을 이미지 URL로 유출 • [ATLAS CS0029·실증] 공유 Google 문서의 간접 인젝션으로 Bard 대화 내용 유출 • [OWASP 인용] Salesforce Agentforce ForcedLeak(2025.09) / Google Gemini Trifecta(2025.09) / Hub MCP 교차 컨텍스트 인젝션(2025.06) / GitHub 공개 이슈 경유 저장소 탈취(2025.05) | AT29: M0024 AI Telemetry Logging M0033 Input and Output Validation for AI Agent Components M0035 AI Red Team M0039 AI Honeypots | AU29: 비신뢰 콘텐츠 구획·출처 표시, 비신뢰 데이터 처리 중 도구 호출 제한, 목표 변경 시 인간 승인, '치명적 삼요소' 동시 성립 차단 | AV29: UT-02, UT-04
A30: D02. 프롬프트 인젝션 및 컨텍스트 노출 | B30: UT-07 | C30: 간접 프롬프트 인젝션 | D30: UT-07.2 | E30: 지연 실행형 주입 | F30: 특정 키워드/후속 대화 턴/시점에 발동하도록 조건부 지시를 심어 즉시 탐지를 회피하고 도구 호출 제한 등 보호 장치 우회 | G30: =IF(AN30+AO30>=2,"상",IF(OR(AN30+AO30=1,AM30>0,AB30>0,AP30>0),"중","하")) -> 중 | H30: 중 | I30: =IF(AND(G30="상",H30="상"),"매우 높음",IF(OR(AND(G30="상",H30="중"),AND(G30="중",H30="상")),"높음",IF(OR(AND(G30="중",H30="중"),AND(G30="상",H30="하"),AND(G30="하",H30="상")),"보통","낮음"))) -> 보통 | J30: ="실제 사고 "&(AN30+AO30)&"건(ATLAS "&AN30&" / OWASP "&AO30&"), 실증 사례 "&(AM30-AN30)&"건, Realized 기법 "&AB30&"개, 취약점·익스플로잇 "&AP30&"건" -> 실제 사고 0건(ATLAS 0 / OWASP 0), 실증 사례 6건, Realized 기법 0개, 취약점·익스플로잇 0건 | K30: 즉시 탐지 회피 후 보호장치 우회 실행 | L30: 방어 회피(Defense Evasion) | M30: 실행, 방어 회피 | O30: ● | P30: ● | Q30: ● | R30: ● | S30: 기밀성, 무결성 | T30: ○ | V30: ● | Y30: T0051.002, T0094 | AA30: =COUNTIF(ATLAS기법매핑!$H$5:$H$212,"*"&D30&"*") -> 2 | AB30: =COUNTIFS(ATLAS기법매핑!$H$5:$H$212,"*"&D30&"*",ATLAS기법매핑!$M$5:$M$212,"Realized") -> 0 | AC30: =COUNTIFS(ATLAS기법매핑!$H$5:$H$212,"*"&D30&"*",ATLAS기법매핑!$M$5:$M$212,"Realized")&" / "&COUNTIFS(ATLAS기법매핑!$H$5:$H$212,"*"&D30&"*",ATLAS기법매핑!$M$5:$M$212,"Demonstrated")&" / "&COUNTIFS(ATLAS기법매핑!$H$5:$H$212,"*"&D30&"*",ATLAS기법매핑!$M$5:$M$212,"Feasible") -> 0 / 2 / 0 | AD30: LLM01 | AG30: ASI02 | AL30: =(LEN(Y30&Z30)>0)+(LEN(AD30&AE30)>0)+(LEN(AF30&AG30)>0)+(LEN(AH30&AI30)>0)+(LEN(AJ30&AK30)>0) -> 3 | AM30: =COUNTIF(ATLAS사례연구!$J$5:$J$77,"*"&D30&"*") -> 6 | AN30: =COUNTIFS(ATLAS사례연구!$J$5:$J$77,"*"&D30&"*",ATLAS사례연구!$C$5:$C$77,"Incident") -> 0 | AO30: 0 | AP30: 0 | AQ30: =IF(AN30+AO30>0,"실제 사고 확인",IF(AB30>0,"실사용 기법 포함",IF(OR(AM30>0,AP30>0),"실증·공개 취약점","이론·시나리오"))) -> 실증·공개 취약점 | AR30: CS0024, CS0037, CS0038, CS0059, CS0063, CS0064 | AS30: • [ATLAS CS0024·실증] RAG를 매개로 자기복제 프롬프트가 GenAI 이메일 비서 간 전파(Morris II 웜) • [ATLAS CS0037·실증] Copilot Studio 고객지원 에이전트를 인젝션해 지식원·도구를 탐색하고 CRM 데이터 유출 • [ATLAS CS0038·실증] 지시 실행을 다음 대화 턴으로 지연시켜 Gemini의 도구 호출 제한 우회 | AT30: M0024 AI Telemetry Logging M0033 Input and Output Validation for AI Agent Components M0035 AI Red Team | AU30: 비신뢰 콘텐츠 구획·출처 표시, 비신뢰 데이터 처리 중 도구 호출 제한, 목표 변경 시 인간 승인, '치명적 삼요소' 동시 성립 차단 | AV30: UT-02, UT-04
A31: D02. 프롬프트 인젝션 및 컨텍스트 노출 | B31: UT-07 | C31: 간접 프롬프트 인젝션 | D31: UT-07.3 | E31: 검색 노출용 콘텐츠 제작 | F31: RAG 수집 대상 사이트/문서를 파악한 후 검색 상위에 노출되도록 설계한 악성 콘텐츠를 외부에 게시하여 AI가 이를 근거로 응답하도록 유도 | G31: =IF(AN31+AO31>=2,"상",IF(OR(AN31+AO31=1,AM31>0,AB31>0,AP31>0),"중","하")) -> 중 | H31: 중 | I31: =IF(AND(G31="상",H31="상"),"매우 높음",IF(OR(AND(G31="상",H31="중"),AND(G31="중",H31="상")),"높음",IF(OR(AND(G31="중",H31="중"),AND(G31="상",H31="하"),AND(G31="하",H31="상")),"보통","낮음"))) -> 보통 | J31: ="실제 사고 "&(AN31+AO31)&"건(ATLAS "&AN31&" / OWASP "&AO31&"), 실증 사례 "&(AM31-AN31)&"건, Realized 기법 "&AB31&"개, 취약점·익스플로잇 "&AP31&"건" -> 실제 사고 0건(ATLAS 0 / OWASP 0), 실증 사례 3건, Realized 기법 0개, 취약점·익스플로잇 0건 | K31: 특정 질의 응답 조작(범위 제한) | L31: 자원 개발(Resource Development) | M31: 정찰, AI 공격 적응 | P31: ● | Q31: ● | S31: 기밀성, 무결성 | T31: ○ | V31: ● | Y31: T0064, T0066 | AA31: =COUNTIF(ATLAS기법매핑!$H$5:$H$212,"*"&D31&"*") -> 2 | AB31: =COUNTIFS(ATLAS기법매핑!$H$5:$H$212,"*"&D31&"*",ATLAS기법매핑!$M$5:$M$212,"Realized") -> 0 | AC31: =COUNTIFS(ATLAS기법매핑!$H$5:$H$212,"*"&D31&"*",ATLAS기법매핑!$M$5:$M$212,"Realized")&" / "&COUNTIFS(ATLAS기법매핑!$H$5:$H$212,"*"&D31&"*",ATLAS기법매핑!$M$5:$M$212,"Demonstrated")&" / "&COUNTIFS(ATLAS기법매핑!$H$5:$H$212,"*"&D31&"*",ATLAS기법매핑!$M$5:$M$212,"Feasible") -> 0 / 2 / 0 | AD31: LLM01 | AE31: LLM07 | AI31: DSGAI21 | AL31: =(LEN(Y31&Z31)>0)+(LEN(AD31&AE31)>0)+(LEN(AF31&AG31)>0)+(LEN(AH31&AI31)>0)+(LEN(AJ31&AK31)>0) -> 3 | AM31: =COUNTIF(ATLAS사례연구!$J$5:$J$77,"*"&D31&"*") -> 3 | AN31: =COUNTIFS(ATLAS사례연구!$J$5:$J$77,"*"&D31&"*",ATLAS사례연구!$C$5:$C$77,"Incident") -> 0 | AO31: 0 | AP31: 0 | AQ31: =IF(AN31+AO31>0,"실제 사고 확인",IF(AB31>0,"실사용 기법 포함",IF(OR(AM31>0,AP31>0),"실증·공개 취약점","이론·시나리오"))) -> 실증·공개 취약점 | AR31: CS0026, CS0035, CS0059 | AS31: • [ATLAS CS0026·실증] 메일을 RAG로 수집하는 M365 Copilot을 조작해 송금 계좌 정보를 바꿔치기 • [ATLAS CS0035·실증] 공개 채널 게시글의 간접 인젝션으로 Slack AI가 비공개 채널 데이터 유출 • [ATLAS CS0059·실증] EchoLeak: 메일 한 통으로 M365 Copilot이 사용자 조작 없이 기업 데이터 유출(제로클릭) | AT31: M0000 Limit Public Release of Information M0020 Generative AI Guardrails | AU31: 비신뢰 콘텐츠 구획·출처 표시, 비신뢰 데이터 처리 중 도구 호출 제한, 목표 변경 시 인간 승인, '치명적 삼요소' 동시 성립 차단 | AV31: UT-02, UT-04
A32: D02. 프롬프트 인젝션 및 컨텍스트 노출 | B32: UT-07 | C32: 간접 프롬프트 인젝션 | D32: UT-07.4 | E32: 에이전트 유인 및 클로킹 | F32: 조작된 AI 비서 링크/클릭 유도 화면으로 에이전트 행동을 유인하거나, AI 크롤러에만 다른 콘텐츠를 제공(클로킹)하여 사람 검토를 회피한 지시 전달 | G32: =IF(AN32+AO32>=2,"상",IF(OR(AN32+AO32=1,AM32>0,AB32>0,AP32>0),"중","하")) -> 중 | H32: 중 | I32: =IF(AND(G32="상",H32="상"),"매우 높음",IF(OR(AND(G32="상",H32="중"),AND(G32="중",H32="상")),"높음",IF(OR(AND(G32="중",H32="중"),AND(G32="상",H32="하"),AND(G32="하",H32="상")),"보통","낮음"))) -> 보통 | J32: ="실제 사고 "&(AN32+AO32)&"건(ATLAS "&AN32&" / OWASP "&AO32&"), 실증 사례 "&(AM32-AN32)&"건, Realized 기법 "&AB32&"개, 취약점·익스플로잇 "&AP32&"건" -> 실제 사고 1건(ATLAS 1 / OWASP 0), 실증 사례 1건, Realized 기법 1개, 취약점·익스플로잇 0건 | K32: 에이전트 행위 유도(사용자 권한 범위) | L32: 초기 접근(Initial Access) | M32: 초기 접근, 실행, 방어 회피 | O32: ● | P32: ● | Q32: ● | R32: ● | S32: 기밀성, 무결성 | T32: ○ | V32: ● | Y32: T0131, T0100, T0134 | AA32: =COUNTIF(ATLAS기법매핑!$H$5:$H$212,"*"&D32&"*") -> 3 | AB32: =COUNTIFS(ATLAS기법매핑!$H$5:$H$212,"*"&D32&"*",ATLAS기법매핑!$M$5:$M$212,"Realized") -> 1 | AC32: =COUNTIFS(ATLAS기법매핑!$H$5:$H$212,"*"&D32&"*",ATLAS기법매핑!$M$5:$M$212,"Realized")&" / "&COUNTIFS(ATLAS기법매핑!$H$5:$H$212,"*"&D32&"*",ATLAS기법매핑!$M$5:$M$212,"Demonstrated")&" / "&COUNTIFS(ATLAS기법매핑!$H$5:$H$212,"*"&D32&"*",ATLAS기법매핑!$M$5:$M$212,"Feasible") -> 1 / 1 / 1 | AD32: LLM01 | AG32: ASI01 | AL32: =(LEN(Y32&Z32)>0)+(LEN(AD32&AE32)>0)+(LEN(AF32&AG32)>0)+(LEN(AH32&AI32)>0)+(LEN(AJ32&AK32)>0) -> 3 | AM32: =COUNTIF(ATLAS사례연구!$J$5:$J$77,"*"&D32&"*") -> 2 | AN32: =COUNTIFS(ATLAS사례연구!$J$5:$J$77,"*"&D32&"*",ATLAS사례연구!$C$5:$C$77,"Incident") -> 1 | AO32: 0 | AP32: 0 | AQ32: =IF(AN32+AO32>0,"실제 사고 확인",IF(AB32>0,"실사용 기법 포함",IF(OR(AM32>0,AP32>0),"실증·공개 취약점","이론·시나리오"))) -> 실제 사고 확인 | AR32: CS0055, CS0072 | AS32: • [ATLAS CS0072·실제사고] 조작된 AI 비서 링크로 메모리를 오염시켜 특정 제품을 추천하게 만드는 홍보성 공격(실제 사고) • [ATLAS CS0055·실증] ClickFix 사회공학으로 컴퓨터 사용 에이전트가 악성 명령 실행 | AT32: M0020 Generative AI Guardrails M0021 Generative AI Guidelines | AU32: 비신뢰 콘텐츠 구획·출처 표시, 비신뢰 데이터 처리 중 도구 호출 제한, 목표 변경 시 인간 승인, '치명적 삼요소' 동시 성립 차단 | AV32: UT-02, UT-04
A33: D02. 프롬프트 인젝션 및 컨텍스트 노출 | B33: UT-07 | C33: 간접 프롬프트 인젝션 | D33: UT-07.5 | E33: 에이전트 목표 탈취 | F33: 주입된 지시가 에이전트의 목표/계획/판단 기준을 점진적으로 변경하여, 정상 업무 흐름 속에서 공격자 의도에 맞는 의사결정과 행위 반복 | G33: =IF(AN33+AO33>=2,"상",IF(OR(AN33+AO33=1,AM33>0,AB33>0,AP33>0),"중","하")) -> 중 | H33: 상 | I33: =IF(AND(G33="상",H33="상"),"매우 높음",IF(OR(AND(G33="상",H33="중"),AND(G33="중",H33="상")),"높음",IF(OR(AND(G33="중",H33="중"),AND(G33="상",H33="하"),AND(G33="하",H33="상")),"보통","낮음"))) -> 높음 | J33: ="실제 사고 "&(AN33+AO33)&"건(ATLAS "&AN33&" / OWASP "&AO33&"), 실증 사례 "&(AM33-AN33)&"건, Realized 기법 "&AB33&"개, 취약점·익스플로잇 "&AP33&"건" -> 실제 사고 0건(ATLAS 0 / OWASP 0), 실증 사례 1건, Realized 기법 0개, 취약점·익스플로잇 2건 | K33: 에이전트 권한 전체를 공격자 목적에 사용 | L33: 실행(Execution) | M33: — | Q33: ● | R33: ● | S33: 기밀성, 무결성 | T33: ○ | V33: ● | AA33: =COUNTIF(ATLAS기법매핑!$H$5:$H$212,"*"&D33&"*") -> 0 | AB33: =COUNTIFS(ATLAS기법매핑!$H$5:$H$212,"*"&D33&"*",ATLAS기법매핑!$M$5:$M$212,"Realized") -> 0 | AC33: =COUNTIFS(ATLAS기법매핑!$H$5:$H$212,"*"&D33&"*",ATLAS기법매핑!$M$5:$M$212,"Realized")&" / "&COUNTIFS(ATLAS기법매핑!$H$5:$H$212,"*"&D33&"*",ATLAS기법매핑!$M$5:$M$212,"Demonstrated")&" / "&COUNTIFS(ATLAS기법매핑!$H$5:$H$212,"*"&D33&"*",ATLAS기법매핑!$M$5:$M$212,"Feasible") -> 0 / 0 / 0 | AE33: LLM03 | AF33: ASI01 | AG33: ASI05, ASI09 | AK33: MCP10 | AL33: =(LEN(Y33&Z33)>0)+(LEN(AD33&AE33)>0)+(LEN(AF33&AG33)>0)+(LEN(AH33&AI33)>0)+(LEN(AJ33&AK33)>0) -> 3 | AM33: =COUNTIF(ATLAS사례연구!$J$5:$J$77,"*"&D33&"*") -> 1 | AN33: =COUNTIFS(ATLAS사례연구!$J$5:$J$77,"*"&D33&"*",ATLAS사례연구!$C$5:$C$77,"Incident") -> 0 | AO33: 0 | AP33: 2 | AQ33: =IF(AN33+AO33>0,"실제 사고 확인",IF(AB33>0,"실사용 기법 포함",IF(OR(AM33>0,AP33>0),"실증·공개 취약점","이론·시나리오"))) -> 실증·공개 취약점 | AR33: CS0063 | AS33: • [ATLAS CS0063·실증] 캘린더 초대·메일에 숨긴 지시로 Gemini 비서가 기기·앱을 조작 • [OWASP 인용] ChatGPT Operator 프롬프트 인젝션(2025.02) / VS Code 에이전트 워크플로 RCE(2025.09) • [OWASP 시나리오] 반복 캘린더 초대로 플래너 에이전트의 목표 가중치를 매일 조금씩 변경(ASI01 시나리오#3) | AT33: — (ATLAS 완화책 없음: Lv2 핵심 통제 참조) | AU33: 비신뢰 콘텐츠 구획·출처 표시, 비신뢰 데이터 처리 중 도구 호출 제한, 목표 변경 시 인간 승인, '치명적 삼요소' 동시 성립 차단 | AV33: UT-02, UT-04
A34: D02. 프롬프트 인젝션 및 컨텍스트 노출 | B34: UT-08 | C34: 숨겨진 컨텍스트 노출 | D34: UT-08.1 | E34: 시스템 프롬프트 추출 | F34: 반복 질의/역할 전환/출력 형식 변환 요청을 통해 시스템 지시문과 내부 규칙을 추출하여 가드레일 우회 및 후속 인젝션 설계에 활용 | G34: =IF(AN34+AO34>=2,"상",IF(OR(AN34+AO34=1,AM34>0,AB34>0,AP34>0),"중","하")) -> 중 | H34: 하 | I34: =IF(AND(G34="상",H34="상"),"매우 높음",IF(OR(AND(G34="상",H34="중"),AND(G34="중",H34="상")),"높음",IF(OR(AND(G34="중",H34="중"),AND(G34="상",H34="하"),AND(G34="하",H34="상")),"보통","낮음"))) -> 낮음 | J34: ="실제 사고 "&(AN34+AO34)&"건(ATLAS "&AN34&" / OWASP "&AO34&"), 실증 사례 "&(AM34-AN34)&"건, Realized 기법 "&AB34&"개, 취약점·익스플로잇 "&AP34&"건" -> 실제 사고 0건(ATLAS 0 / OWASP 0), 실증 사례 3건, Realized 기법 0개, 취약점·익스플로잇 1건 | K34: 정책 정보 노출(직접 피해 제한적) | L34: 탐색(Discovery) | M34: 탐색, 유출 | O34: ● | P34: ● | Q34: ● | R34: ● | S34: 기밀성 | T34: ● | V34: ○ | Y34: T0056, T0069, T0069.000, T0069.001, T0069.002 | AA34: =COUNTIF(ATLAS기법매핑!$H$5:$H$212,"*"&D34&"*") -> 5 | AB34: =COUNTIFS(ATLAS기법매핑!$H$5:$H$212,"*"&D34&"*",ATLAS기법매핑!$M$5:$M$212,"Realized") -> 0 | AC34: =COUNTIFS(ATLAS기법매핑!$H$5:$H$212,"*"&D34&"*",ATLAS기법매핑!$M$5:$M$212,"Realized")&" / "&COUNTIFS(ATLAS기법매핑!$H$5:$H$212,"*"&D34&"*",ATLAS기법매핑!$M$5:$M$212,"Demonstrated")&" / "&COUNTIFS(ATLAS기법매핑!$H$5:$H$212,"*"&D34&"*",ATLAS기법매핑!$M$5:$M$212,"Feasible") -> 0 / 4 / 1 | AD34: LLM08 | AI34: DSGAI15 | AL34: =(LEN(Y34&Z34)>0)+(LEN(AD34&AE34)>0)+(LEN(AF34&AG34)>0)+(LEN(AH34&AI34)>0)+(LEN(AJ34&AK34)>0) -> 3 | AM34: =COUNTIF(ATLAS사례연구!$J$5:$J$77,"*"&D34&"*") -> 3 | AN34: =COUNTIFS(ATLAS사례연구!$J$5:$J$77,"*"&D34&"*",ATLAS사례연구!$C$5:$C$77,"Incident") -> 0 | AO34: 0 | AP34: 1 | AQ34: =IF(AN34+AO34>0,"실제 사고 확인",IF(AB34>0,"실사용 기법 포함",IF(OR(AM34>0,AP34>0),"실증·공개 취약점","이론·시나리오"))) -> 실증·공개 취약점 | AR34: CS0026, CS0048, CS0051 | AS34: • [ATLAS CS0026·실증] 메일을 RAG로 수집하는 M365 Copilot을 조작해 송금 계좌 정보를 바꿔치기 • [ATLAS CS0048·실증] 인터넷에 노출된 ClawdBot 제어 인터페이스 수백 개에서 자격증명 탈취·명령 실행 • [ATLAS CS0051·실증] 웹페이지 인젝션으로 OpenClaw에 지속 지시를 심어 C2로 활용 • [OWASP 인용] CVE-2024-5184 EmailGPT 시스템 프롬프트 노출 | AT34: M0020 Generative AI Guardrails M0005 Control Access to AI Models and Data at Rest M0019 Control Access to AI Models and Data in Production M0000 Limit Public Release of Information M0021 Generative AI Guidelines | AU34: 은닉 컨텍스트 노출 가정 설계, 비밀·보안 로직을 프롬프트에 두지 않음, 권한은 외부 정책엔진에서 강제 | AV34: UT-19
A35: D02. 프롬프트 인젝션 및 컨텍스트 노출 | B35: UT-08 | C35: 숨겨진 컨텍스트 노출 | D35: UT-08.2 | E35: 에이전트 구성 탐색 | F35: 에이전트에 질의하여 연결 도구 목록/호출 체인/활성화 트리거/지식원 구성을 파악함으로써 악용 가능한 도구와 데이터 경로 식별 | G35: =IF(AN35+AO35>=2,"상",IF(OR(AN35+AO35=1,AM35>0,AB35>0,AP35>0),"중","하")) -> 중 | H35: 중 | I35: =IF(AND(G35="상",H35="상"),"매우 높음",IF(OR(AND(G35="상",H35="중"),AND(G35="중",H35="상")),"높음",IF(OR(AND(G35="중",H35="중"),AND(G35="상",H35="하"),AND(G35="하",H35="상")),"보통","낮음"))) -> 보통 | J35: ="실제 사고 "&(AN35+AO35)&"건(ATLAS "&AN35&" / OWASP "&AO35&"), 실증 사례 "&(AM35-AN35)&"건, Realized 기법 "&AB35&"개, 취약점·익스플로잇 "&AP35&"건" -> 실제 사고 0건(ATLAS 0 / OWASP 0), 실증 사례 4건, Realized 기법 0개, 취약점·익스플로잇 0건 | K35: 도구 악용 경로 정밀화 | L35: 탐색(Discovery) | M35: 탐색 | Q35: ● | R35: ● | S35: 기밀성 | T35: ● | V35: ○ | Y35: T0084, T0084.000, T0084.001, T0084.002, T0084.003 | AA35: =COUNTIF(ATLAS기법매핑!$H$5:$H$212,"*"&D35&"*") -> 5 | AB35: =COUNTIFS(ATLAS기법매핑!$H$5:$H$212,"*"&D35&"*",ATLAS기법매핑!$M$5:$M$212,"Realized") -> 0 | AC35: =COUNTIFS(ATLAS기법매핑!$H$5:$H$212,"*"&D35&"*",ATLAS기법매핑!$M$5:$M$212,"Realized")&" / "&COUNTIFS(ATLAS기법매핑!$H$5:$H$212,"*"&D35&"*",ATLAS기법매핑!$M$5:$M$212,"Demonstrated")&" / "&COUNTIFS(ATLAS기법매핑!$H$5:$H$212,"*"&D35&"*",ATLAS기법매핑!$M$5:$M$212,"Feasible") -> 0 / 5 / 0 | AD35: LLM08 | AG35: ASI03 | AK35: MCP10 | AL35: =(LEN(Y35&Z35)>0)+(LEN(AD35&AE35)>0)+(LEN(AF35&AG35)>0)+(LEN(AH35&AI35)>0)+(LEN(AJ35&AK35)>0) -> 4 | AM35: =COUNTIF(ATLAS사례연구!$J$5:$J$77,"*"&D35&"*") -> 4 | AN35: =COUNTIFS(ATLAS사례연구!$J$5:$J$77,"*"&D35&"*",ATLAS사례연구!$C$5:$C$77,"Incident") -> 0 | AO35: 0 | AP35: 0 | AQ35: =IF(AN35+AO35>0,"실제 사고 확인",IF(AB35>0,"실사용 기법 포함",IF(OR(AM35>0,AP35>0),"실증·공개 취약점","이론·시나리오"))) -> 실증·공개 취약점 | AR35: CS0037, CS0052, CS0063, CS0067 | AS35: • [ATLAS CS0037·실증] Copilot Studio 고객지원 에이전트를 인젝션해 지식원·도구를 탐색하고 CRM 데이터 유출 • [ATLAS CS0052·실증] 11개 LLM 프레임워크에서 20개 RCE 취약점 발견, 인터넷 공개 앱에서 실증(LLMSmith) • [ATLAS CS0063·실증] 캘린더 초대·메일에 숨긴 지시로 Gemini 비서가 기기·앱을 조작 | AT35: M0000 Limit Public Release of Information M0039 AI Honeypots | AU35: 은닉 컨텍스트 노출 가정 설계, 비밀·보안 로직을 프롬프트에 두지 않음, 권한은 외부 정책엔진에서 강제 | AV35: UT-19
A36: D02. 프롬프트 인젝션 및 컨텍스트 노출 | B36: UT-08 | C36: 숨겨진 컨텍스트 노출 | D36: UT-08.3 | E36: 런타임 권한 탐색 | F36: 에이전트의 실행 권한/접근 가능 자원/런타임 기능을 탐색하여 권한 상승 및 도구 오용 대상 선별 | G36: =IF(AN36+AO36>=2,"상",IF(OR(AN36+AO36=1,AM36>0,AB36>0,AP36>0),"중","하")) -> 하 | H36: 중 | I36: =IF(AND(G36="상",H36="상"),"매우 높음",IF(OR(AND(G36="상",H36="중"),AND(G36="중",H36="상")),"높음",IF(OR(AND(G36="중",H36="중"),AND(G36="상",H36="하"),AND(G36="하",H36="상")),"보통","낮음"))) -> 낮음 | J36: ="실제 사고 "&(AN36+AO36)&"건(ATLAS "&AN36&" / OWASP "&AO36&"), 실증 사례 "&(AM36-AN36)&"건, Realized 기법 "&AB36&"개, 취약점·익스플로잇 "&AP36&"건" -> 실제 사고 0건(ATLAS 0 / OWASP 0), 실증 사례 0건, Realized 기법 0개, 취약점·익스플로잇 0건 | K36: 권한 상승 및 도구 오용 대상 선별 | L36: 탐색(Discovery) | M36: 탐색 | Q36: ● | R36: ● | S36: 기밀성 | T36: ● | V36: ○ | Y36: T0133 | AA36: =COUNTIF(ATLAS기법매핑!$H$5:$H$212,"*"&D36&"*") -> 1 | AB36: =COUNTIFS(ATLAS기법매핑!$H$5:$H$212,"*"&D36&"*",ATLAS기법매핑!$M$5:$M$212,"Realized") -> 0 | AC36: =COUNTIFS(ATLAS기법매핑!$H$5:$H$212,"*"&D36&"*",ATLAS기법매핑!$M$5:$M$212,"Realized")&" / "&COUNTIFS(ATLAS기법매핑!$H$5:$H$212,"*"&D36&"*",ATLAS기법매핑!$M$5:$M$212,"Demonstrated")&" / "&COUNTIFS(ATLAS기법매핑!$H$5:$H$212,"*"&D36&"*",ATLAS기법매핑!$M$5:$M$212,"Feasible") -> 0 / 0 / 1 | AD36: LLM08 | AL36: =(LEN(Y36&Z36)>0)+(LEN(AD36&AE36)>0)+(LEN(AF36&AG36)>0)+(LEN(AH36&AI36)>0)+(LEN(AJ36&AK36)>0) -> 2 | AM36: =COUNTIF(ATLAS사례연구!$J$5:$J$77,"*"&D36&"*") -> 0 | AN36: =COUNTIFS(ATLAS사례연구!$J$5:$J$77,"*"&D36&"*",ATLAS사례연구!$C$5:$C$77,"Incident") -> 0 | AO36: 0 | AP36: 0 | AQ36: =IF(AN36+AO36>0,"실제 사고 확인",IF(AB36>0,"실사용 기법 포함",IF(OR(AM36>0,AP36>0),"실증·공개 취약점","이론·시나리오"))) -> 이론·시나리오 | AS36: • [OWASP 시나리오] 에이전트 런타임 기능·권한 탐색(ATLAS T0133, 2026.09 신설 기법 정의) | AT36: M0039 AI Honeypots | AU36: 은닉 컨텍스트 노출 가정 설계, 비밀·보안 로직을 프롬프트에 두지 않음, 권한은 외부 정책엔진에서 강제 | AV36: UT-19
A37: D02. 프롬프트 인젝션 및 컨텍스트 노출 | B37: UT-08 | C37: 숨겨진 컨텍스트 노출 | D37: UT-08.4 | E37: 프롬프트 내 비밀정보 노출 | F37: 시스템 프롬프트/에이전트 설정에 API 키/접속 정보/내부 URL을 직접 기재하여, 컨텍스트 추출 시 연동 시스템 자격증명이 함께 노출 | G37: =IF(AN37+AO37>=2,"상",IF(OR(AN37+AO37=1,AM37>0,AB37>0,AP37>0),"중","하")) -> 하 | H37: 상 | I37: =IF(AND(G37="상",H37="상"),"매우 높음",IF(OR(AND(G37="상",H37="중"),AND(G37="중",H37="상")),"높음",IF(OR(AND(G37="중",H37="중"),AND(G37="상",H37="하"),AND(G37="하",H37="상")),"보통","낮음"))) -> 보통 | J37: ="실제 사고 "&(AN37+AO37)&"건(ATLAS "&AN37&" / OWASP "&AO37&"), 실증 사례 "&(AM37-AN37)&"건, Realized 기법 "&AB37&"개, 취약점·익스플로잇 "&AP37&"건" -> 실제 사고 0건(ATLAS 0 / OWASP 0), 실증 사례 0건, Realized 기법 0개, 취약점·익스플로잇 0건 | K37: 연동 시스템 자격증명 노출로 다수 시스템 접근 | L37: 자격증명 접근(Credential Access) | M37: — | O37: ● | P37: ● | Q37: ● | R37: ● | S37: 기밀성 | T37: ● | V37: ○ | AA37: =COUNTIF(ATLAS기법매핑!$H$5:$H$212,"*"&D37&"*") -> 0 | AB37: =COUNTIFS(ATLAS기법매핑!$H$5:$H$212,"*"&D37&"*",ATLAS기법매핑!$M$5:$M$212,"Realized") -> 0 | AC37: =COUNTIFS(ATLAS기법매핑!$H$5:$H$212,"*"&D37&"*",ATLAS기법매핑!$M$5:$M$212,"Realized")&" / "&COUNTIFS(ATLAS기법매핑!$H$5:$H$212,"*"&D37&"*",ATLAS기법매핑!$M$5:$M$212,"Demonstrated")&" / "&COUNTIFS(ATLAS기법매핑!$H$5:$H$212,"*"&D37&"*",ATLAS기법매핑!$M$5:$M$212,"Feasible") -> 0 / 0 / 0 | AD37: LLM08 | AI37: DSGAI02, DSGAI18 | AK37: MCP01 | AL37: =(LEN(Y37&Z37)>0)+(LEN(AD37&AE37)>0)+(LEN(AF37&AG37)>0)+(LEN(AH37&AI37)>0)+(LEN(AJ37&AK37)>0) -> 3 | AM37: =COUNTIF(ATLAS사례연구!$J$5:$J$77,"*"&D37&"*") -> 0 | AN37: =COUNTIFS(ATLAS사례연구!$J$5:$J$77,"*"&D37&"*",ATLAS사례연구!$C$5:$C$77,"Incident") -> 0 | AO37: 0 | AP37: 0 | AQ37: =IF(AN37+AO37>0,"실제 사고 확인",IF(AB37>0,"실사용 기법 포함",IF(OR(AM37>0,AP37>0),"실증·공개 취약점","이론·시나리오"))) -> 이론·시나리오 | AS37: • [OWASP 시나리오] 시스템 프롬프트에 포함된 자격증명이 추출되어 연동 시스템 접근(LLM08 시나리오#1) | AT37: — (ATLAS 완화책 없음: Lv2 핵심 통제 참조) | AU37: 은닉 컨텍스트 노출 가정 설계, 비밀·보안 로직을 프롬프트에 두지 않음, 권한은 외부 정책엔진에서 강제 | AV37: UT-19
A38: D03. AI 데이터 오염 및 유출 | B38: UT-09 | C38: 학습 데이터 오염 | D38: UT-09.1 | E38: 학습 데이터 직접 오염 | F38: 사전학습/파인튜닝 데이터에 소량의 오염 샘플 또는 트리거 패턴을 삽입하여 모델에 편향, 성능 저하, 조건부 오작동(백도어)을 내재화 | G38: =IF(AN38+AO38>=2,"상",IF(OR(AN38+AO38=1,AM38>0,AB38>0,AP38>0),"중","하")) -> 상 | H38: 중 | I38: =IF(AND(G38="상",H38="상"),"매우 높음",IF(OR(AND(G38="상",H38="중"),AND(G38="중",H38="상")),"높음",IF(OR(AND(G38="중",H38="중"),AND(G38="상",H38="하"),AND(G38="하",H38="상")),"보통","낮음"))) -> 높음 | J38: ="실제 사고 "&(AN38+AO38)&"건(ATLAS "&AN38&" / OWASP "&AO38&"), 실증 사례 "&(AM38-AN38)&"건, Realized 기법 "&AB38&"개, 취약점·익스플로잇 "&AP38&"건" -> 실제 사고 2건(ATLAS 2 / OWASP 0), 실증 사례 1건, Realized 기법 1개, 취약점·익스플로잇 0건 | K38: 모델 전반 무결성 훼손(통제권 탈취와 간접 연계) | L38: 지속성(Persistence) | M38: 지속성 | N38: ● | O38: ● | S38: 무결성, 안전·사용자 | T38: ● | V38: ○ | X38: 온라인 학습·피드백 재학습은 운영 중 유입 | Y38: T0020 | AA38: =COUNTIF(ATLAS기법매핑!$H$5:$H$212,"*"&D38&"*") -> 1 | AB38: =COUNTIFS(ATLAS기법매핑!$H$5:$H$212,"*"&D38&"*",ATLAS기법매핑!$M$5:$M$212,"Realized") -> 1 | AC38: =COUNTIFS(ATLAS기법매핑!$H$5:$H$212,"*"&D38&"*",ATLAS기법매핑!$M$5:$M$212,"Realized")&" / "&COUNTIFS(ATLAS기법매핑!$H$5:$H$212,"*"&D38&"*",ATLAS기법매핑!$M$5:$M$212,"Demonstrated")&" / "&COUNTIFS(ATLAS기법매핑!$H$5:$H$212,"*"&D38&"*",ATLAS기법매핑!$M$5:$M$212,"Feasible") -> 1 / 0 / 0 | AD38: LLM05 | AH38: DSGAI04 | AI38: DSGAI05 | AL38: =(LEN(Y38&Z38)>0)+(LEN(AD38&AE38)>0)+(LEN(AF38&AG38)>0)+(LEN(AH38&AI38)>0)+(LEN(AJ38&AK38)>0) -> 3 | AM38: =COUNTIF(ATLAS사례연구!$J$5:$J$77,"*"&D38&"*") -> 3 | AN38: =COUNTIFS(ATLAS사례연구!$J$5:$J$77,"*"&D38&"*",ATLAS사례연구!$C$5:$C$77,"Incident") -> 2 | AO38: 0 | AP38: 0 | AQ38: =IF(AN38+AO38>0,"실제 사고 확인",IF(AB38>0,"실사용 기법 포함",IF(OR(AM38>0,AP38>0),"실증·공개 취약점","이론·시나리오"))) -> 실제 사고 확인 | AR38: CS0002, CS0009, CS0025 | AS38: • [ATLAS CS0002·실제사고] VirusTotal에 변종 샘플을 대량 제출해 크라우드소싱 학습 데이터를 오염 • [ATLAS CS0009·실제사고] Tay 챗봇이 사용자 대화로 온라인 학습되며 오염되어 혐오 발언 생성(실제 사고) • [ATLAS CS0025·실증] URL 목록형 대규모 데이터셋의 만료 도메인을 매입해 학습 데이터 오염(Split-View) | AT38: M0001 Limit Model Artifact Release M0005 Control Access to AI Models and Data at Rest M0007 Sanitize Training Data M0008 Validate AI Model M0023 AI Bill of Materials | AU38: 데이터셋 출처·계보 관리(DBOM/ML-BOM), 학습데이터 정제·이상치 탐지, 재학습 입력 검증 | AV38: UT-05
A39: D03. AI 데이터 오염 및 유출 | B39: UT-09 | C39: 학습 데이터 오염 | D39: UT-09.2 | E39: 오염 데이터셋 유포 | F39: 오염된 데이터셋을 공개 저장소에 배포하거나 정상 데이터셋으로 위장하여, 이를 수집한 다수 조직의 학습 파이프라인을 동시 오염 | G39: =IF(AN39+AO39>=2,"상",IF(OR(AN39+AO39=1,AM39>0,AB39>0,AP39>0),"중","하")) -> 중 | H39: 중 | I39: =IF(AND(G39="상",H39="상"),"매우 높음",IF(OR(AND(G39="상",H39="중"),AND(G39="중",H39="상")),"높음",IF(OR(AND(G39="중",H39="중"),AND(G39="상",H39="하"),AND(G39="하",H39="상")),"보통","낮음"))) -> 보통 | J39: ="실제 사고 "&(AN39+AO39)&"건(ATLAS "&AN39&" / OWASP "&AO39&"), 실증 사례 "&(AM39-AN39)&"건, Realized 기법 "&AB39&"개, 취약점·익스플로잇 "&AP39&"건" -> 실제 사고 0건(ATLAS 0 / OWASP 0), 실증 사례 1건, Realized 기법 0개, 취약점·익스플로잇 0건 | K39: 다수 조직 모델의 무결성 동시 훼손 | L39: 자원 개발(Resource Development) | M39: 자원 개발 | N39: ● | O39: ● | S39: 무결성, 안전·사용자 | T39: ● | V39: ○ | X39: 온라인 학습·피드백 재학습은 운영 중 유입 | Y39: T0115.000 | AA39: =COUNTIF(ATLAS기법매핑!$H$5:$H$212,"*"&D39&"*") -> 1 | AB39: =COUNTIFS(ATLAS기법매핑!$H$5:$H$212,"*"&D39&"*",ATLAS기법매핑!$M$5:$M$212,"Realized") -> 0 | AC39: =COUNTIFS(ATLAS기법매핑!$H$5:$H$212,"*"&D39&"*",ATLAS기법매핑!$M$5:$M$212,"Realized")&" / "&COUNTIFS(ATLAS기법매핑!$H$5:$H$212,"*"&D39&"*",ATLAS기법매핑!$M$5:$M$212,"Demonstrated")&" / "&COUNTIFS(ATLAS기법매핑!$H$5:$H$212,"*"&D39&"*",ATLAS기법매핑!$M$5:$M$212,"Feasible") -> 0 / 1 / 0 | AD39: LLM05 | AE39: LLM04 | AG39: ASI04 | AH39: DSGAI04 | AL39: =(LEN(Y39&Z39)>0)+(LEN(AD39&AE39)>0)+(LEN(AF39&AG39)>0)+(LEN(AH39&AI39)>0)+(LEN(AJ39&AK39)>0) -> 4 | AM39: =COUNTIF(ATLAS사례연구!$J$5:$J$77,"*"&D39&"*") -> 1 | AN39: =COUNTIFS(ATLAS사례연구!$J$5:$J$77,"*"&D39&"*",ATLAS사례연구!$C$5:$C$77,"Incident") -> 0 | AO39: 0 | AP39: 0 | AQ39: =IF(AN39+AO39>0,"실제 사고 확인",IF(AB39>0,"실사용 기법 포함",IF(OR(AM39>0,AP39>0),"실증·공개 취약점","이론·시나리오"))) -> 실증·공개 취약점 | AR39: CS0025 | AS39: • [ATLAS CS0025·실증] URL 목록형 대규모 데이터셋의 만료 도메인을 매입해 학습 데이터 오염(Split-View) | AT39: M0007 Sanitize Training Data | AU39: 데이터셋 출처·계보 관리(DBOM/ML-BOM), 학습데이터 정제·이상치 탐지, 재학습 입력 검증 | AV39: UT-05
A40: D03. AI 데이터 오염 및 유출 | B40: UT-09 | C40: 학습 데이터 오염 | D40: UT-09.3 | E40: 재학습 피드백 오염 | F40: 사용자 피드백/운영 로그를 자동 재학습에 반영하는 구조를 악용하여 조작 입력을 반복 주입함으로써 모델 행동을 점진적으로 왜곡 | G40: =IF(AN40+AO40>=2,"상",IF(OR(AN40+AO40=1,AM40>0,AB40>0,AP40>0),"중","하")) -> 중 | H40: 중 | I40: =IF(AND(G40="상",H40="상"),"매우 높음",IF(OR(AND(G40="상",H40="중"),AND(G40="중",H40="상")),"높음",IF(OR(AND(G40="중",H40="중"),AND(G40="상",H40="하"),AND(G40="하",H40="상")),"보통","낮음"))) -> 보통 | J40: ="실제 사고 "&(AN40+AO40)&"건(ATLAS "&AN40&" / OWASP "&AO40&"), 실증 사례 "&(AM40-AN40)&"건, Realized 기법 "&AB40&"개, 취약점·익스플로잇 "&AP40&"건" -> 실제 사고 1건(ATLAS 1 / OWASP 0), 실증 사례 0건, Realized 기법 0개, 취약점·익스플로잇 0건 | K40: 점진적 왜곡(탐지 시 롤백 가능) | L40: 지속성(Persistence) | M40: — | N40: ● | O40: ● | S40: 무결성, 안전·사용자 | T40: ○ | V40: ● | AA40: =COUNTIF(ATLAS기법매핑!$H$5:$H$212,"*"&D40&"*") -> 0 | AB40: =COUNTIFS(ATLAS기법매핑!$H$5:$H$212,"*"&D40&"*",ATLAS기법매핑!$M$5:$M$212,"Realized") -> 0 | AC40: =COUNTIFS(ATLAS기법매핑!$H$5:$H$212,"*"&D40&"*",ATLAS기법매핑!$M$5:$M$212,"Realized")&" / "&COUNTIFS(ATLAS기법매핑!$H$5:$H$212,"*"&D40&"*",ATLAS기법매핑!$M$5:$M$212,"Demonstrated")&" / "&COUNTIFS(ATLAS기법매핑!$H$5:$H$212,"*"&D40&"*",ATLAS기법매핑!$M$5:$M$212,"Feasible") -> 0 / 0 / 0 | AD40: LLM05 | AE40: LLM07 | AG40: ASI08 | AI40: DSGAI07 | AL40: =(LEN(Y40&Z40)>0)+(LEN(AD40&AE40)>0)+(LEN(AF40&AG40)>0)+(LEN(AH40&AI40)>0)+(LEN(AJ40&AK40)>0) -> 3 | AM40: =COUNTIF(ATLAS사례연구!$J$5:$J$77,"*"&D40&"*") -> 1 | AN40: =COUNTIFS(ATLAS사례연구!$J$5:$J$77,"*"&D40&"*",ATLAS사례연구!$C$5:$C$77,"Incident") -> 1 | AO40: 0 | AP40: 0 | AQ40: =IF(AN40+AO40>0,"실제 사고 확인",IF(AB40>0,"실사용 기법 포함",IF(OR(AM40>0,AP40>0),"실증·공개 취약점","이론·시나리오"))) -> 실제 사고 확인 | AR40: CS0009 | AS40: • [ATLAS CS0009·실제사고] Tay 챗봇이 사용자 대화로 온라인 학습되며 오염되어 혐오 발언 생성(실제 사고) • [OWASP 시나리오] 자동 재학습 피드백 루프를 악용한 모델 왜곡(LLM05 시나리오#3) | AT40: — (ATLAS 완화책 없음: Lv2 핵심 통제 참조) | AU40: 데이터셋 출처·계보 관리(DBOM/ML-BOM), 학습데이터 정제·이상치 탐지, 재학습 입력 검증 | AV40: UT-05
A41: D03. AI 데이터 오염 및 유출 | B41: UT-09 | C41: 학습 데이터 오염 | D41: UT-09.4 | E41: 무결성 저하 공격 | F41: 적대적 입력 반복 투입 또는 데이터셋 일부 훼손을 통해 모델/데이터셋의 신뢰도를 저하시켜 운영 중단 또는 재학습 비용 유발 | G41: =IF(AN41+AO41>=2,"상",IF(OR(AN41+AO41=1,AM41>0,AB41>0,AP41>0),"중","하")) -> 상 | H41: 중 | I41: =IF(AND(G41="상",H41="상"),"매우 높음",IF(OR(AND(G41="상",H41="중"),AND(G41="중",H41="상")),"높음",IF(OR(AND(G41="중",H41="중"),AND(G41="상",H41="하"),AND(G41="하",H41="상")),"보통","낮음"))) -> 높음 | J41: ="실제 사고 "&(AN41+AO41)&"건(ATLAS "&AN41&" / OWASP "&AO41&"), 실증 사례 "&(AM41-AN41)&"건, Realized 기법 "&AB41&"개, 취약점·익스플로잇 "&AP41&"건" -> 실제 사고 2건(ATLAS 2 / OWASP 0), 실증 사례 4건, Realized 기법 1개, 취약점·익스플로잇 0건 | K41: 모델 신뢰도 저하 및 재학습 비용 | L41: 영향(Impact) | M41: 영향 | N41: ● | O41: ● | S41: 무결성, 안전·사용자 | T41: ● | V41: ○ | X41: 온라인 학습·피드백 재학습은 운영 중 유입 | Y41: T0059, T0031 | AA41: =COUNTIF(ATLAS기법매핑!$H$5:$H$212,"*"&D41&"*") -> 2 | AB41: =COUNTIFS(ATLAS기법매핑!$H$5:$H$212,"*"&D41&"*",ATLAS기법매핑!$M$5:$M$212,"Realized") -> 1 | AC41: =COUNTIFS(ATLAS기법매핑!$H$5:$H$212,"*"&D41&"*",ATLAS기법매핑!$M$5:$M$212,"Realized")&" / "&COUNTIFS(ATLAS기법매핑!$H$5:$H$212,"*"&D41&"*",ATLAS기법매핑!$M$5:$M$212,"Demonstrated")&" / "&COUNTIFS(ATLAS기법매핑!$H$5:$H$212,"*"&D41&"*",ATLAS기법매핑!$M$5:$M$212,"Feasible") -> 1 / 1 / 0 | AH41: DSGAI04 | AI41: DSGAI07 | AL41: =(LEN(Y41&Z41)>0)+(LEN(AD41&AE41)>0)+(LEN(AF41&AG41)>0)+(LEN(AH41&AI41)>0)+(LEN(AJ41&AK41)>0) -> 2 | AM41: =COUNTIF(ATLAS사례연구!$J$5:$J$77,"*"&D41&"*") -> 6 | AN41: =COUNTIFS(ATLAS사례연구!$J$5:$J$77,"*"&D41&"*",ATLAS사례연구!$C$5:$C$77,"Incident") -> 2 | AO41: 0 | AP41: 0 | AQ41: =IF(AN41+AO41>0,"실제 사고 확인",IF(AB41>0,"실사용 기법 포함",IF(OR(AM41>0,AP41>0),"실증·공개 취약점","이론·시나리오"))) -> 실제 사고 확인 | AR41: CS0005, CS0006, CS0009, CS0019, CS0025, CS0064 | AS41: • [ATLAS CS0025·실증] URL 목록형 대규모 데이터셋의 만료 도메인을 매입해 학습 데이터 오염(Split-View) • [ATLAS CS0006·실제사고] Clearview AI 저장소 설정 오류로 소스코드·자격증명·모델 노출 • [ATLAS CS0009·실제사고] Tay 챗봇이 사용자 대화로 온라인 학습되며 오염되어 혐오 발언 생성(실제 사고) | AT41: M0003 Predictive AI Model Hardening M0006 Predictive AI Ensembles M0007 Sanitize Training Data M0010 Predictive AI Input Restoration M0015 Predictive AI Adversarial Input Detection | AU41: 데이터셋 출처·계보 관리(DBOM/ML-BOM), 학습데이터 정제·이상치 탐지, 재학습 입력 검증 | AV41: UT-05
A42: D03. AI 데이터 오염 및 유출 | B42: UT-10 | C42: 지식원(RAG) 오염 | D42: UT-10.1 | E42: 검색 코퍼스 오염 | F42: 조직 지식원/RAG 코퍼스에 허위 또는 조작 문서를 기록하여, AI가 이를 권위 있는 근거로 인용한 잘못된 응답/권고 생성 | G42: =IF(AN42+AO42>=2,"상",IF(OR(AN42+AO42=1,AM42>0,AB42>0,AP42>0),"중","하")) -> 중 | H42: 중 | I42: =IF(AND(G42="상",H42="상"),"매우 높음",IF(OR(AND(G42="상",H42="중"),AND(G42="중",H42="상")),"높음",IF(OR(AND(G42="중",H42="중"),AND(G42="상",H42="하"),AND(G42="하",H42="상")),"보통","낮음"))) -> 보통 | J42: ="실제 사고 "&(AN42+AO42)&"건(ATLAS "&AN42&" / OWASP "&AO42&"), 실증 사례 "&(AM42-AN42)&"건, Realized 기법 "&AB42&"개, 취약점·익스플로잇 "&AP42&"건" -> 실제 사고 0건(ATLAS 0 / OWASP 0), 실증 사례 4건, Realized 기법 0개, 취약점·익스플로잇 0건 | K42: 응답 무결성 훼손(업무 판단 및 거래 오류) | L42: 지속성(Persistence) | M42: 지속성, 방어 회피 | P42: ● | Q42: ● | R42: ● | S42: 무결성, 평판·사회 | T42: ○ | V42: ● | X42: 지식원은 운영 중 지속 수집되므로 유입이 운영 단계에서 발생 | Y42: T0070, T0071 | AA42: =COUNTIF(ATLAS기법매핑!$H$5:$H$212,"*"&D42&"*") -> 2 | AB42: =COUNTIFS(ATLAS기법매핑!$H$5:$H$212,"*"&D42&"*",ATLAS기법매핑!$M$5:$M$212,"Realized") -> 0 | AC42: =COUNTIFS(ATLAS기법매핑!$H$5:$H$212,"*"&D42&"*",ATLAS기법매핑!$M$5:$M$212,"Realized")&" / "&COUNTIFS(ATLAS기법매핑!$H$5:$H$212,"*"&D42&"*",ATLAS기법매핑!$M$5:$M$212,"Demonstrated")&" / "&COUNTIFS(ATLAS기법매핑!$H$5:$H$212,"*"&D42&"*",ATLAS기법매핑!$M$5:$M$212,"Feasible") -> 0 / 2 / 0 | AE42: LLM05, LLM07 | AF42: ASI06 | AH42: DSGAI21 | AI42: DSGAI04 | AL42: =(LEN(Y42&Z42)>0)+(LEN(AD42&AE42)>0)+(LEN(AF42&AG42)>0)+(LEN(AH42&AI42)>0)+(LEN(AJ42&AK42)>0) -> 4 | AM42: =COUNTIF(ATLAS사례연구!$J$5:$J$77,"*"&D42&"*") -> 4 | AN42: =COUNTIFS(ATLAS사례연구!$J$5:$J$77,"*"&D42&"*",ATLAS사례연구!$C$5:$C$77,"Incident") -> 0 | AO42: 0 | AP42: 0 | AQ42: =IF(AN42+AO42>0,"실제 사고 확인",IF(AB42>0,"실사용 기법 포함",IF(OR(AM42>0,AP42>0),"실증·공개 취약점","이론·시나리오"))) -> 실증·공개 취약점 | AR42: CS0024, CS0026, CS0035, CS0059 | AS42: • [ATLAS CS0026·실증] 메일을 RAG로 수집하는 M365 Copilot을 조작해 송금 계좌 정보를 바꿔치기 • [ATLAS CS0024·실증] RAG를 매개로 자기복제 프롬프트가 GenAI 이메일 비서 간 전파(Morris II 웜) • [ATLAS CS0035·실증] 공개 채널 게시글의 간접 인젝션으로 Slack AI가 비공개 채널 데이터 유출 | AT42: M0020 Generative AI Guardrails M0035 AI Red Team | AU42: 수집원 신뢰등급·서명, 색인 전 검증, 검색 결과 출처 표시, 임베딩 모델 자체 검증 | AV42: UT-06, UT-10(일부)
A43: D03. AI 데이터 오염 및 유출 | B43: UT-10 | C43: 지식원(RAG) 오염 | D43: UT-10.2 | E43: 에이전트 조회 데이터 오염 | F43: 에이전트 도구가 조회하는 DB/문서 저장소/검색 색인에 악성 지시나 허위 데이터를 기록하여, 도구 호출 결과를 통해 에이전트 행위 조작 | G43: =IF(AN43+AO43>=2,"상",IF(OR(AN43+AO43=1,AM43>0,AB43>0,AP43>0),"중","하")) -> 하 | H43: 상 | I43: =IF(AND(G43="상",H43="상"),"매우 높음",IF(OR(AND(G43="상",H43="중"),AND(G43="중",H43="상")),"높음",IF(OR(AND(G43="중",H43="중"),AND(G43="상",H43="하"),AND(G43="하",H43="상")),"보통","낮음"))) -> 보통 | J43: ="실제 사고 "&(AN43+AO43)&"건(ATLAS "&AN43&" / OWASP "&AO43&"), 실증 사례 "&(AM43-AN43)&"건, Realized 기법 "&AB43&"개, 취약점·익스플로잇 "&AP43&"건" -> 실제 사고 0건(ATLAS 0 / OWASP 0), 실증 사례 0건, Realized 기법 0개, 취약점·익스플로잇 0건 | K43: 도구 결과 신뢰를 통한 에이전트 행위 조작 | L43: 지속성(Persistence) | M43: 지속성 | Q43: ● | R43: ● | S43: 무결성, 평판·사회 | T43: ○ | V43: ● | X43: 지식원은 운영 중 지속 수집되므로 유입이 운영 단계에서 발생 | Y43: T0099 | AA43: =COUNTIF(ATLAS기법매핑!$H$5:$H$212,"*"&D43&"*") -> 1 | AB43: =COUNTIFS(ATLAS기법매핑!$H$5:$H$212,"*"&D43&"*",ATLAS기법매핑!$M$5:$M$212,"Realized") -> 0 | AC43: =COUNTIFS(ATLAS기법매핑!$H$5:$H$212,"*"&D43&"*",ATLAS기법매핑!$M$5:$M$212,"Realized")&" / "&COUNTIFS(ATLAS기법매핑!$H$5:$H$212,"*"&D43&"*",ATLAS기법매핑!$M$5:$M$212,"Demonstrated")&" / "&COUNTIFS(ATLAS기법매핑!$H$5:$H$212,"*"&D43&"*",ATLAS기법매핑!$M$5:$M$212,"Feasible") -> 0 / 0 / 1 | AE43: LLM05 | AF43: ASI06 | AK43: MCP10 | AL43: =(LEN(Y43&Z43)>0)+(LEN(AD43&AE43)>0)+(LEN(AF43&AG43)>0)+(LEN(AH43&AI43)>0)+(LEN(AJ43&AK43)>0) -> 4 | AM43: =COUNTIF(ATLAS사례연구!$J$5:$J$77,"*"&D43&"*") -> 0 | AN43: =COUNTIFS(ATLAS사례연구!$J$5:$J$77,"*"&D43&"*",ATLAS사례연구!$C$5:$C$77,"Incident") -> 0 | AO43: 0 | AP43: 0 | AQ43: =IF(AN43+AO43>0,"실제 사고 확인",IF(AB43>0,"실사용 기법 포함",IF(OR(AM43>0,AP43>0),"실증·공개 취약점","이론·시나리오"))) -> 이론·시나리오 | AS43: — (근거 사례 없음: OWASP 위험 정의 기반) | AT43: M0020 Generative AI Guardrails | AU43: 수집원 신뢰등급·서명, 색인 전 검증, 검색 결과 출처 표시, 임베딩 모델 자체 검증 | AV43: UT-06, UT-10(일부)
A44: D03. AI 데이터 오염 및 유출 | B44: UT-10 | C44: 지식원(RAG) 오염 | D44: UT-10.3 | E44: 임베딩 공간 조작 | F44: 임베딩 유사도를 노린 문서 조작 또는 시맨틱 캐시 오염을 통해 검색 순위를 장악하여 특정 질의에 공격자 콘텐츠가 우선 반환되도록 유도 | G44: =IF(AN44+AO44>=2,"상",IF(OR(AN44+AO44=1,AM44>0,AB44>0,AP44>0),"중","하")) -> 하 | H44: 중 | I44: =IF(AND(G44="상",H44="상"),"매우 높음",IF(OR(AND(G44="상",H44="중"),AND(G44="중",H44="상")),"높음",IF(OR(AND(G44="중",H44="중"),AND(G44="상",H44="하"),AND(G44="하",H44="상")),"보통","낮음"))) -> 낮음 | J44: ="실제 사고 "&(AN44+AO44)&"건(ATLAS "&AN44&" / OWASP "&AO44&"), 실증 사례 "&(AM44-AN44)&"건, Realized 기법 "&AB44&"개, 취약점·익스플로잇 "&AP44&"건" -> 실제 사고 0건(ATLAS 0 / OWASP 0), 실증 사례 0건, Realized 기법 0개, 취약점·익스플로잇 0건 | K44: 특정 질의 검색 결과 장악 | L44: 지속성(Persistence) | M44: AI 공격 적응 | P44: ● | S44: 무결성, 평판·사회 | T44: ○ | V44: ● | X44: 지식원은 운영 중 지속 수집되므로 유입이 운영 단계에서 발생 | Z44: T0066 | AA44: =COUNTIF(ATLAS기법매핑!$H$5:$H$212,"*"&D44&"*") -> 1 | AB44: =COUNTIFS(ATLAS기법매핑!$H$5:$H$212,"*"&D44&"*",ATLAS기법매핑!$M$5:$M$212,"Realized") -> 0 | AC44: =COUNTIFS(ATLAS기법매핑!$H$5:$H$212,"*"&D44&"*",ATLAS기법매핑!$M$5:$M$212,"Realized")&" / "&COUNTIFS(ATLAS기법매핑!$H$5:$H$212,"*"&D44&"*",ATLAS기법매핑!$M$5:$M$212,"Demonstrated")&" / "&COUNTIFS(ATLAS기법매핑!$H$5:$H$212,"*"&D44&"*",ATLAS기법매핑!$M$5:$M$212,"Feasible") -> 0 / 1 / 0 | AD44: LLM09 | AG44: ASI04 | AI44: DSGAI13 | AL44: =(LEN(Y44&Z44)>0)+(LEN(AD44&AE44)>0)+(LEN(AF44&AG44)>0)+(LEN(AH44&AI44)>0)+(LEN(AJ44&AK44)>0) -> 4 | AM44: =COUNTIF(ATLAS사례연구!$J$5:$J$77,"*"&D44&"*") -> 0 | AN44: =COUNTIFS(ATLAS사례연구!$J$5:$J$77,"*"&D44&"*",ATLAS사례연구!$C$5:$C$77,"Incident") -> 0 | AO44: 0 | AP44: 0 | AQ44: =IF(AN44+AO44>0,"실제 사고 확인",IF(AB44>0,"실사용 기법 포함",IF(OR(AM44>0,AP44>0),"실증·공개 취약점","이론·시나리오"))) -> 이론·시나리오 | AS44: • [OWASP 시나리오] 임베딩 유사도를 노린 공개 수집 파이프라인 공격(LLM09 시나리오#1) | AT44: M0020 Generative AI Guardrails | AU44: 수집원 신뢰등급·서명, 색인 전 검증, 검색 결과 출처 표시, 임베딩 모델 자체 검증 | AV44: UT-06, UT-10(일부)
A45: D03. AI 데이터 오염 및 유출 | B45: UT-11 | C45: 에이전트 메모리 오염 | D45: UT-11.1 | E45: 장기 메모리 오염 | F45: 공유 문서/웹 콘텐츠의 인젝션을 통해 에이전트 장기 메모리에 허위 사실이나 지속 지시를 기록하여, 이후 모든 세션에서 오염된 기억 기반으로 응답/행위 | G45: =IF(AN45+AO45>=2,"상",IF(OR(AN45+AO45=1,AM45>0,AB45>0,AP45>0),"중","하")) -> 중 | H45: 상 | I45: =IF(AND(G45="상",H45="상"),"매우 높음",IF(OR(AND(G45="상",H45="중"),AND(G45="중",H45="상")),"높음",IF(OR(AND(G45="중",H45="중"),AND(G45="상",H45="하"),AND(G45="하",H45="상")),"보통","낮음"))) -> 높음 | J45: ="실제 사고 "&(AN45+AO45)&"건(ATLAS "&AN45&" / OWASP "&AO45&"), 실증 사례 "&(AM45-AN45)&"건, Realized 기법 "&AB45&"개, 취약점·익스플로잇 "&AP45&"건" -> 실제 사고 1건(ATLAS 1 / OWASP 0), 실증 사례 3건, Realized 기법 2개, 취약점·익스플로잇 0건 | K45: 세션 간 지속되는 행위 장악(C2 연계 사례) | L45: 지속성(Persistence) | M45: 지속성 | O45: ● | Q45: ● | R45: ● | S45: 무결성, 기밀성 | V45: ● | X45: 메모리는 운영 중 기록되므로 유입·발현 모두 운영 | Y45: T0080, T0080.000 | AA45: =COUNTIF(ATLAS기법매핑!$H$5:$H$212,"*"&D45&"*") -> 2 | AB45: =COUNTIFS(ATLAS기법매핑!$H$5:$H$212,"*"&D45&"*",ATLAS기법매핑!$M$5:$M$212,"Realized") -> 2 | AC45: =COUNTIFS(ATLAS기법매핑!$H$5:$H$212,"*"&D45&"*",ATLAS기법매핑!$M$5:$M$212,"Realized")&" / "&COUNTIFS(ATLAS기법매핑!$H$5:$H$212,"*"&D45&"*",ATLAS기법매핑!$M$5:$M$212,"Demonstrated")&" / "&COUNTIFS(ATLAS기법매핑!$H$5:$H$212,"*"&D45&"*",ATLAS기법매핑!$M$5:$M$212,"Feasible") -> 2 / 0 / 0 | AE45: LLM01, LLM05 | AF45: ASI06 | AI45: DSGAI04 | AK45: MCP10 | AL45: =(LEN(Y45&Z45)>0)+(LEN(AD45&AE45)>0)+(LEN(AF45&AG45)>0)+(LEN(AH45&AI45)>0)+(LEN(AJ45&AK45)>0) -> 5 | AM45: =COUNTIF(ATLAS사례연구!$J$5:$J$77,"*"&D45&"*") -> 4 | AN45: =COUNTIFS(ATLAS사례연구!$J$5:$J$77,"*"&D45&"*",ATLAS사례연구!$C$5:$C$77,"Incident") -> 1 | AO45: 0 | AP45: 0 | AQ45: =IF(AN45+AO45>0,"실제 사고 확인",IF(AB45>0,"실사용 기법 포함",IF(OR(AM45>0,AP45>0),"실증·공개 취약점","이론·시나리오"))) -> 실제 사고 확인 | AR45: CS0036, CS0040, CS0066, CS0072 | AS45: • [ATLAS CS0072·실제사고] 조작된 AI 비서 링크로 메모리를 오염시켜 특정 제품을 추천하게 만드는 홍보성 공격(실제 사고) • [ATLAS CS0040·실증] 공유 문서의 인젝션으로 ChatGPT 장기 메모리에 허위 정보를 영구 기록 • [ATLAS CS0036·실증] LLM 데스크톱 앱 메모리에서 인증 토큰을 추출해 사용자 가장(AIKatz) | AT45: M0031 Memory Hardening M0035 AI Red Team | AU45: 메모리 쓰기 검증·출처 점수, 사용자·작업별 메모리 분리, 스냅샷·롤백, 에이전트 출력의 자동 재수집 금지 | AV45: UT-07
A46: D03. AI 데이터 오염 및 유출 | B46: UT-11 | C46: 에이전트 메모리 오염 | D46: UT-11.2 | E46: 대화 스레드 오염 | F46: 진행 중인 대화 스레드에 조작 지시를 삽입하여 동일 세션 내 후속 응답과 도구 호출을 지속적으로 왜곡 | G46: =IF(AN46+AO46>=2,"상",IF(OR(AN46+AO46=1,AM46>0,AB46>0,AP46>0),"중","하")) -> 중 | H46: 중 | I46: =IF(AND(G46="상",H46="상"),"매우 높음",IF(OR(AND(G46="상",H46="중"),AND(G46="중",H46="상")),"높음",IF(OR(AND(G46="중",H46="중"),AND(G46="상",H46="하"),AND(G46="하",H46="상")),"보통","낮음"))) -> 보통 | J46: ="실제 사고 "&(AN46+AO46)&"건(ATLAS "&AN46&" / OWASP "&AO46&"), 실증 사례 "&(AM46-AN46)&"건, Realized 기법 "&AB46&"개, 취약점·익스플로잇 "&AP46&"건" -> 실제 사고 0건(ATLAS 0 / OWASP 0), 실증 사례 3건, Realized 기법 0개, 취약점·익스플로잇 0건 | K46: 단일 대화 범위 왜곡 | L46: 지속성(Persistence) | M46: 지속성 | O46: ● | Q46: ● | R46: ● | S46: 무결성, 기밀성 | V46: ● | X46: 메모리는 운영 중 기록되므로 유입·발현 모두 운영 | Y46: T0080.001 | AA46: =COUNTIF(ATLAS기법매핑!$H$5:$H$212,"*"&D46&"*") -> 1 | AB46: =COUNTIFS(ATLAS기법매핑!$H$5:$H$212,"*"&D46&"*",ATLAS기법매핑!$M$5:$M$212,"Realized") -> 0 | AC46: =COUNTIFS(ATLAS기법매핑!$H$5:$H$212,"*"&D46&"*",ATLAS기법매핑!$M$5:$M$212,"Realized")&" / "&COUNTIFS(ATLAS기법매핑!$H$5:$H$212,"*"&D46&"*",ATLAS기법매핑!$M$5:$M$212,"Demonstrated")&" / "&COUNTIFS(ATLAS기법매핑!$H$5:$H$212,"*"&D46&"*",ATLAS기법매핑!$M$5:$M$212,"Feasible") -> 0 / 1 / 0 | AE46: LLM01 | AF46: ASI06 | AL46: =(LEN(Y46&Z46)>0)+(LEN(AD46&AE46)>0)+(LEN(AF46&AG46)>0)+(LEN(AH46&AI46)>0)+(LEN(AJ46&AK46)>0) -> 3 | AM46: =COUNTIF(ATLAS사례연구!$J$5:$J$77,"*"&D46&"*") -> 3 | AN46: =COUNTIFS(ATLAS사례연구!$J$5:$J$77,"*"&D46&"*",ATLAS사례연구!$C$5:$C$77,"Incident") -> 0 | AO46: 0 | AP46: 0 | AQ46: =IF(AN46+AO46>0,"실제 사고 확인",IF(AB46>0,"실사용 기법 포함",IF(OR(AM46>0,AP46>0),"실증·공개 취약점","이론·시나리오"))) -> 실증·공개 취약점 | AR46: CS0036, CS0051, CS0063 | AS46: • [ATLAS CS0036·실증] LLM 데스크톱 앱 메모리에서 인증 토큰을 추출해 사용자 가장(AIKatz) • [ATLAS CS0051·실증] 웹페이지 인젝션으로 OpenClaw에 지속 지시를 심어 C2로 활용 • [ATLAS CS0063·실증] 캘린더 초대·메일에 숨긴 지시로 Gemini 비서가 기기·앱을 조작 | AT46: M0035 AI Red Team | AU46: 메모리 쓰기 검증·출처 점수, 사용자·작업별 메모리 분리, 스냅샷·롤백, 에이전트 출력의 자동 재수집 금지 | AV46: UT-07
A47: D03. AI 데이터 오염 및 유출 | B47: UT-11 | C47: 에이전트 메모리 오염 | D47: UT-11.3 | E47: 대화 이력 조작 | F47: 대화 이력을 변조/삭제하여 공격 흔적을 은폐하거나 과거 맥락을 위조함으로써 사용자 및 모니터링의 이상 인지 방해 | G47: =IF(AN47+AO47>=2,"상",IF(OR(AN47+AO47=1,AM47>0,AB47>0,AP47>0),"중","하")) -> 중 | H47: 중 | I47: =IF(AND(G47="상",H47="상"),"매우 높음",IF(OR(AND(G47="상",H47="중"),AND(G47="중",H47="상")),"높음",IF(OR(AND(G47="중",H47="중"),AND(G47="상",H47="하"),AND(G47="하",H47="상")),"보통","낮음"))) -> 보통 | J47: ="실제 사고 "&(AN47+AO47)&"건(ATLAS "&AN47&" / OWASP "&AO47&"), 실증 사례 "&(AM47-AN47)&"건, Realized 기법 "&AB47&"개, 취약점·익스플로잇 "&AP47&"건" -> 실제 사고 0건(ATLAS 0 / OWASP 0), 실증 사례 2건, Realized 기법 0개, 취약점·익스플로잇 0건 | K47: 공격 흔적 은폐 및 이상 인지 방해 | L47: 방어 회피(Defense Evasion) | M47: 방어 회피 | O47: ● | Q47: ● | R47: ● | S47: 무결성, 기밀성 | V47: ● | X47: 메모리는 운영 중 기록되므로 유입·발현 모두 운영 | Y47: T0092 | AA47: =COUNTIF(ATLAS기법매핑!$H$5:$H$212,"*"&D47&"*") -> 1 | AB47: =COUNTIFS(ATLAS기법매핑!$H$5:$H$212,"*"&D47&"*",ATLAS기법매핑!$M$5:$M$212,"Realized") -> 0 | AC47: =COUNTIFS(ATLAS기법매핑!$H$5:$H$212,"*"&D47&"*",ATLAS기법매핑!$M$5:$M$212,"Realized")&" / "&COUNTIFS(ATLAS기법매핑!$H$5:$H$212,"*"&D47&"*",ATLAS기법매핑!$M$5:$M$212,"Demonstrated")&" / "&COUNTIFS(ATLAS기법매핑!$H$5:$H$212,"*"&D47&"*",ATLAS기법매핑!$M$5:$M$212,"Feasible") -> 0 / 1 / 0 | AE47: LLM08, LLM02 | AF47: ASI06 | AL47: =(LEN(Y47&Z47)>0)+(LEN(AD47&AE47)>0)+(LEN(AF47&AG47)>0)+(LEN(AH47&AI47)>0)+(LEN(AJ47&AK47)>0) -> 3 | AM47: =COUNTIF(ATLAS사례연구!$J$5:$J$77,"*"&D47&"*") -> 2 | AN47: =COUNTIFS(ATLAS사례연구!$J$5:$J$77,"*"&D47&"*",ATLAS사례연구!$C$5:$C$77,"Incident") -> 0 | AO47: 0 | AP47: 0 | AQ47: =IF(AN47+AO47>0,"실제 사고 확인",IF(AB47>0,"실사용 기법 포함",IF(OR(AM47>0,AP47>0),"실증·공개 취약점","이론·시나리오"))) -> 실증·공개 취약점 | AR47: CS0036, CS0048 | AS47: • [ATLAS CS0036·실증] LLM 데스크톱 앱 메모리에서 인증 토큰을 추출해 사용자 가장(AIKatz) • [ATLAS CS0048·실증] 인터넷에 노출된 ClawdBot 제어 인터페이스 수백 개에서 자격증명 탈취·명령 실행 | AT47: — (ATLAS 완화책 없음: Lv2 핵심 통제 참조) | AU47: 메모리 쓰기 검증·출처 점수, 사용자·작업별 메모리 분리, 스냅샷·롤백, 에이전트 출력의 자동 재수집 금지 | AV47: UT-07
A48: D03. AI 데이터 오염 및 유출 | B48: UT-11 | C48: 에이전트 메모리 오염 | D48: UT-11.4 | E48: 공유 메모리 오염 | F48: 다중 에이전트가 공유하는 메모리/컨텍스트 저장소에 허위 정책 또는 사실을 기록하여 다른 에이전트의 판단까지 연쇄 오염 | G48: =IF(AN48+AO48>=2,"상",IF(OR(AN48+AO48=1,AM48>0,AB48>0,AP48>0),"중","하")) -> 하 | H48: 중 | I48: =IF(AND(G48="상",H48="상"),"매우 높음",IF(OR(AND(G48="상",H48="중"),AND(G48="중",H48="상")),"높음",IF(OR(AND(G48="중",H48="중"),AND(G48="상",H48="하"),AND(G48="하",H48="상")),"보통","낮음"))) -> 낮음 | J48: ="실제 사고 "&(AN48+AO48)&"건(ATLAS "&AN48&" / OWASP "&AO48&"), 실증 사례 "&(AM48-AN48)&"건, Realized 기법 "&AB48&"개, 취약점·익스플로잇 "&AP48&"건" -> 실제 사고 0건(ATLAS 0 / OWASP 0), 실증 사례 0건, Realized 기법 0개, 취약점·익스플로잇 0건 | K48: 다중 에이전트 판단 오염(무결성 훼손) | L48: 지속성(Persistence) | M48: — | R48: ● | S48: 무결성, 기밀성 | V48: ● | X48: 메모리는 운영 중 기록되므로 유입·발현 모두 운영 | AA48: =COUNTIF(ATLAS기법매핑!$H$5:$H$212,"*"&D48&"*") -> 0 | AB48: =COUNTIFS(ATLAS기법매핑!$H$5:$H$212,"*"&D48&"*",ATLAS기법매핑!$M$5:$M$212,"Realized") -> 0 | AC48: =COUNTIFS(ATLAS기법매핑!$H$5:$H$212,"*"&D48&"*",ATLAS기법매핑!$M$5:$M$212,"Realized")&" / "&COUNTIFS(ATLAS기법매핑!$H$5:$H$212,"*"&D48&"*",ATLAS기법매핑!$M$5:$M$212,"Demonstrated")&" / "&COUNTIFS(ATLAS기법매핑!$H$5:$H$212,"*"&D48&"*",ATLAS기법매핑!$M$5:$M$212,"Feasible") -> 0 / 0 / 0 | AF48: ASI06 | AG48: ASI08, ASI01 | AI48: DSGAI11 | AL48: =(LEN(Y48&Z48)>0)+(LEN(AD48&AE48)>0)+(LEN(AF48&AG48)>0)+(LEN(AH48&AI48)>0)+(LEN(AJ48&AK48)>0) -> 2 | AM48: =COUNTIF(ATLAS사례연구!$J$5:$J$77,"*"&D48&"*") -> 0 | AN48: =COUNTIFS(ATLAS사례연구!$J$5:$J$77,"*"&D48&"*",ATLAS사례연구!$C$5:$C$77,"Incident") -> 0 | AO48: 0 | AP48: 0 | AQ48: =IF(AN48+AO48>0,"실제 사고 확인",IF(AB48>0,"실사용 기법 포함",IF(OR(AM48>0,AP48>0),"실증·공개 취약점","이론·시나리오"))) -> 이론·시나리오 | AS48: • [OWASP 시나리오] 공유 메모리에 가짜 환불 정책을 삽입해 다른 에이전트가 재사용(ASI06 시나리오#4) | AT48: — (ATLAS 완화책 없음: Lv2 핵심 통제 참조) | AU48: 메모리 쓰기 검증·출처 점수, 사용자·작업별 메모리 분리, 스냅샷·롤백, 에이전트 출력의 자동 재수집 금지 | AV48: UT-07
A49: D03. AI 데이터 오염 및 유출 | B49: UT-12 | C49: 민감정보 노출 | D49: UT-12.1 | E49: 학습 데이터 암기 출력 | F49: 학습 데이터에 포함된 개인정보/비밀정보를 모델이 암기하여, 반복 토큰 등 특정 질의 패턴에 원문 그대로 출력 | G49: =IF(AN49+AO49>=2,"상",IF(OR(AN49+AO49=1,AM49>0,AB49>0,AP49>0),"중","하")) -> 중 | H49: 중 | I49: =IF(AND(G49="상",H49="상"),"매우 높음",IF(OR(AND(G49="상",H49="중"),AND(G49="중",H49="상")),"높음",IF(OR(AND(G49="중",H49="중"),AND(G49="상",H49="하"),AND(G49="하",H49="상")),"보통","낮음"))) -> 보통 | J49: ="실제 사고 "&(AN49+AO49)&"건(ATLAS "&AN49&" / OWASP "&AO49&"), 실증 사례 "&(AM49-AN49)&"건, Realized 기법 "&AB49&"개, 취약점·익스플로잇 "&AP49&"건" -> 실제 사고 0건(ATLAS 0 / OWASP 0), 실증 사례 2건, Realized 기법 0개, 취약점·익스플로잇 0건 | K49: 암기 데이터 단편 노출(대량 추출 난이도 높음) | L49: 유출(Exfiltration) | M49: 유출 | O49: ● | Q49: ● | S49: 기밀성, 규제·법적 | T49: ● | V49: ○ | W49: ○ | X49: 삭제 후에도 가중치에 잔존 시 종료 단계 위험 | Y49: T0057 | AA49: =COUNTIF(ATLAS기법매핑!$H$5:$H$212,"*"&D49&"*") -> 1 | AB49: =COUNTIFS(ATLAS기법매핑!$H$5:$H$212,"*"&D49&"*",ATLAS기법매핑!$M$5:$M$212,"Realized") -> 0 | AC49: =COUNTIFS(ATLAS기법매핑!$H$5:$H$212,"*"&D49&"*",ATLAS기법매핑!$M$5:$M$212,"Realized")&" / "&COUNTIFS(ATLAS기법매핑!$H$5:$H$212,"*"&D49&"*",ATLAS기법매핑!$M$5:$M$212,"Demonstrated")&" / "&COUNTIFS(ATLAS기법매핑!$H$5:$H$212,"*"&D49&"*",ATLAS기법매핑!$M$5:$M$212,"Feasible") -> 0 / 1 / 0 | AD49: LLM02 | AE49: LLM01 | AH49: DSGAI01 | AL49: =(LEN(Y49&Z49)>0)+(LEN(AD49&AE49)>0)+(LEN(AF49&AG49)>0)+(LEN(AH49&AI49)>0)+(LEN(AJ49&AK49)>0) -> 3 | AM49: =COUNTIF(ATLAS사례연구!$J$5:$J$77,"*"&D49&"*") -> 2 | AN49: =COUNTIFS(ATLAS사례연구!$J$5:$J$77,"*"&D49&"*",ATLAS사례연구!$C$5:$C$77,"Incident") -> 0 | AO49: 0 | AP49: 0 | AQ49: =IF(AN49+AO49>0,"실제 사고 확인",IF(AB49>0,"실사용 기법 포함",IF(OR(AM49>0,AP49>0),"실증·공개 취약점","이론·시나리오"))) -> 실증·공개 취약점 | AR49: CS0024, CS0067 | AS49: • [ATLAS CS0024·실증] RAG를 매개로 자기복제 프롬프트가 GenAI 이메일 비서 간 전파(Morris II 웜) • [ATLAS CS0067·실증] Claude Code GitHub Action이 인젝션으로 저장소 비밀값을 노출 | AT49: M0008 Validate AI Model M0020 Generative AI Guardrails M0021 Generative AI Guidelines M0022 Generative AI Model Alignment M0035 AI Red Team | AU49: 학습·색인 전 비식별화, 문서별 ACL 기반 검색, 입·출력 DLP(멀티모달 포함), 필요 최소 컨텍스트 | AV49: UT-18
A50: D03. AI 데이터 오염 및 유출 | B50: UT-12 | C50: 민감정보 노출 | D50: UT-12.2 | E50: 검색 권한 과다 노출 | F50: RAG/에이전트 도구의 검색 범위가 사용자 권한보다 넓게 설정되어, 일반 질의만으로 열람 권한 없는 문서/데이터가 응답에 포함 | G50: =IF(AN50+AO50>=2,"상",IF(OR(AN50+AO50=1,AM50>0,AB50>0,AP50>0),"중","하")) -> 중 | H50: 상 | I50: =IF(AND(G50="상",H50="상"),"매우 높음",IF(OR(AND(G50="상",H50="중"),AND(G50="중",H50="상")),"높음",IF(OR(AND(G50="중",H50="중"),AND(G50="상",H50="하"),AND(G50="하",H50="상")),"보통","낮음"))) -> 높음 | J50: ="실제 사고 "&(AN50+AO50)&"건(ATLAS "&AN50&" / OWASP "&AO50&"), 실증 사례 "&(AM50-AN50)&"건, Realized 기법 "&AB50&"개, 취약점·익스플로잇 "&AP50&"건" -> 실제 사고 0건(ATLAS 0 / OWASP 0), 실증 사례 7건, Realized 기법 0개, 취약점·익스플로잇 1건 | K50: 열람 권한 밖 중요정보 대량 노출 | L50: 수집(Collection) | M50: 수집 | O50: ● | P50: ● | Q50: ● | S50: 기밀성, 규제·법적 | T50: ● | V50: ○ | Y50: T0085, T0085.000, T0085.001 | AA50: =COUNTIF(ATLAS기법매핑!$H$5:$H$212,"*"&D50&"*") -> 3 | AB50: =COUNTIFS(ATLAS기법매핑!$H$5:$H$212,"*"&D50&"*",ATLAS기법매핑!$M$5:$M$212,"Realized") -> 0 | AC50: =COUNTIFS(ATLAS기법매핑!$H$5:$H$212,"*"&D50&"*",ATLAS기법매핑!$M$5:$M$212,"Realized")&" / "&COUNTIFS(ATLAS기법매핑!$H$5:$H$212,"*"&D50&"*",ATLAS기법매핑!$M$5:$M$212,"Demonstrated")&" / "&COUNTIFS(ATLAS기법매핑!$H$5:$H$212,"*"&D50&"*",ATLAS기법매핑!$M$5:$M$212,"Feasible") -> 0 / 3 / 0 | AD50: LLM02 | AE50: LLM03 | AG50: ASI03 | AH50: DSGAI01 | AK50: MCP10 | AL50: =(LEN(Y50&Z50)>0)+(LEN(AD50&AE50)>0)+(LEN(AF50&AG50)>0)+(LEN(AH50&AI50)>0)+(LEN(AJ50&AK50)>0) -> 5 | AM50: =COUNTIF(ATLAS사례연구!$J$5:$J$77,"*"&D50&"*") -> 7 | AN50: =COUNTIFS(ATLAS사례연구!$J$5:$J$77,"*"&D50&"*",ATLAS사례연구!$C$5:$C$77,"Incident") -> 0 | AO50: 0 | AP50: 1 | AQ50: =IF(AN50+AO50>0,"실제 사고 확인",IF(AB50>0,"실사용 기법 포함",IF(OR(AM50>0,AP50>0),"실증·공개 취약점","이론·시나리오"))) -> 실증·공개 취약점 | AR50: CS0035, CS0037, CS0038, CS0039, CS0059, CS0063, CS0066 | AS50: • [ATLAS CS0035·실증] 공개 채널 게시글의 간접 인젝션으로 Slack AI가 비공개 채널 데이터 유출 • [ATLAS CS0037·실증] Copilot Studio 고객지원 에이전트를 인젝션해 지식원·도구를 탐색하고 CRM 데이터 유출 • [ATLAS CS0038·실증] 지시 실행을 다음 대화 턴으로 지연시켜 Gemini의 도구 호출 제한 우회 • [OWASP 인용] CVE-2026-0612 The Librarian 정보 유출 취약점 | AT50: M0024 AI Telemetry Logging M0026 Privileged AI Agent Permissions Configuration M0027 Single-User AI Agent Permissions Configuration M0032 Segmentation of AI Agent Components M0028 AI Agent Tools Permissions Configuration | AU50: 학습·색인 전 비식별화, 문서별 ACL 기반 검색, 입·출력 DLP(멀티모달 포함), 필요 최소 컨텍스트 | AV50: UT-18
A51: D03. AI 데이터 오염 및 유출 | B51: UT-12 | C51: 민감정보 노출 | D51: UT-12.3 | E51: 프롬프트 과다 공유 | F51: 업무 처리에 불필요한 전체 고객 기록/내부 문서를 프롬프트에 포함하여 외부 AI 제공자 및 하위 처리자에게 전송함으로써 조직 통제 밖으로 데이터 유출 | G51: =IF(AN51+AO51>=2,"상",IF(OR(AN51+AO51=1,AM51>0,AB51>0,AP51>0),"중","하")) -> 하 | H51: 중 | I51: =IF(AND(G51="상",H51="상"),"매우 높음",IF(OR(AND(G51="상",H51="중"),AND(G51="중",H51="상")),"높음",IF(OR(AND(G51="중",H51="중"),AND(G51="상",H51="하"),AND(G51="하",H51="상")),"보통","낮음"))) -> 낮음 | J51: ="실제 사고 "&(AN51+AO51)&"건(ATLAS "&AN51&" / OWASP "&AO51&"), 실증 사례 "&(AM51-AN51)&"건, Realized 기법 "&AB51&"개, 취약점·익스플로잇 "&AP51&"건" -> 실제 사고 0건(ATLAS 0 / OWASP 0), 실증 사례 0건, Realized 기법 0개, 취약점·익스플로잇 0건 | K51: 외부 제공자 범위 노출(계약 통제 가능) | L51: 해당 없음(구조적 결함) | M51: — | O51: ● | P51: ● | Q51: ● | S51: 기밀성, 규제·법적 | T51: ○ | V51: ● | AA51: =COUNTIF(ATLAS기법매핑!$H$5:$H$212,"*"&D51&"*") -> 0 | AB51: =COUNTIFS(ATLAS기법매핑!$H$5:$H$212,"*"&D51&"*",ATLAS기법매핑!$M$5:$M$212,"Realized") -> 0 | AC51: =COUNTIFS(ATLAS기법매핑!$H$5:$H$212,"*"&D51&"*",ATLAS기법매핑!$M$5:$M$212,"Realized")&" / "&COUNTIFS(ATLAS기법매핑!$H$5:$H$212,"*"&D51&"*",ATLAS기법매핑!$M$5:$M$212,"Demonstrated")&" / "&COUNTIFS(ATLAS기법매핑!$H$5:$H$212,"*"&D51&"*",ATLAS기법매핑!$M$5:$M$212,"Feasible") -> 0 / 0 / 0 | AE51: LLM02 | AH51: DSGAI15 | AL51: =(LEN(Y51&Z51)>0)+(LEN(AD51&AE51)>0)+(LEN(AF51&AG51)>0)+(LEN(AH51&AI51)>0)+(LEN(AJ51&AK51)>0) -> 2 | AM51: =COUNTIF(ATLAS사례연구!$J$5:$J$77,"*"&D51&"*") -> 0 | AN51: =COUNTIFS(ATLAS사례연구!$J$5:$J$77,"*"&D51&"*",ATLAS사례연구!$C$5:$C$77,"Incident") -> 0 | AO51: 0 | AP51: 0 | AQ51: =IF(AN51+AO51>0,"실제 사고 확인",IF(AB51>0,"실사용 기법 포함",IF(OR(AM51>0,AP51>0),"실증·공개 취약점","이론·시나리오"))) -> 이론·시나리오 | AS51: • [OWASP 시나리오] 잔액 조회마다 전체 KYC 파일을 프롬프트에 포함한 뱅킹 비서(DSGAI15 시나리오) | AT51: — (ATLAS 완화책 없음: Lv2 핵심 통제 참조) | AU51: 학습·색인 전 비식별화, 문서별 ACL 기반 검색, 입·출력 DLP(멀티모달 포함), 필요 최소 컨텍스트 | AV51: UT-18
A52: D03. AI 데이터 오염 및 유출 | B52: UT-12 | C52: 민감정보 노출 | D52: UT-12.4 | E52: 멀티모달 입력 노출 | F52: 스크린샷/문서 이미지/음성 등 멀티모달 입력에 포함된 민감정보가 텍스트 기반 DLP를 우회하여 AI 서비스 및 로그로 전달 | G52: =IF(AN52+AO52>=2,"상",IF(OR(AN52+AO52=1,AM52>0,AB52>0,AP52>0),"중","하")) -> 하 | H52: 중 | I52: =IF(AND(G52="상",H52="상"),"매우 높음",IF(OR(AND(G52="상",H52="중"),AND(G52="중",H52="상")),"높음",IF(OR(AND(G52="중",H52="중"),AND(G52="상",H52="하"),AND(G52="하",H52="상")),"보통","낮음"))) -> 낮음 | J52: ="실제 사고 "&(AN52+AO52)&"건(ATLAS "&AN52&" / OWASP "&AO52&"), 실증 사례 "&(AM52-AN52)&"건, Realized 기법 "&AB52&"개, 취약점·익스플로잇 "&AP52&"건" -> 실제 사고 0건(ATLAS 0 / OWASP 0), 실증 사례 0건, Realized 기법 0개, 취약점·익스플로잇 0건 | K52: 텍스트 DLP 우회 노출(입력 범위) | L52: 해당 없음(구조적 결함) | M52: — | O52: ● | Q52: ● | S52: 기밀성, 규제·법적 | V52: ● | AA52: =COUNTIF(ATLAS기법매핑!$H$5:$H$212,"*"&D52&"*") -> 0 | AB52: =COUNTIFS(ATLAS기법매핑!$H$5:$H$212,"*"&D52&"*",ATLAS기법매핑!$M$5:$M$212,"Realized") -> 0 | AC52: =COUNTIFS(ATLAS기법매핑!$H$5:$H$212,"*"&D52&"*",ATLAS기법매핑!$M$5:$M$212,"Realized")&" / "&COUNTIFS(ATLAS기법매핑!$H$5:$H$212,"*"&D52&"*",ATLAS기법매핑!$M$5:$M$212,"Demonstrated")&" / "&COUNTIFS(ATLAS기법매핑!$H$5:$H$212,"*"&D52&"*",ATLAS기법매핑!$M$5:$M$212,"Feasible") -> 0 / 0 / 0 | AE52: LLM02 | AH52: DSGAI09 | AL52: =(LEN(Y52&Z52)>0)+(LEN(AD52&AE52)>0)+(LEN(AF52&AG52)>0)+(LEN(AH52&AI52)>0)+(LEN(AJ52&AK52)>0) -> 2 | AM52: =COUNTIF(ATLAS사례연구!$J$5:$J$77,"*"&D52&"*") -> 0 | AN52: =COUNTIFS(ATLAS사례연구!$J$5:$J$77,"*"&D52&"*",ATLAS사례연구!$C$5:$C$77,"Incident") -> 0 | AO52: 0 | AP52: 0 | AQ52: =IF(AN52+AO52>0,"실제 사고 확인",IF(AB52>0,"실사용 기법 포함",IF(OR(AM52>0,AP52>0),"실증·공개 취약점","이론·시나리오"))) -> 이론·시나리오 | AS52: • [OWASP 시나리오] API 키가 보이는 관리자 화면 스크린샷을 AI에 공유(DSGAI09 시나리오) | AT52: — (ATLAS 완화책 없음: Lv2 핵심 통제 참조) | AU52: 학습·색인 전 비식별화, 문서별 ACL 기반 검색, 입·출력 DLP(멀티모달 포함), 필요 최소 컨텍스트 | AV52: UT-18
A53: D03. AI 데이터 오염 및 유출 | B53: UT-13 | C53: 사용자 간 데이터 격리 실패 | D53: UT-13.1 | E53: 세션 간 데이터 혼입 | F53: KV 캐시/세션 상태/공유 대화 컨텍스트의 격리 결함으로 한 사용자의 프롬프트와 응답이 다른 사용자 세션에 노출 | G53: =IF(AN53+AO53>=2,"상",IF(OR(AN53+AO53=1,AM53>0,AB53>0,AP53>0),"중","하")) -> 중 | H53: 중 | I53: =IF(AND(G53="상",H53="상"),"매우 높음",IF(OR(AND(G53="상",H53="중"),AND(G53="중",H53="상")),"높음",IF(OR(AND(G53="중",H53="중"),AND(G53="상",H53="하"),AND(G53="하",H53="상")),"보통","낮음"))) -> 보통 | J53: ="실제 사고 "&(AN53+AO53)&"건(ATLAS "&AN53&" / OWASP "&AO53&"), 실증 사례 "&(AM53-AN53)&"건, Realized 기법 "&AB53&"개, 취약점·익스플로잇 "&AP53&"건" -> 실제 사고 0건(ATLAS 0 / OWASP 0), 실증 사례 0건, Realized 기법 0개, 취약점·익스플로잇 1건 | K53: 타 사용자 대화 일부 노출(비의도적, 범위 가변) | L53: 수집(Collection) | M53: — | P53: ● | Q53: ● | R53: ● | S53: 기밀성, 규제·법적 | T53: ● | U53: ○ | V53: ○ | AA53: =COUNTIF(ATLAS기법매핑!$H$5:$H$212,"*"&D53&"*") -> 0 | AB53: =COUNTIFS(ATLAS기법매핑!$H$5:$H$212,"*"&D53&"*",ATLAS기법매핑!$M$5:$M$212,"Realized") -> 0 | AC53: =COUNTIFS(ATLAS기법매핑!$H$5:$H$212,"*"&D53&"*",ATLAS기법매핑!$M$5:$M$212,"Realized")&" / "&COUNTIFS(ATLAS기법매핑!$H$5:$H$212,"*"&D53&"*",ATLAS기법매핑!$M$5:$M$212,"Demonstrated")&" / "&COUNTIFS(ATLAS기법매핑!$H$5:$H$212,"*"&D53&"*",ATLAS기법매핑!$M$5:$M$212,"Feasible") -> 0 / 0 / 0 | AE53: LLM02 | AH53: DSGAI11 | AJ53: MCP10 | AL53: =(LEN(Y53&Z53)>0)+(LEN(AD53&AE53)>0)+(LEN(AF53&AG53)>0)+(LEN(AH53&AI53)>0)+(LEN(AJ53&AK53)>0) -> 3 | AM53: =COUNTIF(ATLAS사례연구!$J$5:$J$77,"*"&D53&"*") -> 0 | AN53: =COUNTIFS(ATLAS사례연구!$J$5:$J$77,"*"&D53&"*",ATLAS사례연구!$C$5:$C$77,"Incident") -> 0 | AO53: 0 | AP53: 1 | AQ53: =IF(AN53+AO53>0,"실제 사고 확인",IF(AB53>0,"실사용 기법 포함",IF(OR(AM53>0,AP53>0),"실증·공개 취약점","이론·시나리오"))) -> 실증·공개 취약점 | AS53: • [OWASP 인용] CVE-2025-6515 oatpp-mcp 세션 식별자 결함 • [OWASP 시나리오] 공유 추론 상태 결함으로 타 사용자의 의료 서신 노출(LLM02 시나리오#2) | AT53: — (ATLAS 완화책 없음: Lv2 핵심 통제 참조) | AU53: 검색 전 테넌트 필터, 테넌트별 인덱스·캐시 분리, 벡터 DB 인증·암호화·내보내기 제한 | AV53: UT-22
A54: D03. AI 데이터 오염 및 유출 | B54: UT-13 | C54: 사용자 간 데이터 격리 실패 | D54: UT-13.2 | E54: 테넌트 간 인덱스 유출 | F54: 공유 벡터 인덱스의 검색 후 필터링 구조로 인해 다른 테넌트 데이터가 검색 결과/유사도 점수/응답 지연을 통해 노출 | G54: =IF(AN54+AO54>=2,"상",IF(OR(AN54+AO54=1,AM54>0,AB54>0,AP54>0),"중","하")) -> 하 | H54: 상 | I54: =IF(AND(G54="상",H54="상"),"매우 높음",IF(OR(AND(G54="상",H54="중"),AND(G54="중",H54="상")),"높음",IF(OR(AND(G54="중",H54="중"),AND(G54="상",H54="하"),AND(G54="하",H54="상")),"보통","낮음"))) -> 보통 | J54: ="실제 사고 "&(AN54+AO54)&"건(ATLAS "&AN54&" / OWASP "&AO54&"), 실증 사례 "&(AM54-AN54)&"건, Realized 기법 "&AB54&"개, 취약점·익스플로잇 "&AP54&"건" -> 실제 사고 0건(ATLAS 0 / OWASP 0), 실증 사례 0건, Realized 기법 0개, 취약점·익스플로잇 0건 | K54: 타 고객사 데이터 노출(다수 테넌트) | L54: 수집(Collection) | M54: 수집 | P54: ● | Q54: ● | R54: ● | S54: 기밀성, 규제·법적 | T54: ● | U54: ○ | V54: ○ | Z54: T0085.000 | AA54: =COUNTIF(ATLAS기법매핑!$H$5:$H$212,"*"&D54&"*") -> 1 | AB54: =COUNTIFS(ATLAS기법매핑!$H$5:$H$212,"*"&D54&"*",ATLAS기법매핑!$M$5:$M$212,"Realized") -> 0 | AC54: =COUNTIFS(ATLAS기법매핑!$H$5:$H$212,"*"&D54&"*",ATLAS기법매핑!$M$5:$M$212,"Realized")&" / "&COUNTIFS(ATLAS기법매핑!$H$5:$H$212,"*"&D54&"*",ATLAS기법매핑!$M$5:$M$212,"Demonstrated")&" / "&COUNTIFS(ATLAS기법매핑!$H$5:$H$212,"*"&D54&"*",ATLAS기법매핑!$M$5:$M$212,"Feasible") -> 0 / 1 / 0 | AD54: LLM09 | AE54: LLM02 | AG54: ASI06 | AL54: =(LEN(Y54&Z54)>0)+(LEN(AD54&AE54)>0)+(LEN(AF54&AG54)>0)+(LEN(AH54&AI54)>0)+(LEN(AJ54&AK54)>0) -> 3 | AM54: =COUNTIF(ATLAS사례연구!$J$5:$J$77,"*"&D54&"*") -> 0 | AN54: =COUNTIFS(ATLAS사례연구!$J$5:$J$77,"*"&D54&"*",ATLAS사례연구!$C$5:$C$77,"Incident") -> 0 | AO54: 0 | AP54: 0 | AQ54: =IF(AN54+AO54>0,"실제 사고 확인",IF(AB54>0,"실사용 기법 포함",IF(OR(AM54>0,AP54>0),"실증·공개 취약점","이론·시나리오"))) -> 이론·시나리오 | AS54: • [OWASP 시나리오] 공유 벡터 인덱스의 교차 테넌트 추론(LLM09 시나리오#2), 로펌 간 공유 RAG 인덱스 유출(LLM02 시나리오#5) | AT54: M0024 AI Telemetry Logging M0026 Privileged AI Agent Permissions Configuration M0027 Single-User AI Agent Permissions Configuration M0032 Segmentation of AI Agent Components | AU54: 검색 전 테넌트 필터, 테넌트별 인덱스·캐시 분리, 벡터 DB 인증·암호화·내보내기 제한 | AV54: UT-22
A55: D03. AI 데이터 오염 및 유출 | B55: UT-13 | C55: 사용자 간 데이터 격리 실패 | D55: UT-13.3 | E55: 벡터 DB 플랫폼 취약점 | F55: 벡터 DB의 인증 미적용/기본 설정/경로 탐색 취약점을 악용하여 임베딩 및 원문 데이터 대량 탈취 또는 서버 장악 | G55: =IF(AN55+AO55>=2,"상",IF(OR(AN55+AO55=1,AM55>0,AB55>0,AP55>0),"중","하")) -> 중 | H55: 상 | I55: =IF(AND(G55="상",H55="상"),"매우 높음",IF(OR(AND(G55="상",H55="중"),AND(G55="중",H55="상")),"높음",IF(OR(AND(G55="중",H55="중"),AND(G55="상",H55="하"),AND(G55="하",H55="상")),"보통","낮음"))) -> 높음 | J55: ="실제 사고 "&(AN55+AO55)&"건(ATLAS "&AN55&" / OWASP "&AO55&"), 실증 사례 "&(AM55-AN55)&"건, Realized 기법 "&AB55&"개, 취약점·익스플로잇 "&AP55&"건" -> 실제 사고 0건(ATLAS 0 / OWASP 0), 실증 사례 0건, Realized 기법 0개, 취약점·익스플로잇 4건 | K55: 임베딩/원문 대량 탈취 및 서버 장악(RCE) | L55: 초기 접근(Initial Access) | M55: — | P55: ● | S55: 기밀성, 무결성 | T55: ○ | U55: ● | V55: ○ | AA55: =COUNTIF(ATLAS기법매핑!$H$5:$H$212,"*"&D55&"*") -> 0 | AB55: =COUNTIFS(ATLAS기법매핑!$H$5:$H$212,"*"&D55&"*",ATLAS기법매핑!$M$5:$M$212,"Realized") -> 0 | AC55: =COUNTIFS(ATLAS기법매핑!$H$5:$H$212,"*"&D55&"*",ATLAS기법매핑!$M$5:$M$212,"Realized")&" / "&COUNTIFS(ATLAS기법매핑!$H$5:$H$212,"*"&D55&"*",ATLAS기법매핑!$M$5:$M$212,"Demonstrated")&" / "&COUNTIFS(ATLAS기법매핑!$H$5:$H$212,"*"&D55&"*",ATLAS기법매핑!$M$5:$M$212,"Feasible") -> 0 / 0 / 0 | AE55: LLM09 | AH55: DSGAI13 | AI55: DSGAI05 | AL55: =(LEN(Y55&Z55)>0)+(LEN(AD55&AE55)>0)+(LEN(AF55&AG55)>0)+(LEN(AH55&AI55)>0)+(LEN(AJ55&AK55)>0) -> 2 | AM55: =COUNTIF(ATLAS사례연구!$J$5:$J$77,"*"&D55&"*") -> 0 | AN55: =COUNTIFS(ATLAS사례연구!$J$5:$J$77,"*"&D55&"*",ATLAS사례연구!$C$5:$C$77,"Incident") -> 0 | AO55: 0 | AP55: 4 | AQ55: =IF(AN55+AO55>0,"실제 사고 확인",IF(AB55>0,"실사용 기법 포함",IF(OR(AM55>0,AP55>0),"실증·공개 취약점","이론·시나리오"))) -> 실증·공개 취약점 | AS55: • [OWASP 인용] Qdrant CVE-2024-3584·CVE-2024-3829 / Milvus CVE-2025-64513 / RAGFlow CVE-2025-69286 | AT55: — (ATLAS 완화책 없음: Lv2 핵심 통제 참조) | AU55: 검색 전 테넌트 필터, 테넌트별 인덱스·캐시 분리, 벡터 DB 인증·암호화·내보내기 제한 | AV55: UT-22
A56: D04. 모델 조작 및 탈취 | B56: UT-14 | C56: 모델 변조(백도어 삽입) | D56: UT-14.1 | E56: 가중치 조작 | F56: 모델 가중치를 직접 편집하거나 오염 데이터로 추가 학습하여, 일반 성능은 유지한 채 특정 질의에만 허위 응답/악성 동작을 수행하는 모델 생성 | G56: =IF(AN56+AO56>=2,"상",IF(OR(AN56+AO56=1,AM56>0,AB56>0,AP56>0),"중","하")) -> 중 | H56: 중 | I56: =IF(AND(G56="상",H56="상"),"매우 높음",IF(OR(AND(G56="상",H56="중"),AND(G56="중",H56="상")),"높음",IF(OR(AND(G56="중",H56="중"),AND(G56="상",H56="하"),AND(G56="하",H56="상")),"보통","낮음"))) -> 보통 | J56: ="실제 사고 "&(AN56+AO56)&"건(ATLAS "&AN56&" / OWASP "&AO56&"), 실증 사례 "&(AM56-AN56)&"건, Realized 기법 "&AB56&"개, 취약점·익스플로잇 "&AP56&"건" -> 실제 사고 0건(ATLAS 0 / OWASP 0), 실증 사례 3건, Realized 기법 1개, 취약점·익스플로잇 0건 | K56: 특정 질의 대상 허위 응답(무결성 훼손) | L56: 지속성(Persistence) | M56: AI 공격 적응, 지속성 | N56: ● | O56: ● | S56: 무결성, 안전·사용자 | T56: ● | U56: ○ | V56: ○ | Y56: T0018, T0018.000 | AA56: =COUNTIF(ATLAS기법매핑!$H$5:$H$212,"*"&D56&"*") -> 2 | AB56: =COUNTIFS(ATLAS기법매핑!$H$5:$H$212,"*"&D56&"*",ATLAS기법매핑!$M$5:$M$212,"Realized") -> 1 | AC56: =COUNTIFS(ATLAS기법매핑!$H$5:$H$212,"*"&D56&"*",ATLAS기법매핑!$M$5:$M$212,"Realized")&" / "&COUNTIFS(ATLAS기법매핑!$H$5:$H$212,"*"&D56&"*",ATLAS기법매핑!$M$5:$M$212,"Demonstrated")&" / "&COUNTIFS(ATLAS기법매핑!$H$5:$H$212,"*"&D56&"*",ATLAS기법매핑!$M$5:$M$212,"Feasible") -> 1 / 1 / 0 | AD56: LLM05 | AE56: LLM04 | AH56: DSGAI04 | AL56: =(LEN(Y56&Z56)>0)+(LEN(AD56&AE56)>0)+(LEN(AF56&AG56)>0)+(LEN(AH56&AI56)>0)+(LEN(AJ56&AK56)>0) -> 3 | AM56: =COUNTIF(ATLAS사례연구!$J$5:$J$77,"*"&D56&"*") -> 3 | AN56: =COUNTIFS(ATLAS사례연구!$J$5:$J$77,"*"&D56&"*",ATLAS사례연구!$C$5:$C$77,"Incident") -> 0 | AO56: 0 | AP56: 0 | AQ56: =IF(AN56+AO56>0,"실제 사고 확인",IF(AB56>0,"실사용 기법 포함",IF(OR(AM56>0,AP56>0),"실증·공개 취약점","이론·시나리오"))) -> 실사용 기법 포함 | AR56: CS0019, CS0027, CS0028 | AS56: • [ATLAS CS0019·실증] LLM 가중치를 편집해 허위 사실을 답하게 만든 뒤 Hugging Face에 배포(PoisonGPT) • [ATLAS CS0027·실증] 실존 기업을 사칭한 Hugging Face 조직 계정으로 악성 모델 유포 • [ATLAS CS0028·실증] 노출된 사설 컨테이너 레지스트리 8천여 개 발견, 모델 이미지 변조 가능성 입증 | AT56: M0005 Control Access to AI Models and Data at Rest M0008 Validate AI Model M0013 Code Signing M0035 AI Red Team M0007 Sanitize Training Data | AU56: 아티팩트 서명·해시 검증, 안전 포맷 사용 및 로딩 격리, 배포 전 모델 검증·백도어 스캔 | AV56: UT-08, UT-05(일부)
A57: D04. 모델 조작 및 탈취 | B57: UT-14 | C57: 모델 변조(백도어 삽입) | D57: UT-14.2 | E57: 모델 구조 변조 | F57: 모델 아키텍처/로딩 코드 변경 또는 모델 파일 내 악성 코드 삽입을 통해 모델 로딩 시점에 임의 코드 실행 또는 백도어 동작 활성화 | G57: =IF(AN57+AO57>=2,"상",IF(OR(AN57+AO57=1,AM57>0,AB57>0,AP57>0),"중","하")) -> 중 | H57: 상 | I57: =IF(AND(G57="상",H57="상"),"매우 높음",IF(OR(AND(G57="상",H57="중"),AND(G57="중",H57="상")),"높음",IF(OR(AND(G57="중",H57="중"),AND(G57="상",H57="하"),AND(G57="하",H57="상")),"보통","낮음"))) -> 높음 | J57: ="실제 사고 "&(AN57+AO57)&"건(ATLAS "&AN57&" / OWASP "&AO57&"), 실증 사례 "&(AM57-AN57)&"건, Realized 기법 "&AB57&"개, 취약점·익스플로잇 "&AP57&"건" -> 실제 사고 1건(ATLAS 1 / OWASP 0), 실증 사례 4건, Realized 기법 2개, 취약점·익스플로잇 0건 | K57: 모델 로딩 시 호스트 코드 실행 | L57: 지속성(Persistence) | M57: AI 공격 적응, 지속성, 방어 회피, 영향 | N57: ● | O57: ● | S57: 무결성, 안전·사용자 | T57: ○ | U57: ● | Y57: T0018.001, T0018.002, T0076, T0112.001 | AA57: =COUNTIF(ATLAS기법매핑!$H$5:$H$212,"*"&D57&"*") -> 4 | AB57: =COUNTIFS(ATLAS기법매핑!$H$5:$H$212,"*"&D57&"*",ATLAS기법매핑!$M$5:$M$212,"Realized") -> 2 | AC57: =COUNTIFS(ATLAS기법매핑!$H$5:$H$212,"*"&D57&"*",ATLAS기법매핑!$M$5:$M$212,"Realized")&" / "&COUNTIFS(ATLAS기법매핑!$H$5:$H$212,"*"&D57&"*",ATLAS기법매핑!$M$5:$M$212,"Demonstrated")&" / "&COUNTIFS(ATLAS기법매핑!$H$5:$H$212,"*"&D57&"*",ATLAS기법매핑!$M$5:$M$212,"Feasible") -> 2 / 1 / 1 | AH57: DSGAI04 | AI57: DSGAI05 | AK57: MCP04 | AL57: =(LEN(Y57&Z57)>0)+(LEN(AD57&AE57)>0)+(LEN(AF57&AG57)>0)+(LEN(AH57&AI57)>0)+(LEN(AJ57&AK57)>0) -> 3 | AM57: =COUNTIF(ATLAS사례연구!$J$5:$J$77,"*"&D57&"*") -> 5 | AN57: =COUNTIFS(ATLAS사례연구!$J$5:$J$77,"*"&D57&"*",ATLAS사례연구!$C$5:$C$77,"Incident") -> 1 | AO57: 0 | AP57: 0 | AQ57: =IF(AN57+AO57>0,"실제 사고 확인",IF(AB57>0,"실사용 기법 포함",IF(OR(AM57>0,AP57>0),"실증·공개 취약점","이론·시나리오"))) -> 실제 사고 확인 | AR57: CS0013, CS0027, CS0028, CS0031, CS0065 | AS57: • [ATLAS CS0013·실증] 모바일 앱에서 추출한 딥러닝 모델에 백도어 삽입 후 재패키징 • [ATLAS CS0031·실제사고] Hugging Face에 역쉘을 내장한 악성 모델 호스팅(실제 사고) • [ATLAS CS0027·실증] 실존 기업을 사칭한 Hugging Face 조직 계정으로 악성 모델 유포 | AT57: M0005 Control Access to AI Models and Data at Rest M0013 Code Signing M0008 Validate AI Model M0035 AI Red Team | AU57: 아티팩트 서명·해시 검증, 안전 포맷 사용 및 로딩 격리, 배포 전 모델 검증·백도어 스캔 | AV57: UT-08, UT-05(일부)
A58: D04. 모델 조작 및 탈취 | B58: UT-14 | C58: 모델 변조(백도어 삽입) | D58: UT-14.3 | E58: 추론 템플릿 변조 | F58: 채팅 템플릿(예: GGUF)/프롬프트 구성 로직에 조건부 지시를 삽입하여 가중치 변경 없이 추론 시점에 백도어 동작 유발 | G58: =IF(AN58+AO58>=2,"상",IF(OR(AN58+AO58=1,AM58>0,AB58>0,AP58>0),"중","하")) -> 중 | H58: 중 | I58: =IF(AND(G58="상",H58="상"),"매우 높음",IF(OR(AND(G58="상",H58="중"),AND(G58="중",H58="상")),"높음",IF(OR(AND(G58="중",H58="중"),AND(G58="상",H58="하"),AND(G58="하",H58="상")),"보통","낮음"))) -> 보통 | J58: ="실제 사고 "&(AN58+AO58)&"건(ATLAS "&AN58&" / OWASP "&AO58&"), 실증 사례 "&(AM58-AN58)&"건, Realized 기법 "&AB58&"개, 취약점·익스플로잇 "&AP58&"건" -> 실제 사고 0건(ATLAS 0 / OWASP 0), 실증 사례 1건, Realized 기법 0개, 취약점·익스플로잇 0건 | K58: 가중치 변경 없는 응답 조작(무결성 훼손) | L58: 지속성(Persistence) | M58: AI 공격 적응, 지속성 | O58: ● | S58: 무결성, 안전·사용자 | U58: ● | V58: ○ | Y58: T0018.003 | AA58: =COUNTIF(ATLAS기법매핑!$H$5:$H$212,"*"&D58&"*") -> 1 | AB58: =COUNTIFS(ATLAS기법매핑!$H$5:$H$212,"*"&D58&"*",ATLAS기법매핑!$M$5:$M$212,"Realized") -> 0 | AC58: =COUNTIFS(ATLAS기법매핑!$H$5:$H$212,"*"&D58&"*",ATLAS기법매핑!$M$5:$M$212,"Realized")&" / "&COUNTIFS(ATLAS기법매핑!$H$5:$H$212,"*"&D58&"*",ATLAS기법매핑!$M$5:$M$212,"Demonstrated")&" / "&COUNTIFS(ATLAS기법매핑!$H$5:$H$212,"*"&D58&"*",ATLAS기법매핑!$M$5:$M$212,"Feasible") -> 0 / 1 / 0 | AD58: LLM05 | AG58: ASI04 | AL58: =(LEN(Y58&Z58)>0)+(LEN(AD58&AE58)>0)+(LEN(AF58&AG58)>0)+(LEN(AH58&AI58)>0)+(LEN(AJ58&AK58)>0) -> 3 | AM58: =COUNTIF(ATLAS사례연구!$J$5:$J$77,"*"&D58&"*") -> 1 | AN58: =COUNTIFS(ATLAS사례연구!$J$5:$J$77,"*"&D58&"*",ATLAS사례연구!$C$5:$C$77,"Incident") -> 0 | AO58: 0 | AP58: 0 | AQ58: =IF(AN58+AO58>0,"실제 사고 확인",IF(AB58>0,"실사용 기법 포함",IF(OR(AM58>0,AP58>0),"실증·공개 취약점","이론·시나리오"))) -> 실증·공개 취약점 | AR58: CS0064 | AS58: • [ATLAS CS0064·실증] GGUF 채팅 템플릿을 오염시켜 가중치 변경 없이 추론 시점 백도어 구현 | AT58: — (ATLAS 완화책 없음: Lv2 핵심 통제 참조) | AU58: 아티팩트 서명·해시 검증, 안전 포맷 사용 및 로딩 격리, 배포 전 모델 검증·백도어 스캔 | AV58: UT-08, UT-05(일부)
A59: D04. 모델 조작 및 탈취 | B59: UT-14 | C59: 모델 변조(백도어 삽입) | D59: UT-14.4 | E59: 백도어 트리거 활성화 | F59: 학습 단계에서 심어진 백도어를 특정 패턴(이미지 패치/키워드)이 포함된 입력으로 활성화하여 공격자 지정 출력 유도 | G59: =IF(AN59+AO59>=2,"상",IF(OR(AN59+AO59=1,AM59>0,AB59>0,AP59>0),"중","하")) -> 중 | H59: 중 | I59: =IF(AND(G59="상",H59="상"),"매우 높음",IF(OR(AND(G59="상",H59="중"),AND(G59="중",H59="상")),"높음",IF(OR(AND(G59="중",H59="중"),AND(G59="상",H59="하"),AND(G59="하",H59="상")),"보통","낮음"))) -> 보통 | J59: ="실제 사고 "&(AN59+AO59)&"건(ATLAS "&AN59&" / OWASP "&AO59&"), 실증 사례 "&(AM59-AN59)&"건, Realized 기법 "&AB59&"개, 취약점·익스플로잇 "&AP59&"건" -> 실제 사고 0건(ATLAS 0 / OWASP 0), 실증 사례 1건, Realized 기법 0개, 취약점·익스플로잇 0건 | K59: 트리거 조건 범위 내 오작동 | L59: AI 공격 적응(AI Attack Adaptation) | M59: AI 공격 적응 | N59: ● | O59: ● | S59: 무결성, 안전·사용자 | V59: ● | Y59: T0043.004 | AA59: =COUNTIF(ATLAS기법매핑!$H$5:$H$212,"*"&D59&"*") -> 1 | AB59: =COUNTIFS(ATLAS기법매핑!$H$5:$H$212,"*"&D59&"*",ATLAS기법매핑!$M$5:$M$212,"Realized") -> 0 | AC59: =COUNTIFS(ATLAS기법매핑!$H$5:$H$212,"*"&D59&"*",ATLAS기법매핑!$M$5:$M$212,"Realized")&" / "&COUNTIFS(ATLAS기법매핑!$H$5:$H$212,"*"&D59&"*",ATLAS기법매핑!$M$5:$M$212,"Demonstrated")&" / "&COUNTIFS(ATLAS기법매핑!$H$5:$H$212,"*"&D59&"*",ATLAS기법매핑!$M$5:$M$212,"Feasible") -> 0 / 1 / 0 | AD59: LLM05 | AI59: DSGAI04 | AL59: =(LEN(Y59&Z59)>0)+(LEN(AD59&AE59)>0)+(LEN(AF59&AG59)>0)+(LEN(AH59&AI59)>0)+(LEN(AJ59&AK59)>0) -> 3 | AM59: =COUNTIF(ATLAS사례연구!$J$5:$J$77,"*"&D59&"*") -> 1 | AN59: =COUNTIFS(ATLAS사례연구!$J$5:$J$77,"*"&D59&"*",ATLAS사례연구!$C$5:$C$77,"Incident") -> 0 | AO59: 0 | AP59: 0 | AQ59: =IF(AN59+AO59>0,"실제 사고 확인",IF(AB59>0,"실사용 기법 포함",IF(OR(AM59>0,AP59>0),"실증·공개 취약점","이론·시나리오"))) -> 실증·공개 취약점 | AR59: CS0013 | AS59: • [ATLAS CS0013·실증] 모바일 앱에서 추출한 딥러닝 모델에 백도어 삽입 후 재패키징 • [OWASP 시나리오] 백도어 트리거를 포함한 입력으로 오염 모델 활성화(ATLAS T0043.004 기법 정의) | AT59: M0003 Predictive AI Model Hardening M0006 Predictive AI Ensembles M0008 Validate AI Model M0010 Predictive AI Input Restoration M0015 Predictive AI Adversarial Input Detection | AU59: 아티팩트 서명·해시 검증, 안전 포맷 사용 및 로딩 격리, 배포 전 모델 검증·백도어 스캔 | AV59: UT-08, UT-05(일부)
A60: D04. 모델 조작 및 탈취 | B60: UT-15 | C60: 모델을 이용한 데이터 추론 공격 | D60: UT-15.1 | E60: 멤버십 추론 | F60: 모델 응답의 확신도/손실 패턴을 분석하여 특정 개인/레코드의 학습 데이터 포함 여부를 판별 | G60: =IF(AN60+AO60>=2,"상",IF(OR(AN60+AO60=1,AM60>0,AB60>0,AP60>0),"중","하")) -> 중 | H60: 중 | I60: =IF(AND(G60="상",H60="상"),"매우 높음",IF(OR(AND(G60="상",H60="중"),AND(G60="중",H60="상")),"높음",IF(OR(AND(G60="중",H60="중"),AND(G60="상",H60="하"),AND(G60="하",H60="상")),"보통","낮음"))) -> 보통 | J60: ="실제 사고 "&(AN60+AO60)&"건(ATLAS "&AN60&" / OWASP "&AO60&"), 실증 사례 "&(AM60-AN60)&"건, Realized 기법 "&AB60&"개, 취약점·익스플로잇 "&AP60&"건" -> 실제 사고 0건(ATLAS 0 / OWASP 0), 실증 사례 0건, Realized 기법 2개, 취약점·익스플로잇 0건 | K60: 특정 개인 단위 프라이버시 침해 | L60: 유출(Exfiltration) | M60: AI 모델 접근, 유출 | N60: ● | O60: ● | P60: ● | S60: 기밀성, 규제·법적 | T60: ○ | V60: ● | Y60: T0024, T0024.000 | Z60: T0040 | AA60: =COUNTIF(ATLAS기법매핑!$H$5:$H$212,"*"&D60&"*") -> 3 | AB60: =COUNTIFS(ATLAS기법매핑!$H$5:$H$212,"*"&D60&"*",ATLAS기법매핑!$M$5:$M$212,"Realized") -> 2 | AC60: =COUNTIFS(ATLAS기법매핑!$H$5:$H$212,"*"&D60&"*",ATLAS기법매핑!$M$5:$M$212,"Realized")&" / "&COUNTIFS(ATLAS기법매핑!$H$5:$H$212,"*"&D60&"*",ATLAS기법매핑!$M$5:$M$212,"Demonstrated")&" / "&COUNTIFS(ATLAS기법매핑!$H$5:$H$212,"*"&D60&"*",ATLAS기법매핑!$M$5:$M$212,"Feasible") -> 2 / 0 / 1 | AD60: LLM02 | AH60: DSGAI18 | AL60: =(LEN(Y60&Z60)>0)+(LEN(AD60&AE60)>0)+(LEN(AF60&AG60)>0)+(LEN(AH60&AI60)>0)+(LEN(AJ60&AK60)>0) -> 3 | AM60: =COUNTIF(ATLAS사례연구!$J$5:$J$77,"*"&D60&"*") -> 0 | AN60: =COUNTIFS(ATLAS사례연구!$J$5:$J$77,"*"&D60&"*",ATLAS사례연구!$C$5:$C$77,"Incident") -> 0 | AO60: 0 | AP60: 0 | AQ60: =IF(AN60+AO60>0,"실제 사고 확인",IF(AB60>0,"실사용 기법 포함",IF(OR(AM60>0,AP60>0),"실증·공개 취약점","이론·시나리오"))) -> 실사용 기법 포함 | AS60: • [OWASP 시나리오] 임상 파인튜닝 모델에서 특정 환자의 학습 포함 여부 추론(LLM02 시나리오#8) | AT60: M0024 AI Telemetry Logging M0004 Limit AI Service Query Volume and Rate M0019 Control Access to AI Models and Data in Production M0035 AI Red Team M0002 Predictive AI Output Obfuscation | AU60: 차등프라이버시 학습, 출력 확률 난독화, 쿼리량 제한, 멤버십 추론 감사 | AV60: UT-20
A61: D04. 모델 조작 및 탈취 | B61: UT-15 | C61: 모델을 이용한 데이터 추론 공격 | D61: UT-15.2 | E61: 원본 복원(역전) 공격 | F61: 모델 출력 또는 유출된 임베딩 벡터를 역산하여 학습 데이터/원문 텍스트를 복원 | G61: =IF(AN61+AO61>=2,"상",IF(OR(AN61+AO61=1,AM61>0,AB61>0,AP61>0),"중","하")) -> 하 | H61: 중 | I61: =IF(AND(G61="상",H61="상"),"매우 높음",IF(OR(AND(G61="상",H61="중"),AND(G61="중",H61="상")),"높음",IF(OR(AND(G61="중",H61="중"),AND(G61="상",H61="하"),AND(G61="하",H61="상")),"보통","낮음"))) -> 낮음 | J61: ="실제 사고 "&(AN61+AO61)&"건(ATLAS "&AN61&" / OWASP "&AO61&"), 실증 사례 "&(AM61-AN61)&"건, Realized 기법 "&AB61&"개, 취약점·익스플로잇 "&AP61&"건" -> 실제 사고 0건(ATLAS 0 / OWASP 0), 실증 사례 0건, Realized 기법 0개, 취약점·익스플로잇 0건 | K61: 원문 복원(임베딩 대량 유출 시 피해 확대) | L61: 유출(Exfiltration) | M61: 유출 | N61: ● | O61: ● | P61: ● | S61: 기밀성, 규제·법적 | T61: ○ | V61: ● | Y61: T0024.001 | AA61: =COUNTIF(ATLAS기법매핑!$H$5:$H$212,"*"&D61&"*") -> 1 | AB61: =COUNTIFS(ATLAS기법매핑!$H$5:$H$212,"*"&D61&"*",ATLAS기법매핑!$M$5:$M$212,"Realized") -> 0 | AC61: =COUNTIFS(ATLAS기법매핑!$H$5:$H$212,"*"&D61&"*",ATLAS기법매핑!$M$5:$M$212,"Realized")&" / "&COUNTIFS(ATLAS기법매핑!$H$5:$H$212,"*"&D61&"*",ATLAS기법매핑!$M$5:$M$212,"Demonstrated")&" / "&COUNTIFS(ATLAS기법매핑!$H$5:$H$212,"*"&D61&"*",ATLAS기법매핑!$M$5:$M$212,"Feasible") -> 0 / 0 / 1 | AE61: LLM09, LLM02 | AH61: DSGAI18 | AL61: =(LEN(Y61&Z61)>0)+(LEN(AD61&AE61)>0)+(LEN(AF61&AG61)>0)+(LEN(AH61&AI61)>0)+(LEN(AJ61&AK61)>0) -> 3 | AM61: =COUNTIF(ATLAS사례연구!$J$5:$J$77,"*"&D61&"*") -> 0 | AN61: =COUNTIFS(ATLAS사례연구!$J$5:$J$77,"*"&D61&"*",ATLAS사례연구!$C$5:$C$77,"Incident") -> 0 | AO61: 0 | AP61: 0 | AQ61: =IF(AN61+AO61>0,"실제 사고 확인",IF(AB61>0,"실사용 기법 포함",IF(OR(AM61>0,AP61>0),"실증·공개 취약점","이론·시나리오"))) -> 이론·시나리오 | AS61: • [OWASP 시나리오] 유출된 '임베딩 전용' 백업이 역전 공격으로 원문 유출(LLM02 시나리오#6) | AT61: M0002 Predictive AI Output Obfuscation M0004 Limit AI Service Query Volume and Rate M0024 AI Telemetry Logging M0035 AI Red Team | AU61: 차등프라이버시 학습, 출력 확률 난독화, 쿼리량 제한, 멤버십 추론 감사 | AV61: UT-20
A62: D04. 모델 조작 및 탈취 | B62: UT-15 | C62: 모델을 이용한 데이터 추론 공격 | D62: UT-15.3 | E62: 부채널 추론 | F62: 응답 길이/토큰 스트리밍 패턴/응답 지연 등 부가 정보를 관찰하여 암호화된 대화의 주제나 모델 내부 상태 추론 | G62: =IF(AN62+AO62>=2,"상",IF(OR(AN62+AO62=1,AM62>0,AB62>0,AP62>0),"중","하")) -> 중 | H62: 하 | I62: =IF(AND(G62="상",H62="상"),"매우 높음",IF(OR(AND(G62="상",H62="중"),AND(G62="중",H62="상")),"높음",IF(OR(AND(G62="중",H62="중"),AND(G62="상",H62="하"),AND(G62="하",H62="상")),"보통","낮음"))) -> 낮음 | J62: ="실제 사고 "&(AN62+AO62)&"건(ATLAS "&AN62&" / OWASP "&AO62&"), 실증 사례 "&(AM62-AN62)&"건, Realized 기법 "&AB62&"개, 취약점·익스플로잇 "&AP62&"건" -> 실제 사고 0건(ATLAS 0 / OWASP 0), 실증 사례 2건, Realized 기법 0개, 취약점·익스플로잇 0건 | K62: 대화 주제 수준 추론(노출 제한적) | L62: 탐색(Discovery) | M62: 탐색 | O62: ● | S62: 기밀성, 규제·법적 | T62: ○ | V62: ● | Y62: T0063 | AA62: =COUNTIF(ATLAS기법매핑!$H$5:$H$212,"*"&D62&"*") -> 1 | AB62: =COUNTIFS(ATLAS기법매핑!$H$5:$H$212,"*"&D62&"*",ATLAS기법매핑!$M$5:$M$212,"Realized") -> 0 | AC62: =COUNTIFS(ATLAS기법매핑!$H$5:$H$212,"*"&D62&"*",ATLAS기법매핑!$M$5:$M$212,"Realized")&" / "&COUNTIFS(ATLAS기법매핑!$H$5:$H$212,"*"&D62&"*",ATLAS기법매핑!$M$5:$M$212,"Demonstrated")&" / "&COUNTIFS(ATLAS기법매핑!$H$5:$H$212,"*"&D62&"*",ATLAS기법매핑!$M$5:$M$212,"Feasible") -> 0 / 1 / 0 | AD62: LLM02 | AE62: LLM08 | AL62: =(LEN(Y62&Z62)>0)+(LEN(AD62&AE62)>0)+(LEN(AF62&AG62)>0)+(LEN(AH62&AI62)>0)+(LEN(AJ62&AK62)>0) -> 2 | AM62: =COUNTIF(ATLAS사례연구!$J$5:$J$77,"*"&D62&"*") -> 2 | AN62: =COUNTIFS(ATLAS사례연구!$J$5:$J$77,"*"&D62&"*",ATLAS사례연구!$C$5:$C$77,"Incident") -> 0 | AO62: 0 | AP62: 0 | AQ62: =IF(AN62+AO62>0,"실제 사고 확인",IF(AB62>0,"실사용 기법 포함",IF(OR(AM62>0,AP62>0),"실증·공개 취약점","이론·시나리오"))) -> 실증·공개 취약점 | AR62: CS0003, CS0008 | AS62: • [ATLAS CS0003·실증] Cylance AI 악성코드 탐지기의 판단 로직을 분석해 범용 우회 문자열 생성 • [ATLAS CS0008·실증] ProofPoint 이메일 보호 모델의 복제본을 만들어 실서비스 탐지 회피 • [OWASP 시나리오] 암호화 스트리밍 응답 패턴으로 질의 주제 추론(Whisper Leak, LLM02 시나리오#7) | AT62: M0002 Predictive AI Output Obfuscation M0012 Encrypt Sensitive Information M0017 AI Model Distribution Methods M0019 Control Access to AI Models and Data in Production | AU62: 차등프라이버시 학습, 출력 확률 난독화, 쿼리량 제한, 멤버십 추론 감사 | AV62: UT-20
A63: D04. 모델 조작 및 탈취 | B63: UT-16 | C63: 모델 탈취 | D63: UT-16.1 | E63: 질의 기반 모델 복제 | F63: 대량 API 질의 결과를 학습 데이터로 활용하여 대상 모델 기능을 복제한 대리 모델을 구축하고, 지식재산 탈취 및 화이트박스 공격 준비에 활용 | G63: =IF(AN63+AO63>=2,"상",IF(OR(AN63+AO63=1,AM63>0,AB63>0,AP63>0),"중","하")) -> 중 | H63: 중 | I63: =IF(AND(G63="상",H63="상"),"매우 높음",IF(OR(AND(G63="상",H63="중"),AND(G63="중",H63="상")),"높음",IF(OR(AND(G63="중",H63="중"),AND(G63="상",H63="하"),AND(G63="하",H63="상")),"보통","낮음"))) -> 보통 | J63: ="실제 사고 "&(AN63+AO63)&"건(ATLAS "&AN63&" / OWASP "&AO63&"), 실증 사례 "&(AM63-AN63)&"건, Realized 기법 "&AB63&"개, 취약점·익스플로잇 "&AP63&"건" -> 실제 사고 1건(ATLAS 1 / OWASP 0), 실증 사례 6건, Realized 기법 2개, 취약점·익스플로잇 0건 | K63: 지식재산 손실(시스템 통제 영향 없음) | L63: 유출(Exfiltration) | M63: AI 공격 적응, AI 모델 접근, 유출 | N63: ● | O63: ● | S63: 재무 | U63: ○ | V63: ● | X63: 앱에 비암호화 모델을 포함해 배포하면 배포 단계 노출 | Y63: T0024.002, T0005, T0005.000, T0005.001, T0005.002 | Z63: T0040, T0044 | AA63: =COUNTIF(ATLAS기법매핑!$H$5:$H$212,"*"&D63&"*") -> 7 | AB63: =COUNTIFS(ATLAS기법매핑!$H$5:$H$212,"*"&D63&"*",ATLAS기법매핑!$M$5:$M$212,"Realized") -> 2 | AC63: =COUNTIFS(ATLAS기법매핑!$H$5:$H$212,"*"&D63&"*",ATLAS기법매핑!$M$5:$M$212,"Realized")&" / "&COUNTIFS(ATLAS기법매핑!$H$5:$H$212,"*"&D63&"*",ATLAS기법매핑!$M$5:$M$212,"Demonstrated")&" / "&COUNTIFS(ATLAS기법매핑!$H$5:$H$212,"*"&D63&"*",ATLAS기법매핑!$M$5:$M$212,"Feasible") -> 2 / 4 / 1 | AE63: LLM06 | AH63: DSGAI20 | AL63: =(LEN(Y63&Z63)>0)+(LEN(AD63&AE63)>0)+(LEN(AF63&AG63)>0)+(LEN(AH63&AI63)>0)+(LEN(AJ63&AK63)>0) -> 3 | AM63: =COUNTIF(ATLAS사례연구!$J$5:$J$77,"*"&D63&"*") -> 7 | AN63: =COUNTIFS(ATLAS사례연구!$J$5:$J$77,"*"&D63&"*",ATLAS사례연구!$C$5:$C$77,"Incident") -> 1 | AO63: 0 | AP63: 0 | AQ63: =IF(AN63+AO63>0,"실제 사고 확인",IF(AB63>0,"실사용 기법 포함",IF(OR(AM63>0,AP63>0),"실증·공개 취약점","이론·시나리오"))) -> 실제 사고 확인 | AR63: CS0000, CS0005, CS0007, CS0008, CS0012, CS0014, CS0056 | AS63: • [ATLAS CS0056·실제사고] 약 2.4만 계정·1,600만 쿼리로 Claude 능력을 증류하려는 캠페인 적발(실제 사고) • [ATLAS CS0005·실증] 번역 API 질의로 모델을 복제하고 적대적 예제를 원 서비스에 전이 • [ATLAS CS0007·실증] 공개 정보로 GPT-2 규모 모델을 재현(모델 복제) | AT63: M0000 Limit Public Release of Information M0002 Predictive AI Output Obfuscation M0004 Limit AI Service Query Volume and Rate M0024 AI Telemetry Logging M0001 Limit Model Artifact Release | AU63: 쿼리량·패턴 제한, 증류 캠페인 탐지, 워터마킹, 모델 아티팩트 암호화·접근통제 | AV63: UT-24
A64: D04. 모델 조작 및 탈취 | B64: UT-16 | C64: 모델 탈취 | D64: UT-16.2 | E64: 모델 파일 탈취 | F64: 앱 패키지/모델 저장소/학습 클러스터에서 모델 가중치 및 데이터셋 등 AI 아티팩트 파일을 직접 수집하여 반출 | G64: =IF(AN64+AO64>=2,"상",IF(OR(AN64+AO64=1,AM64>0,AB64>0,AP64>0),"중","하")) -> 중 | H64: 상 | I64: =IF(AND(G64="상",H64="상"),"매우 높음",IF(OR(AND(G64="상",H64="중"),AND(G64="중",H64="상")),"높음",IF(OR(AND(G64="중",H64="중"),AND(G64="상",H64="하"),AND(G64="하",H64="상")),"보통","낮음"))) -> 높음 | J64: ="실제 사고 "&(AN64+AO64)&"건(ATLAS "&AN64&" / OWASP "&AO64&"), 실증 사례 "&(AM64-AN64)&"건, Realized 기법 "&AB64&"개, 취약점·익스플로잇 "&AP64&"건" -> 실제 사고 1건(ATLAS 1 / OWASP 0), 실증 사례 3건, Realized 기법 1개, 취약점·익스플로잇 0건 | K64: 핵심 모델 자산 및 학습 데이터 일괄 탈취 | L64: 수집(Collection) | M64: 수집 | N64: ● | O64: ● | S64: 기밀성, 재무 | U64: ● | V64: ○ | Y64: T0035 | AA64: =COUNTIF(ATLAS기법매핑!$H$5:$H$212,"*"&D64&"*") -> 1 | AB64: =COUNTIFS(ATLAS기법매핑!$H$5:$H$212,"*"&D64&"*",ATLAS기법매핑!$M$5:$M$212,"Realized") -> 1 | AC64: =COUNTIFS(ATLAS기법매핑!$H$5:$H$212,"*"&D64&"*",ATLAS기법매핑!$M$5:$M$212,"Realized")&" / "&COUNTIFS(ATLAS기법매핑!$H$5:$H$212,"*"&D64&"*",ATLAS기법매핑!$M$5:$M$212,"Demonstrated")&" / "&COUNTIFS(ATLAS기법매핑!$H$5:$H$212,"*"&D64&"*",ATLAS기법매핑!$M$5:$M$212,"Feasible") -> 1 / 0 / 0 | AE64: LLM02 | AH64: DSGAI20 | AL64: =(LEN(Y64&Z64)>0)+(LEN(AD64&AE64)>0)+(LEN(AF64&AG64)>0)+(LEN(AH64&AI64)>0)+(LEN(AJ64&AK64)>0) -> 3 | AM64: =COUNTIF(ATLAS사례연구!$J$5:$J$77,"*"&D64&"*") -> 4 | AN64: =COUNTIFS(ATLAS사례연구!$J$5:$J$77,"*"&D64&"*",ATLAS사례연구!$C$5:$C$77,"Incident") -> 1 | AO64: 0 | AP64: 0 | AQ64: =IF(AN64+AO64>0,"실제 사고 확인",IF(AB64>0,"실사용 기법 포함",IF(OR(AM64>0,AP64>0),"실증·공개 취약점","이론·시나리오"))) -> 실제 사고 확인 | AR64: CS0010, CS0018, CS0023, CS0058 | AS64: • [ATLAS CS0058·실증] Google Photos 앱에서 암호화되지 않은 TFLite 모델을 추출 • [ATLAS CS0023·실제사고] 인증 없는 Ray 클러스터를 탈취해 연산자원·자격증명·모델 탈취(ShadowRay, 실제 사고) • [ATLAS CS0010·실증] 레드팀이 기존 침투기법과 AI 회피를 결합해 Azure 내부 서비스 중단 시연 | AT64: M0001 Limit Model Artifact Release M0005 Control Access to AI Models and Data at Rest M0012 Encrypt Sensitive Information M0017 AI Model Distribution Methods | AU64: 쿼리량·패턴 제한, 증류 캠페인 탐지, 워터마킹, 모델 아티팩트 암호화·접근통제 | AV64: UT-24
A65: D04. 모델 조작 및 탈취 | B65: UT-17 | C65: 예측 AI 회피 공격 | D65: UT-17.1 | E65: 디지털 적대적 예제 | F65: 모델 경사 정보/대리 모델/반복 질의로 최적화한 미세 섭동 입력을 생성하여 탐지/분류 모델의 오판(예: 악성코드를 정상으로 분류) 유도 | G65: =IF(AN65+AO65>=2,"상",IF(OR(AN65+AO65=1,AM65>0,AB65>0,AP65>0),"중","하")) -> 상 | H65: 중 | I65: =IF(AND(G65="상",H65="상"),"매우 높음",IF(OR(AND(G65="상",H65="중"),AND(G65="중",H65="상")),"높음",IF(OR(AND(G65="중",H65="중"),AND(G65="상",H65="하"),AND(G65="하",H65="상")),"보통","낮음"))) -> 높음 | J65: ="실제 사고 "&(AN65+AO65)&"건(ATLAS "&AN65&" / OWASP "&AO65&"), 실증 사례 "&(AM65-AN65)&"건, Realized 기법 "&AB65&"개, 취약점·익스플로잇 "&AP65&"건" -> 실제 사고 6건(ATLAS 6 / OWASP 0), 실증 사례 15건, Realized 기법 3개, 취약점·익스플로잇 0건 | K65: 특정 판단 단위 오분류(보안 탐지 우회 시 피해 확대) | L65: 방어 회피(Defense Evasion) | M65: AI 공격 적응, 초기 접근, 방어 회피, 영향 | N65: ● | S65: 무결성, 안전·사용자 | T65: ○ | V65: ● | Y65: T0015, T0043, T0043.000, T0043.001, T0043.002, T0043.003, T0042 | AA65: =COUNTIF(ATLAS기법매핑!$H$5:$H$212,"*"&D65&"*") -> 7 | AB65: =COUNTIFS(ATLAS기법매핑!$H$5:$H$212,"*"&D65&"*",ATLAS기법매핑!$M$5:$M$212,"Realized") -> 3 | AC65: =COUNTIFS(ATLAS기법매핑!$H$5:$H$212,"*"&D65&"*",ATLAS기법매핑!$M$5:$M$212,"Realized")&" / "&COUNTIFS(ATLAS기법매핑!$H$5:$H$212,"*"&D65&"*",ATLAS기법매핑!$M$5:$M$212,"Demonstrated")&" / "&COUNTIFS(ATLAS기법매핑!$H$5:$H$212,"*"&D65&"*",ATLAS기법매핑!$M$5:$M$212,"Feasible") -> 3 / 4 / 0 | AL65: =(LEN(Y65&Z65)>0)+(LEN(AD65&AE65)>0)+(LEN(AF65&AG65)>0)+(LEN(AH65&AI65)>0)+(LEN(AJ65&AK65)>0) -> 1 | AM65: =COUNTIF(ATLAS사례연구!$J$5:$J$77,"*"&D65&"*") -> 21 | AN65: =COUNTIFS(ATLAS사례연구!$J$5:$J$77,"*"&D65&"*",ATLAS사례연구!$C$5:$C$77,"Incident") -> 6 | AO65: 0 | AP65: 0 | AQ65: =IF(AN65+AO65>0,"실제 사고 확인",IF(AB65>0,"실사용 기법 포함",IF(OR(AM65>0,AP65>0),"실증·공개 취약점","이론·시나리오"))) -> 실제 사고 확인 | AR65: CS0000, CS0001, CS0002, CS0003, CS0004, CS0005, CS0008, CS0010, CS0011, CS0012, CS0013, CS0014, CS0016, CS0017, CS0019, CS0028, CS0032, CS0033, CS0034, CS0043, CS0058 | AS65: • [ATLAS CS0004·실제사고] 카메라 영상 주입으로 얼굴인식 인증을 우회해 세금 사기(실제 사고) • [ATLAS CS0017·실제사고] ID.me 자동 신원확인을 우회해 180건 이상 허위 실업급여 청구(실제 사고) • [ATLAS CS0032·실제사고] 피싱 사이트가 ML 기반 피싱 탐지기를 회피하도록 시각 요소 변형(실제 사고) | AT65: M0003 Predictive AI Model Hardening M0006 Predictive AI Ensembles M0010 Predictive AI Input Restoration M0015 Predictive AI Adversarial Input Detection M0004 Limit AI Service Query Volume and Rate | AU65: 적대적 학습·모델 강건화, 입력 복원, 앙상블·다중센서 융합, 적대적 입력 탐지 | AV65: UT-35
A66: D04. 모델 조작 및 탈취 | B66: UT-17 | C66: 예측 AI 회피 공격 | D66: UT-17.2 | E66: 물리적 적대적 객체 | F66: 패치/안경/표지 등 물리적 대응물을 실제 환경에 배치하여 카메라 기반 인식 모델(얼굴인식/자율주행)의 오인식 유발 | G66: =IF(AN66+AO66>=2,"상",IF(OR(AN66+AO66=1,AM66>0,AB66>0,AP66>0),"중","하")) -> 중 | H66: 중 | I66: =IF(AND(G66="상",H66="상"),"매우 높음",IF(OR(AND(G66="상",H66="중"),AND(G66="중",H66="상")),"높음",IF(OR(AND(G66="중",H66="중"),AND(G66="상",H66="하"),AND(G66="하",H66="상")),"보통","낮음"))) -> 보통 | J66: ="실제 사고 "&(AN66+AO66)&"건(ATLAS "&AN66&" / OWASP "&AO66&"), 실증 사례 "&(AM66-AN66)&"건, Realized 기법 "&AB66&"개, 취약점·익스플로잇 "&AP66&"건" -> 실제 사고 0건(ATLAS 0 / OWASP 0), 실증 사례 2건, Realized 기법 0개, 취약점·익스플로잇 0건 | K66: 물리 보안 및 안전 영향(국지적) | L66: 방어 회피(Defense Evasion) | M66: AI 모델 접근 | N66: ● | S66: 안전·사용자 | T66: ○ | V66: ● | Y66: T0041 | AA66: =COUNTIF(ATLAS기법매핑!$H$5:$H$212,"*"&D66&"*") -> 1 | AB66: =COUNTIFS(ATLAS기법매핑!$H$5:$H$212,"*"&D66&"*",ATLAS기법매핑!$M$5:$M$212,"Realized") -> 0 | AC66: =COUNTIFS(ATLAS기법매핑!$H$5:$H$212,"*"&D66&"*",ATLAS기법매핑!$M$5:$M$212,"Realized")&" / "&COUNTIFS(ATLAS기법매핑!$H$5:$H$212,"*"&D66&"*",ATLAS기법매핑!$M$5:$M$212,"Demonstrated")&" / "&COUNTIFS(ATLAS기법매핑!$H$5:$H$212,"*"&D66&"*",ATLAS기법매핑!$M$5:$M$212,"Feasible") -> 0 / 1 / 0 | AL66: =(LEN(Y66&Z66)>0)+(LEN(AD66&AE66)>0)+(LEN(AF66&AG66)>0)+(LEN(AH66&AI66)>0)+(LEN(AJ66&AK66)>0) -> 1 | AM66: =COUNTIF(ATLAS사례연구!$J$5:$J$77,"*"&D66&"*") -> 2 | AN66: =COUNTIFS(ATLAS사례연구!$J$5:$J$77,"*"&D66&"*",ATLAS사례연구!$C$5:$C$77,"Incident") -> 0 | AO66: 0 | AP66: 0 | AQ66: =IF(AN66+AO66>0,"실제 사고 확인",IF(AB66>0,"실사용 기법 포함",IF(OR(AM66>0,AP66>0),"실증·공개 취약점","이론·시나리오"))) -> 실증·공개 취약점 | AR66: CS0012, CS0013 | AS66: • [ATLAS CS0012·실증] 물리적 대응물로 상용 얼굴식별 서비스에 표적 오분류 유도 • [ATLAS CS0013·실증] 모바일 앱에서 추출한 딥러닝 모델에 백도어 삽입 후 재패키징 | AT66: M0009 Predictive AI Multi-Sensor Fusion | AU66: 적대적 학습·모델 강건화, 입력 복원, 앙상블·다중센서 융합, 적대적 입력 탐지 | AV66: UT-35
A67: D05. 출력 처리 결함 및 신뢰성 훼손 | B67: UT-18 | C67: 부적절한 출력 처리 | D67: UT-18.1 | E67: 렌더링 해석기 공격 | F67: 모델 출력의 HTML/마크다운/ANSI 제어문자가 브라우저/터미널/IDE에서 해석되어 스크립트 실행, 화면 위조, 세션 탈취 유발 | G67: =IF(AN67+AO67>=2,"상",IF(OR(AN67+AO67=1,AM67>0,AB67>0,AP67>0),"중","하")) -> 중 | H67: 중 | I67: =IF(AND(G67="상",H67="상"),"매우 높음",IF(OR(AND(G67="상",H67="중"),AND(G67="중",H67="상")),"높음",IF(OR(AND(G67="중",H67="중"),AND(G67="상",H67="하"),AND(G67="하",H67="상")),"보통","낮음"))) -> 보통 | J67: ="실제 사고 "&(AN67+AO67)&"건(ATLAS "&AN67&" / OWASP "&AO67&"), 실증 사례 "&(AM67-AN67)&"건, Realized 기법 "&AB67&"개, 취약점·익스플로잇 "&AP67&"건" -> 실제 사고 0건(ATLAS 0 / OWASP 0), 실증 사례 5건, Realized 기법 0개, 취약점·익스플로잇 0건 | K67: 세션 탈취 등 사용자 단위 피해 | L67: 실행(Execution) | M67: 유출 | O67: ● | P67: ● | Q67: ● | S67: 기밀성, 무결성 | T67: ● | V67: ○ | Y67: T0077 | AA67: =COUNTIF(ATLAS기법매핑!$H$5:$H$212,"*"&D67&"*") -> 1 | AB67: =COUNTIFS(ATLAS기법매핑!$H$5:$H$212,"*"&D67&"*",ATLAS기법매핑!$M$5:$M$212,"Realized") -> 0 | AC67: =COUNTIFS(ATLAS기법매핑!$H$5:$H$212,"*"&D67&"*",ATLAS기법매핑!$M$5:$M$212,"Realized")&" / "&COUNTIFS(ATLAS기법매핑!$H$5:$H$212,"*"&D67&"*",ATLAS기법매핑!$M$5:$M$212,"Demonstrated")&" / "&COUNTIFS(ATLAS기법매핑!$H$5:$H$212,"*"&D67&"*",ATLAS기법매핑!$M$5:$M$212,"Feasible") -> 0 / 1 / 0 | AD67: LLM10 | AE67: LLM01 | AG67: ASI09 | AI67: DSGAI16 | AL67: =(LEN(Y67&Z67)>0)+(LEN(AD67&AE67)>0)+(LEN(AF67&AG67)>0)+(LEN(AH67&AI67)>0)+(LEN(AJ67&AK67)>0) -> 4 | AM67: =COUNTIF(ATLAS사례연구!$J$5:$J$77,"*"&D67&"*") -> 5 | AN67: =COUNTIFS(ATLAS사례연구!$J$5:$J$77,"*"&D67&"*",ATLAS사례연구!$C$5:$C$77,"Incident") -> 0 | AO67: 0 | AP67: 0 | AQ67: =IF(AN67+AO67>0,"실제 사고 확인",IF(AB67>0,"실사용 기법 포함",IF(OR(AM67>0,AP67>0),"실증·공개 취약점","이론·시나리오"))) -> 실증·공개 취약점 | AR67: CS0021, CS0029, CS0035, CS0059, CS0060 | AS67: • [ATLAS CS0060·실증] Lenovo 챗봇이 생성한 악성 HTML이 상담원 브라우저에서 실행되어 세션 쿠키 탈취(XSS) • [ATLAS CS0021·실증] 웹페이지 간접 인젝션으로 ChatGPT 대화 내용을 이미지 URL로 유출 • [ATLAS CS0029·실증] 공유 Google 문서의 간접 인젝션으로 Bard 대화 내용 유출 | AT67: — (ATLAS 완화책 없음: Lv2 핵심 통제 참조) | AU67: 출력 대상 시스템별 인코딩과 이스케이프, 쿼리 파라미터화·읽기전용 계정, 외부 리소스 자동 로딩 차단, 모델 독립적 출력 보안 계층 | AV67: UT-16, UT-17
A68: D05. 출력 처리 결함 및 신뢰성 훼손 | B68: UT-18 | C68: 부적절한 출력 처리 | D68: UT-18.2 | E68: DB 질의 생성 공격 | F68: 자연어를 SQL/그래프 질의로 변환하는 기능에 조작 입력을 주입하여, 검증 없이 실행된 질의로 대량 조회/변경/삭제 수행 | G68: =IF(AN68+AO68>=2,"상",IF(OR(AN68+AO68=1,AM68>0,AB68>0,AP68>0),"중","하")) -> 중 | H68: 상 | I68: =IF(AND(G68="상",H68="상"),"매우 높음",IF(OR(AND(G68="상",H68="중"),AND(G68="중",H68="상")),"높음",IF(OR(AND(G68="중",H68="중"),AND(G68="상",H68="하"),AND(G68="하",H68="상")),"보통","낮음"))) -> 높음 | J68: ="실제 사고 "&(AN68+AO68)&"건(ATLAS "&AN68&" / OWASP "&AO68&"), 실증 사례 "&(AM68-AN68)&"건, Realized 기법 "&AB68&"개, 취약점·익스플로잇 "&AP68&"건" -> 실제 사고 0건(ATLAS 0 / OWASP 0), 실증 사례 0건, Realized 기법 1개, 취약점·익스플로잇 2건 | K68: DB 전체 조회/변경/삭제 가능 | L68: 실행(Execution) | M68: 실행 | O68: ● | P68: ● | Q68: ● | S68: 기밀성, 무결성, 가용성 | T68: ● | V68: ○ | Z68: T0050 | AA68: =COUNTIF(ATLAS기법매핑!$H$5:$H$212,"*"&D68&"*") -> 1 | AB68: =COUNTIFS(ATLAS기법매핑!$H$5:$H$212,"*"&D68&"*",ATLAS기법매핑!$M$5:$M$212,"Realized") -> 1 | AC68: =COUNTIFS(ATLAS기법매핑!$H$5:$H$212,"*"&D68&"*",ATLAS기법매핑!$M$5:$M$212,"Realized")&" / "&COUNTIFS(ATLAS기법매핑!$H$5:$H$212,"*"&D68&"*",ATLAS기법매핑!$M$5:$M$212,"Demonstrated")&" / "&COUNTIFS(ATLAS기법매핑!$H$5:$H$212,"*"&D68&"*",ATLAS기법매핑!$M$5:$M$212,"Feasible") -> 1 / 0 / 0 | AD68: LLM10 | AG68: ASI05 | AH68: DSGAI12 | AI68: DSGAI01 | AL68: =(LEN(Y68&Z68)>0)+(LEN(AD68&AE68)>0)+(LEN(AF68&AG68)>0)+(LEN(AH68&AI68)>0)+(LEN(AJ68&AK68)>0) -> 4 | AM68: =COUNTIF(ATLAS사례연구!$J$5:$J$77,"*"&D68&"*") -> 0 | AN68: =COUNTIFS(ATLAS사례연구!$J$5:$J$77,"*"&D68&"*",ATLAS사례연구!$C$5:$C$77,"Incident") -> 0 | AO68: 0 | AP68: 2 | AQ68: =IF(AN68+AO68>0,"실제 사고 확인",IF(AB68>0,"실사용 기법 포함",IF(OR(AM68>0,AP68>0),"실증·공개 취약점","이론·시나리오"))) -> 실사용 기법 포함 | AS68: • [OWASP 인용] LangChain GraphCypherQAChain CVE-2024-8309 / CVE-2024-7042 • [OWASP 시나리오] 채팅형 SQL 기능의 생성 쿼리가 검증 없이 실행되어 테이블 삭제(LLM10 시나리오#3) | AT68: M0011 Restrict Library Loading | AU68: 출력 대상 시스템별 인코딩과 이스케이프, 쿼리 파라미터화·읽기전용 계정, 외부 리소스 자동 로딩 차단, 모델 독립적 출력 보안 계층 | AV68: UT-16, UT-17
A69: D05. 출력 처리 결함 및 신뢰성 훼손 | B69: UT-18 | C69: 부적절한 출력 처리 | D69: UT-18.3 | E69: 생성 코드의 무검증 사용 | F69: 모델이 생성한 코드/이메일 템플릿/설정을 검토 없이 배포하거나 후속 시스템에 전달하여 취약 코드 및 악성 구문이 운영 환경에 반영 | G69: =IF(AN69+AO69>=2,"상",IF(OR(AN69+AO69=1,AM69>0,AB69>0,AP69>0),"중","하")) -> 중 | H69: 중 | I69: =IF(AND(G69="상",H69="상"),"매우 높음",IF(OR(AND(G69="상",H69="중"),AND(G69="중",H69="상")),"높음",IF(OR(AND(G69="중",H69="중"),AND(G69="상",H69="하"),AND(G69="하",H69="상")),"보통","낮음"))) -> 보통 | J69: ="실제 사고 "&(AN69+AO69)&"건(ATLAS "&AN69&" / OWASP "&AO69&"), 실증 사례 "&(AM69-AN69)&"건, Realized 기법 "&AB69&"개, 취약점·익스플로잇 "&AP69&"건" -> 실제 사고 0건(ATLAS 0 / OWASP 0), 실증 사례 1건, Realized 기법 0개, 취약점·익스플로잇 0건 | K69: 취약 코드 및 악성 구문의 운영 반영 | L69: 실행(Execution) | M69: — | O69: ● | P69: ● | Q69: ● | S69: 무결성, 기밀성 | T69: ● | V69: ○ | AA69: =COUNTIF(ATLAS기법매핑!$H$5:$H$212,"*"&D69&"*") -> 0 | AB69: =COUNTIFS(ATLAS기법매핑!$H$5:$H$212,"*"&D69&"*",ATLAS기법매핑!$M$5:$M$212,"Realized") -> 0 | AC69: =COUNTIFS(ATLAS기법매핑!$H$5:$H$212,"*"&D69&"*",ATLAS기법매핑!$M$5:$M$212,"Realized")&" / "&COUNTIFS(ATLAS기법매핑!$H$5:$H$212,"*"&D69&"*",ATLAS기법매핑!$M$5:$M$212,"Demonstrated")&" / "&COUNTIFS(ATLAS기법매핑!$H$5:$H$212,"*"&D69&"*",ATLAS기법매핑!$M$5:$M$212,"Feasible") -> 0 / 0 / 0 | AD69: LLM10 | AG69: ASI02 | AK69: MCP05 | AL69: =(LEN(Y69&Z69)>0)+(LEN(AD69&AE69)>0)+(LEN(AF69&AG69)>0)+(LEN(AH69&AI69)>0)+(LEN(AJ69&AK69)>0) -> 3 | AM69: =COUNTIF(ATLAS사례연구!$J$5:$J$77,"*"&D69&"*") -> 1 | AN69: =COUNTIFS(ATLAS사례연구!$J$5:$J$77,"*"&D69&"*",ATLAS사례연구!$C$5:$C$77,"Incident") -> 0 | AO69: 0 | AP69: 0 | AQ69: =IF(AN69+AO69>0,"실제 사고 확인",IF(AB69>0,"실사용 기법 포함",IF(OR(AM69>0,AP69>0),"실증·공개 취약점","이론·시나리오"))) -> 실증·공개 취약점 | AR69: CS0052 | AS69: • [ATLAS CS0052·실증] 11개 LLM 프레임워크에서 20개 RCE 취약점 발견, 인터넷 공개 앱에서 실증(LLMSmith) • [OWASP 시나리오] 생성 코드·템플릿을 검토 없이 배포하여 취약점 반영(LLM10 시나리오#5·#6) | AT69: — (ATLAS 완화책 없음: Lv2 핵심 통제 참조) | AU69: 출력 대상 시스템별 인코딩과 이스케이프, 쿼리 파라미터화·읽기전용 계정, 외부 리소스 자동 로딩 차단, 모델 독립적 출력 보안 계층 | AV69: UT-16, UT-17
A70: D05. 출력 처리 결함 및 신뢰성 훼손 | B70: UT-19 | C70: AI를 통한 데이터 반출 | D70: UT-19.1 | E70: 렌더링 채널 반출 | F70: 인젝션된 지시로 민감정보를 외부 이미지 URL/링크 파라미터에 삽입하게 하여, 클라이언트 자동 렌더링 시점에 사용자 조작 없이 데이터 반출 | G70: =IF(AN70+AO70>=2,"상",IF(OR(AN70+AO70=1,AM70>0,AB70>0,AP70>0),"중","하")) -> 중 | H70: 상 | I70: =IF(AND(G70="상",H70="상"),"매우 높음",IF(OR(AND(G70="상",H70="중"),AND(G70="중",H70="상")),"높음",IF(OR(AND(G70="중",H70="중"),AND(G70="상",H70="하"),AND(G70="하",H70="상")),"보통","낮음"))) -> 높음 | J70: ="실제 사고 "&(AN70+AO70)&"건(ATLAS "&AN70&" / OWASP "&AO70&"), 실증 사례 "&(AM70-AN70)&"건, Realized 기법 "&AB70&"개, 취약점·익스플로잇 "&AP70&"건" -> 실제 사고 0건(ATLAS 0 / OWASP 0), 실증 사례 4건, Realized 기법 0개, 취약점·익스플로잇 0건 | K70: 사용자 조작 없는 대량 유출(제로클릭) | L70: 유출(Exfiltration) | M70: 유출 | O70: ● | P70: ● | Q70: ● | R70: ● | S70: 기밀성 | T70: ○ | V70: ● | Z70: T0077 | AA70: =COUNTIF(ATLAS기법매핑!$H$5:$H$212,"*"&D70&"*") -> 1 | AB70: =COUNTIFS(ATLAS기법매핑!$H$5:$H$212,"*"&D70&"*",ATLAS기법매핑!$M$5:$M$212,"Realized") -> 0 | AC70: =COUNTIFS(ATLAS기법매핑!$H$5:$H$212,"*"&D70&"*",ATLAS기법매핑!$M$5:$M$212,"Realized")&" / "&COUNTIFS(ATLAS기법매핑!$H$5:$H$212,"*"&D70&"*",ATLAS기법매핑!$M$5:$M$212,"Demonstrated")&" / "&COUNTIFS(ATLAS기법매핑!$H$5:$H$212,"*"&D70&"*",ATLAS기법매핑!$M$5:$M$212,"Feasible") -> 0 / 1 / 0 | AE70: LLM02, LLM01 | AG70: ASI01 | AI70: DSGAI01 | AK70: MCP06 | AL70: =(LEN(Y70&Z70)>0)+(LEN(AD70&AE70)>0)+(LEN(AF70&AG70)>0)+(LEN(AH70&AI70)>0)+(LEN(AJ70&AK70)>0) -> 5 | AM70: =COUNTIF(ATLAS사례연구!$J$5:$J$77,"*"&D70&"*") -> 4 | AN70: =COUNTIFS(ATLAS사례연구!$J$5:$J$77,"*"&D70&"*",ATLAS사례연구!$C$5:$C$77,"Incident") -> 0 | AO70: 0 | AP70: 0 | AQ70: =IF(AN70+AO70>0,"실제 사고 확인",IF(AB70>0,"실사용 기법 포함",IF(OR(AM70>0,AP70>0),"실증·공개 취약점","이론·시나리오"))) -> 실증·공개 취약점 | AR70: CS0021, CS0029, CS0035, CS0059 | AS70: • [ATLAS CS0021·실증] 웹페이지 간접 인젝션으로 ChatGPT 대화 내용을 이미지 URL로 유출 • [ATLAS CS0029·실증] 공유 Google 문서의 간접 인젝션으로 Bard 대화 내용 유출 • [ATLAS CS0035·실증] 공개 채널 게시글의 간접 인젝션으로 Slack AI가 비공개 채널 데이터 유출 | AT70: — (ATLAS 완화책 없음: Lv2 핵심 통제 참조) | AU70: 외부 URL 렌더링 차단·egress 허용목록, 도구 콜백 대상 검증, 유출 패턴 탐지 | AV70: UT-21
A71: D05. 출력 처리 결함 및 신뢰성 훼손 | B71: UT-19 | C71: AI를 통한 데이터 반출 | D71: UT-19.2 | E71: 도구 호출 경유 반출 | F71: 에이전트의 메일 발송/웹 요청/파일 공유 도구 호출 인자에 수집 데이터를 포함시켜 정상 업무 행위로 위장된 외부 전송 수행 | G71: =IF(AN71+AO71>=2,"상",IF(OR(AN71+AO71=1,AM71>0,AB71>0,AP71>0),"중","하")) -> 중 | H71: 상 | I71: =IF(AND(G71="상",H71="상"),"매우 높음",IF(OR(AND(G71="상",H71="중"),AND(G71="중",H71="상")),"높음",IF(OR(AND(G71="중",H71="중"),AND(G71="상",H71="하"),AND(G71="하",H71="상")),"보통","낮음"))) -> 높음 | J71: ="실제 사고 "&(AN71+AO71)&"건(ATLAS "&AN71&" / OWASP "&AO71&"), 실증 사례 "&(AM71-AN71)&"건, Realized 기법 "&AB71&"개, 취약점·익스플로잇 "&AP71&"건" -> 실제 사고 1건(ATLAS 1 / OWASP 0), 실증 사례 9건, Realized 기법 1개, 취약점·익스플로잇 0건 | K71: 정상 업무로 위장된 대량 외부 전송 | L71: 유출(Exfiltration) | M71: 유출 | O71: ● | P71: ● | Q71: ● | R71: ● | S71: 기밀성 | T71: ○ | V71: ● | Y71: T0086 | AA71: =COUNTIF(ATLAS기법매핑!$H$5:$H$212,"*"&D71&"*") -> 1 | AB71: =COUNTIFS(ATLAS기법매핑!$H$5:$H$212,"*"&D71&"*",ATLAS기법매핑!$M$5:$M$212,"Realized") -> 1 | AC71: =COUNTIFS(ATLAS기법매핑!$H$5:$H$212,"*"&D71&"*",ATLAS기법매핑!$M$5:$M$212,"Realized")&" / "&COUNTIFS(ATLAS기법매핑!$H$5:$H$212,"*"&D71&"*",ATLAS기법매핑!$M$5:$M$212,"Demonstrated")&" / "&COUNTIFS(ATLAS기법매핑!$H$5:$H$212,"*"&D71&"*",ATLAS기법매핑!$M$5:$M$212,"Feasible") -> 1 / 0 / 0 | AE71: LLM03, LLM10 | AG71: ASI02 | AI71: DSGAI16 | AL71: =(LEN(Y71&Z71)>0)+(LEN(AD71&AE71)>0)+(LEN(AF71&AG71)>0)+(LEN(AH71&AI71)>0)+(LEN(AJ71&AK71)>0) -> 4 | AM71: =COUNTIF(ATLAS사례연구!$J$5:$J$77,"*"&D71&"*") -> 10 | AN71: =COUNTIFS(ATLAS사례연구!$J$5:$J$77,"*"&D71&"*",ATLAS사례연구!$C$5:$C$77,"Incident") -> 1 | AO71: 0 | AP71: 0 | AQ71: =IF(AN71+AO71>0,"실제 사고 확인",IF(AB71>0,"실사용 기법 포함",IF(OR(AM71>0,AP71>0),"실증·공개 취약점","이론·시나리오"))) -> 실제 사고 확인 | AR71: CS0037, CS0039, CS0045, CS0053, CS0054, CS0061, CS0063, CS0064, CS0066, CS0067 | AS71: • [ATLAS CS0053·실제사고] Postmark를 사칭한 악성 MCP 서버가 발송 메일을 몰래 BCC로 유출(실제 사고) • [ATLAS CS0037·실증] Copilot Studio 고객지원 에이전트를 인젝션해 지식원·도구를 탐색하고 CRM 데이터 유출 • [ATLAS CS0039·실증] 외부 사용자가 Jira 티켓에 악성 입력을 넣어 AI가 내부자 권한으로 행위(Living off AI) | AT71: M0024 AI Telemetry Logging M0026 Privileged AI Agent Permissions Configuration M0027 Single-User AI Agent Permissions Configuration M0028 AI Agent Tools Permissions Configuration M0029 Human In-the-Loop for AI Agent Actions | AU71: 외부 URL 렌더링 차단·egress 허용목록, 도구 콜백 대상 검증, 유출 패턴 탐지 | AV71: UT-21
A72: D05. 출력 처리 결함 및 신뢰성 훼손 | B72: UT-19 | C72: AI를 통한 데이터 반출 | D72: UT-19.3 | E72: 은닉 채널 반출 | F72: DNS 질의/비가시 유니코드 문자 등 모니터링 사각지대 채널에 데이터를 인코딩하여 DLP 및 egress 통제를 우회한 반출 | G72: =IF(AN72+AO72>=2,"상",IF(OR(AN72+AO72=1,AM72>0,AB72>0,AP72>0),"중","하")) -> 하 | H72: 중 | I72: =IF(AND(G72="상",H72="상"),"매우 높음",IF(OR(AND(G72="상",H72="중"),AND(G72="중",H72="상")),"높음",IF(OR(AND(G72="중",H72="중"),AND(G72="상",H72="하"),AND(G72="하",H72="상")),"보통","낮음"))) -> 낮음 | J72: ="실제 사고 "&(AN72+AO72)&"건(ATLAS "&AN72&" / OWASP "&AO72&"), 실증 사례 "&(AM72-AN72)&"건, Realized 기법 "&AB72&"개, 취약점·익스플로잇 "&AP72&"건" -> 실제 사고 0건(ATLAS 0 / OWASP 0), 실증 사례 0건, Realized 기법 0개, 취약점·익스플로잇 0건 | K72: 저대역 은닉 유출(탐지 곤란) | L72: 유출(Exfiltration) | M72: — | O72: ● | P72: ● | Q72: ● | R72: ● | S72: 기밀성 | T72: ○ | V72: ● | AA72: =COUNTIF(ATLAS기법매핑!$H$5:$H$212,"*"&D72&"*") -> 0 | AB72: =COUNTIFS(ATLAS기법매핑!$H$5:$H$212,"*"&D72&"*",ATLAS기법매핑!$M$5:$M$212,"Realized") -> 0 | AC72: =COUNTIFS(ATLAS기법매핑!$H$5:$H$212,"*"&D72&"*",ATLAS기법매핑!$M$5:$M$212,"Realized")&" / "&COUNTIFS(ATLAS기법매핑!$H$5:$H$212,"*"&D72&"*",ATLAS기법매핑!$M$5:$M$212,"Demonstrated")&" / "&COUNTIFS(ATLAS기법매핑!$H$5:$H$212,"*"&D72&"*",ATLAS기법매핑!$M$5:$M$212,"Feasible") -> 0 / 0 / 0 | AE72: LLM02 | AI72: DSGAI09 | AL72: =(LEN(Y72&Z72)>0)+(LEN(AD72&AE72)>0)+(LEN(AF72&AG72)>0)+(LEN(AH72&AI72)>0)+(LEN(AJ72&AK72)>0) -> 2 | AM72: =COUNTIF(ATLAS사례연구!$J$5:$J$77,"*"&D72&"*") -> 0 | AN72: =COUNTIFS(ATLAS사례연구!$J$5:$J$77,"*"&D72&"*",ATLAS사례연구!$C$5:$C$77,"Incident") -> 0 | AO72: 0 | AP72: 0 | AQ72: =IF(AN72+AO72>0,"실제 사고 확인",IF(AB72>0,"실사용 기법 포함",IF(OR(AM72>0,AP72>0),"실증·공개 취약점","이론·시나리오"))) -> 이론·시나리오 | AS72: • [OWASP 시나리오] 코드 런타임이 스프레드시트 내용을 DNS 질의에 인코딩해 반출(LLM02 시나리오#10) | AT72: — (ATLAS 완화책 없음: Lv2 핵심 통제 참조) | AU72: 외부 URL 렌더링 차단·egress 허용목록, 도구 콜백 대상 검증, 유출 패턴 탐지 | AV72: UT-21
A73: D05. 출력 처리 결함 및 신뢰성 훼손 | B73: UT-20 | C73: AI 출력 신뢰성 훼손 | D73: UT-20.1 | E73: 환각에 의한 허위정보 | F73: 근거 없는 사실/수치/인용을 그럴듯하게 생성하여 업무 판단, 고객 안내, 규정 해석에 오류 유발 | G73: =IF(AN73+AO73>=2,"상",IF(OR(AN73+AO73=1,AM73>0,AB73>0,AP73>0),"중","하")) -> 하 | H73: 중 | I73: =IF(AND(G73="상",H73="상"),"매우 높음",IF(OR(AND(G73="상",H73="중"),AND(G73="중",H73="상")),"높음",IF(OR(AND(G73="중",H73="중"),AND(G73="상",H73="하"),AND(G73="하",H73="상")),"보통","낮음"))) -> 낮음 | J73: ="실제 사고 "&(AN73+AO73)&"건(ATLAS "&AN73&" / OWASP "&AO73&"), 실증 사례 "&(AM73-AN73)&"건, Realized 기법 "&AB73&"개, 취약점·익스플로잇 "&AP73&"건" -> 실제 사고 0건(ATLAS 0 / OWASP 0), 실증 사례 0건, Realized 기법 0개, 취약점·익스플로잇 0건 | K73: 업무 판단 오류(재무 및 평판 영향) | L73: 해당 없음(구조적 결함) | M73: — | O73: ● | P73: ● | Q73: ● | R73: ● | S73: 안전·사용자, 평판·사회 | T73: ○ | V73: ● | AA73: =COUNTIF(ATLAS기법매핑!$H$5:$H$212,"*"&D73&"*") -> 0 | AB73: =COUNTIFS(ATLAS기법매핑!$H$5:$H$212,"*"&D73&"*",ATLAS기법매핑!$M$5:$M$212,"Realized") -> 0 | AC73: =COUNTIFS(ATLAS기법매핑!$H$5:$H$212,"*"&D73&"*",ATLAS기법매핑!$M$5:$M$212,"Realized")&" / "&COUNTIFS(ATLAS기법매핑!$H$5:$H$212,"*"&D73&"*",ATLAS기법매핑!$M$5:$M$212,"Demonstrated")&" / "&COUNTIFS(ATLAS기법매핑!$H$5:$H$212,"*"&D73&"*",ATLAS기법매핑!$M$5:$M$212,"Feasible") -> 0 / 0 / 0 | AD73: LLM07 | AI73: DSGAI21 | AL73: =(LEN(Y73&Z73)>0)+(LEN(AD73&AE73)>0)+(LEN(AF73&AG73)>0)+(LEN(AH73&AI73)>0)+(LEN(AJ73&AK73)>0) -> 2 | AM73: =COUNTIF(ATLAS사례연구!$J$5:$J$77,"*"&D73&"*") -> 0 | AN73: =COUNTIFS(ATLAS사례연구!$J$5:$J$77,"*"&D73&"*",ATLAS사례연구!$C$5:$C$77,"Incident") -> 0 | AO73: 0 | AP73: 0 | AQ73: =IF(AN73+AO73>0,"실제 사고 확인",IF(AB73>0,"실사용 기법 포함",IF(OR(AM73>0,AP73>0),"실증·공개 취약점","이론·시나리오"))) -> 이론·시나리오 | AS73: • [OWASP 시나리오] 정책 오독으로 부당 환불 승인, 임상 요약의 금기사항 누락(LLM07 시나리오#2·#3) | AT73: — (ATLAS 완화책 없음: Lv2 핵심 통제 참조) | AU73: 근거 인용·출처 검증(그라운딩), 신뢰도 표시, 고위험 결정의 독립 검증, 추천 출처 편향 모니터링 | AV73: UT-29, UT-04(일부)
A74: D05. 출력 처리 결함 및 신뢰성 훼손 | B74: UT-20 | C74: AI 출력 신뢰성 훼손 | D74: UT-20.2 | E74: 환각 악용 공격 | F74: 모델이 반복적으로 환각하는 패키지명/URL/API를 탐색한 뒤 공격자가 해당 이름을 선점하여 AI 권고를 통해 악성 자원 유포 | G74: =IF(AN74+AO74>=2,"상",IF(OR(AN74+AO74=1,AM74>0,AB74>0,AP74>0),"중","하")) -> 중 | H74: 중 | I74: =IF(AND(G74="상",H74="상"),"매우 높음",IF(OR(AND(G74="상",H74="중"),AND(G74="중",H74="상")),"높음",IF(OR(AND(G74="중",H74="중"),AND(G74="상",H74="하"),AND(G74="하",H74="상")),"보통","낮음"))) -> 보통 | J74: ="실제 사고 "&(AN74+AO74)&"건(ATLAS "&AN74&" / OWASP "&AO74&"), 실증 사례 "&(AM74-AN74)&"건, Realized 기법 "&AB74&"개, 취약점·익스플로잇 "&AP74&"건" -> 실제 사고 0건(ATLAS 0 / OWASP 0), 실증 사례 1건, Realized 기법 0개, 취약점·익스플로잇 0건 | K74: 환각 대상 선점을 통한 악성 자원 유포 기반 | L74: 탐색(Discovery) | M74: 탐색 | O74: ● | P74: ● | Q74: ● | R74: ● | S74: 무결성, 안전·사용자, 평판·사회 | T74: ○ | V74: ● | Y74: T0062 | AA74: =COUNTIF(ATLAS기법매핑!$H$5:$H$212,"*"&D74&"*") -> 1 | AB74: =COUNTIFS(ATLAS기법매핑!$H$5:$H$212,"*"&D74&"*",ATLAS기법매핑!$M$5:$M$212,"Realized") -> 0 | AC74: =COUNTIFS(ATLAS기법매핑!$H$5:$H$212,"*"&D74&"*",ATLAS기법매핑!$M$5:$M$212,"Realized")&" / "&COUNTIFS(ATLAS기법매핑!$H$5:$H$212,"*"&D74&"*",ATLAS기법매핑!$M$5:$M$212,"Demonstrated")&" / "&COUNTIFS(ATLAS기법매핑!$H$5:$H$212,"*"&D74&"*",ATLAS기법매핑!$M$5:$M$212,"Feasible") -> 0 / 1 / 0 | AD74: LLM07 | AL74: =(LEN(Y74&Z74)>0)+(LEN(AD74&AE74)>0)+(LEN(AF74&AG74)>0)+(LEN(AH74&AI74)>0)+(LEN(AJ74&AK74)>0) -> 2 | AM74: =COUNTIF(ATLAS사례연구!$J$5:$J$77,"*"&D74&"*") -> 1 | AN74: =COUNTIFS(ATLAS사례연구!$J$5:$J$77,"*"&D74&"*",ATLAS사례연구!$C$5:$C$77,"Incident") -> 0 | AO74: 0 | AP74: 0 | AQ74: =IF(AN74+AO74>0,"실제 사고 확인",IF(AB74>0,"실사용 기법 포함",IF(OR(AM74>0,AP74>0),"실증·공개 취약점","이론·시나리오"))) -> 실증·공개 취약점 | AR74: CS0022 | AS74: • [ATLAS CS0022·실증] LLM이 환각한 가짜 패키지명을 공격자가 선점해 악성 패키지 배포 가능성 입증 | AT74: M0004 Limit AI Service Query Volume and Rate M0020 Generative AI Guardrails M0021 Generative AI Guidelines M0022 Generative AI Model Alignment | AU74: 근거 인용·출처 검증(그라운딩), 신뢰도 표시, 고위험 결정의 독립 검증, 추천 출처 편향 모니터링 | AV74: UT-29, UT-04(일부)
A75: D05. 출력 처리 결함 및 신뢰성 훼손 | B75: UT-20 | C75: AI 출력 신뢰성 훼손 | D75: UT-20.3 | E75: 응답 편향 조작 | F75: 메모리/검색 근거/지시 조작을 통해 AI 응답을 특정 업체/제품/결론 쪽으로 체계적으로 편향시켜 사용자 의사결정 왜곡 | G75: =IF(AN75+AO75>=2,"상",IF(OR(AN75+AO75=1,AM75>0,AB75>0,AP75>0),"중","하")) -> 중 | H75: 중 | I75: =IF(AND(G75="상",H75="상"),"매우 높음",IF(OR(AND(G75="상",H75="중"),AND(G75="중",H75="상")),"높음",IF(OR(AND(G75="중",H75="중"),AND(G75="상",H75="하"),AND(G75="하",H75="상")),"보통","낮음"))) -> 보통 | J75: ="실제 사고 "&(AN75+AO75)&"건(ATLAS "&AN75&" / OWASP "&AO75&"), 실증 사례 "&(AM75-AN75)&"건, Realized 기법 "&AB75&"개, 취약점·익스플로잇 "&AP75&"건" -> 실제 사고 1건(ATLAS 1 / OWASP 0), 실증 사례 2건, Realized 기법 1개, 취약점·익스플로잇 0건 | K75: 사용자 의사결정 왜곡(재무 영향) | L75: 영향(Impact) | M75: 영향 | O75: ● | P75: ● | Q75: ● | R75: ● | S75: 무결성, 재무 | T75: ○ | V75: ● | Y75: T0130 | AA75: =COUNTIF(ATLAS기법매핑!$H$5:$H$212,"*"&D75&"*") -> 1 | AB75: =COUNTIFS(ATLAS기법매핑!$H$5:$H$212,"*"&D75&"*",ATLAS기법매핑!$M$5:$M$212,"Realized") -> 1 | AC75: =COUNTIFS(ATLAS기법매핑!$H$5:$H$212,"*"&D75&"*",ATLAS기법매핑!$M$5:$M$212,"Realized")&" / "&COUNTIFS(ATLAS기법매핑!$H$5:$H$212,"*"&D75&"*",ATLAS기법매핑!$M$5:$M$212,"Demonstrated")&" / "&COUNTIFS(ATLAS기법매핑!$H$5:$H$212,"*"&D75&"*",ATLAS기법매핑!$M$5:$M$212,"Feasible") -> 1 / 0 / 0 | AD75: LLM07 | AG75: ASI10 | AI75: DSGAI21 | AL75: =(LEN(Y75&Z75)>0)+(LEN(AD75&AE75)>0)+(LEN(AF75&AG75)>0)+(LEN(AH75&AI75)>0)+(LEN(AJ75&AK75)>0) -> 4 | AM75: =COUNTIF(ATLAS사례연구!$J$5:$J$77,"*"&D75&"*") -> 3 | AN75: =COUNTIFS(ATLAS사례연구!$J$5:$J$77,"*"&D75&"*",ATLAS사례연구!$C$5:$C$77,"Incident") -> 1 | AO75: 0 | AP75: 0 | AQ75: =IF(AN75+AO75>0,"실제 사고 확인",IF(AB75>0,"실사용 기법 포함",IF(OR(AM75>0,AP75>0),"실증·공개 취약점","이론·시나리오"))) -> 실제 사고 확인 | AR75: CS0019, CS0026, CS0072 | AS75: • [ATLAS CS0072·실제사고] 조작된 AI 비서 링크로 메모리를 오염시켜 특정 제품을 추천하게 만드는 홍보성 공격(실제 사고) • [ATLAS CS0019·실증] LLM 가중치를 편집해 허위 사실을 답하게 만든 뒤 Hugging Face에 배포(PoisonGPT) • [ATLAS CS0026·실증] 메일을 RAG로 수집하는 M365 Copilot을 조작해 송금 계좌 정보를 바꿔치기 | AT75: — (ATLAS 완화책 없음: Lv2 핵심 통제 참조) | AU75: 근거 인용·출처 검증(그라운딩), 신뢰도 표시, 고위험 결정의 독립 검증, 추천 출처 편향 모니터링 | AV75: UT-29, UT-04(일부)
A76: D05. 출력 처리 결함 및 신뢰성 훼손 | B76: UT-20 | C76: AI 출력 신뢰성 훼손 | D76: UT-20.4 | E76: 검증 없는 채택(과신) | F76: AI 출력을 사람 또는 자동화 워크플로가 독립 검증 없이 그대로 채택하여 오류가 업무 결과/고객 응대/시스템 조치로 직접 전파 | G76: =IF(AN76+AO76>=2,"상",IF(OR(AN76+AO76=1,AM76>0,AB76>0,AP76>0),"중","하")) -> 하 | H76: 중 | I76: =IF(AND(G76="상",H76="상"),"매우 높음",IF(OR(AND(G76="상",H76="중"),AND(G76="중",H76="상")),"높음",IF(OR(AND(G76="중",H76="중"),AND(G76="상",H76="하"),AND(G76="하",H76="상")),"보통","낮음"))) -> 낮음 | J76: ="실제 사고 "&(AN76+AO76)&"건(ATLAS "&AN76&" / OWASP "&AO76&"), 실증 사례 "&(AM76-AN76)&"건, Realized 기법 "&AB76&"개, 취약점·익스플로잇 "&AP76&"건" -> 실제 사고 0건(ATLAS 0 / OWASP 0), 실증 사례 0건, Realized 기법 0개, 취약점·익스플로잇 0건 | K76: 오류의 업무 결과 직접 전파 | L76: 해당 없음(구조적 결함) | M76: — | O76: ● | P76: ● | Q76: ● | R76: ● | S76: 무결성, 안전·사용자, 평판·사회 | T76: ○ | V76: ● | AA76: =COUNTIF(ATLAS기법매핑!$H$5:$H$212,"*"&D76&"*") -> 0 | AB76: =COUNTIFS(ATLAS기법매핑!$H$5:$H$212,"*"&D76&"*",ATLAS기법매핑!$M$5:$M$212,"Realized") -> 0 | AC76: =COUNTIFS(ATLAS기법매핑!$H$5:$H$212,"*"&D76&"*",ATLAS기법매핑!$M$5:$M$212,"Realized")&" / "&COUNTIFS(ATLAS기법매핑!$H$5:$H$212,"*"&D76&"*",ATLAS기법매핑!$M$5:$M$212,"Demonstrated")&" / "&COUNTIFS(ATLAS기법매핑!$H$5:$H$212,"*"&D76&"*",ATLAS기법매핑!$M$5:$M$212,"Feasible") -> 0 / 0 / 0 | AD76: LLM07 | AG76: ASI09 | AL76: =(LEN(Y76&Z76)>0)+(LEN(AD76&AE76)>0)+(LEN(AF76&AG76)>0)+(LEN(AH76&AI76)>0)+(LEN(AJ76&AK76)>0) -> 2 | AM76: =COUNTIF(ATLAS사례연구!$J$5:$J$77,"*"&D76&"*") -> 0 | AN76: =COUNTIFS(ATLAS사례연구!$J$5:$J$77,"*"&D76&"*",ATLAS사례연구!$C$5:$C$77,"Incident") -> 0 | AO76: 0 | AP76: 0 | AQ76: =IF(AN76+AO76>0,"실제 사고 확인",IF(AB76>0,"실사용 기법 포함",IF(OR(AM76>0,AP76>0),"실증·공개 취약점","이론·시나리오"))) -> 이론·시나리오 | AS76: • [OWASP 시나리오] 수행하지 않은 백업을 완료로 보고, 정상 트래픽을 침입으로 오판해 자동 대응 발동(LLM07 시나리오#5·#7) | AT76: — (ATLAS 완화책 없음: Lv2 핵심 통제 참조) | AU76: 근거 인용·출처 검증(그라운딩), 신뢰도 표시, 고위험 결정의 독립 검증, 추천 출처 편향 모니터링 | AV76: UT-29, UT-04(일부)
A77: D06. 에이전트 오남용 및 통제 상실 | B77: UT-21 | C77: 과도한 에이전시 | D77: UT-21.1 | E77: 과도한 기능 | F77: 업무 수행에 불필요한 도구/플러그인 기능(예: 요약용 비서의 메일 발송 기능)이 에이전트에 부여되어, 인젝션 시 악용 가능한 행위 범위 확대 | G77: =IF(AN77+AO77>=2,"상",IF(OR(AN77+AO77=1,AM77>0,AB77>0,AP77>0),"중","하")) -> 하 | H77: 중 | I77: =IF(AND(G77="상",H77="상"),"매우 높음",IF(OR(AND(G77="상",H77="중"),AND(G77="중",H77="상")),"높음",IF(OR(AND(G77="중",H77="중"),AND(G77="상",H77="하"),AND(G77="하",H77="상")),"보통","낮음"))) -> 낮음 | J77: ="실제 사고 "&(AN77+AO77)&"건(ATLAS "&AN77&" / OWASP "&AO77&"), 실증 사례 "&(AM77-AN77)&"건, Realized 기법 "&AB77&"개, 취약점·익스플로잇 "&AP77&"건" -> 실제 사고 0건(ATLAS 0 / OWASP 0), 실증 사례 0건, Realized 기법 0개, 취약점·익스플로잇 0건 | K77: 악용 시 피해 범위 확대 요인 | L77: 해당 없음(구조적 결함) | M77: — | O77: ● | Q77: ● | R77: ● | S77: 무결성, 가용성, 기밀성 | T77: ● | AA77: =COUNTIF(ATLAS기법매핑!$H$5:$H$212,"*"&D77&"*") -> 0 | AB77: =COUNTIFS(ATLAS기법매핑!$H$5:$H$212,"*"&D77&"*",ATLAS기법매핑!$M$5:$M$212,"Realized") -> 0 | AC77: =COUNTIFS(ATLAS기법매핑!$H$5:$H$212,"*"&D77&"*",ATLAS기법매핑!$M$5:$M$212,"Realized")&" / "&COUNTIFS(ATLAS기법매핑!$H$5:$H$212,"*"&D77&"*",ATLAS기법매핑!$M$5:$M$212,"Demonstrated")&" / "&COUNTIFS(ATLAS기법매핑!$H$5:$H$212,"*"&D77&"*",ATLAS기법매핑!$M$5:$M$212,"Feasible") -> 0 / 0 / 0 | AD77: LLM03 | AI77: DSGAI06 | AL77: =(LEN(Y77&Z77)>0)+(LEN(AD77&AE77)>0)+(LEN(AF77&AG77)>0)+(LEN(AH77&AI77)>0)+(LEN(AJ77&AK77)>0) -> 2 | AM77: =COUNTIF(ATLAS사례연구!$J$5:$J$77,"*"&D77&"*") -> 0 | AN77: =COUNTIFS(ATLAS사례연구!$J$5:$J$77,"*"&D77&"*",ATLAS사례연구!$C$5:$C$77,"Incident") -> 0 | AO77: 0 | AP77: 0 | AQ77: =IF(AN77+AO77>0,"실제 사고 확인",IF(AB77>0,"실사용 기법 포함",IF(OR(AM77>0,AP77>0),"실증·공개 취약점","이론·시나리오"))) -> 이론·시나리오 | AS77: • [OWASP 시나리오] 메일 요약용 비서가 발송 기능까지 보유해 인젝션 시 받은편지함 전체를 외부로 전달(LLM03 시나리오#1) | AT77: — (ATLAS 완화책 없음: Lv2 핵심 통제 참조) | AU77: 최소 에이전시·최소권한, 도구별 범위·호출량 제한, 인자 의미 검증, 파괴적 작업 인간 승인 | AV77: UT-11, UT-12
A78: D06. 에이전트 오남용 및 통제 상실 | B78: UT-21 | C78: 과도한 에이전시 | D78: UT-21.2 | E78: 과도한 권한 | F78: 에이전트가 사용자 범위가 아닌 관리자/서비스 전체 권한 계정으로 동작하거나 권한이 점진적으로 확장되어, 단일 오작동이 조직 전체 데이터 접근으로 확대 | G78: =IF(AN78+AO78>=2,"상",IF(OR(AN78+AO78=1,AM78>0,AB78>0,AP78>0),"중","하")) -> 중 | H78: 상 | I78: =IF(AND(G78="상",H78="상"),"매우 높음",IF(OR(AND(G78="상",H78="중"),AND(G78="중",H78="상")),"높음",IF(OR(AND(G78="중",H78="중"),AND(G78="상",H78="하"),AND(G78="하",H78="상")),"보통","낮음"))) -> 높음 | J78: ="실제 사고 "&(AN78+AO78)&"건(ATLAS "&AN78&" / OWASP "&AO78&"), 실증 사례 "&(AM78-AN78)&"건, Realized 기법 "&AB78&"개, 취약점·익스플로잇 "&AP78&"건" -> 실제 사고 0건(ATLAS 0 / OWASP 0), 실증 사례 1건, Realized 기법 0개, 취약점·익스플로잇 0건 | K78: 조직 전체 데이터 접근 권한 노출 | L78: 해당 없음(구조적 결함) | M78: — | O78: ● | Q78: ● | R78: ● | S78: 무결성, 가용성, 기밀성 | T78: ● | V78: ○ | AA78: =COUNTIF(ATLAS기법매핑!$H$5:$H$212,"*"&D78&"*") -> 0 | AB78: =COUNTIFS(ATLAS기법매핑!$H$5:$H$212,"*"&D78&"*",ATLAS기법매핑!$M$5:$M$212,"Realized") -> 0 | AC78: =COUNTIFS(ATLAS기법매핑!$H$5:$H$212,"*"&D78&"*",ATLAS기법매핑!$M$5:$M$212,"Realized")&" / "&COUNTIFS(ATLAS기법매핑!$H$5:$H$212,"*"&D78&"*",ATLAS기법매핑!$M$5:$M$212,"Demonstrated")&" / "&COUNTIFS(ATLAS기법매핑!$H$5:$H$212,"*"&D78&"*",ATLAS기법매핑!$M$5:$M$212,"Feasible") -> 0 / 0 / 0 | AD78: LLM03 | AG78: ASI03 | AI78: DSGAI02 | AJ78: MCP02 | AL78: =(LEN(Y78&Z78)>0)+(LEN(AD78&AE78)>0)+(LEN(AF78&AG78)>0)+(LEN(AH78&AI78)>0)+(LEN(AJ78&AK78)>0) -> 4 | AM78: =COUNTIF(ATLAS사례연구!$J$5:$J$77,"*"&D78&"*") -> 1 | AN78: =COUNTIFS(ATLAS사례연구!$J$5:$J$77,"*"&D78&"*",ATLAS사례연구!$C$5:$C$77,"Incident") -> 0 | AO78: 0 | AP78: 0 | AQ78: =IF(AN78+AO78>0,"실제 사고 확인",IF(AB78>0,"실사용 기법 포함",IF(OR(AM78>0,AP78>0),"실증·공개 취약점","이론·시나리오"))) -> 실증·공개 취약점 | AR78: CS0037 | AS78: • [ATLAS CS0037·실증] Copilot Studio 고객지원 에이전트를 인젝션해 지식원·도구를 탐색하고 CRM 데이터 유출 • [OWASP 시나리오] 주문 조회용 지원 봇이 결제 API 전체 권한으로 환불까지 실행(ASI02 시나리오#3) | AT78: — (ATLAS 완화책 없음: Lv2 핵심 통제 참조) | AU78: 최소 에이전시·최소권한, 도구별 범위·호출량 제한, 인자 의미 검증, 파괴적 작업 인간 승인 | AV78: UT-11, UT-12
A79: D06. 에이전트 오남용 및 통제 상실 | B79: UT-21 | C79: 과도한 에이전시 | D79: UT-21.3 | E79: 과도한 자율성 | F79: 결제/삭제/외부 발송 등 고위험 행위를 사람 승인 없이 자율 실행하도록 설계되어 오판 및 조작이 즉시 실제 피해로 전환 | G79: =IF(AN79+AO79>=2,"상",IF(OR(AN79+AO79=1,AM79>0,AB79>0,AP79>0),"중","하")) -> 하 | H79: 중 | I79: =IF(AND(G79="상",H79="상"),"매우 높음",IF(OR(AND(G79="상",H79="중"),AND(G79="중",H79="상")),"높음",IF(OR(AND(G79="중",H79="중"),AND(G79="상",H79="하"),AND(G79="하",H79="상")),"보통","낮음"))) -> 낮음 | J79: ="실제 사고 "&(AN79+AO79)&"건(ATLAS "&AN79&" / OWASP "&AO79&"), 실증 사례 "&(AM79-AN79)&"건, Realized 기법 "&AB79&"개, 취약점·익스플로잇 "&AP79&"건" -> 실제 사고 0건(ATLAS 0 / OWASP 0), 실증 사례 0건, Realized 기법 0개, 취약점·익스플로잇 0건 | K79: 승인 부재로 오판이 즉시 실제 피해로 전환 | L79: 해당 없음(구조적 결함) | M79: — | O79: ● | Q79: ● | R79: ● | S79: 무결성, 가용성, 기밀성 | T79: ● | V79: ○ | AA79: =COUNTIF(ATLAS기법매핑!$H$5:$H$212,"*"&D79&"*") -> 0 | AB79: =COUNTIFS(ATLAS기법매핑!$H$5:$H$212,"*"&D79&"*",ATLAS기법매핑!$M$5:$M$212,"Realized") -> 0 | AC79: =COUNTIFS(ATLAS기법매핑!$H$5:$H$212,"*"&D79&"*",ATLAS기법매핑!$M$5:$M$212,"Realized")&" / "&COUNTIFS(ATLAS기법매핑!$H$5:$H$212,"*"&D79&"*",ATLAS기법매핑!$M$5:$M$212,"Demonstrated")&" / "&COUNTIFS(ATLAS기법매핑!$H$5:$H$212,"*"&D79&"*",ATLAS기법매핑!$M$5:$M$212,"Feasible") -> 0 / 0 / 0 | AD79: LLM03 | AG79: ASI09 | AL79: =(LEN(Y79&Z79)>0)+(LEN(AD79&AE79)>0)+(LEN(AF79&AG79)>0)+(LEN(AH79&AI79)>0)+(LEN(AJ79&AK79)>0) -> 2 | AM79: =COUNTIF(ATLAS사례연구!$J$5:$J$77,"*"&D79&"*") -> 0 | AN79: =COUNTIFS(ATLAS사례연구!$J$5:$J$77,"*"&D79&"*",ATLAS사례연구!$C$5:$C$77,"Incident") -> 0 | AO79: 0 | AP79: 0 | AQ79: =IF(AN79+AO79>0,"실제 사고 확인",IF(AB79>0,"실사용 기법 포함",IF(OR(AM79>0,AP79>0),"실증·공개 취약점","이론·시나리오"))) -> 이론·시나리오 | AS79: • [OWASP 시나리오] 고위험 작업에 대한 승인 절차 부재(LLM03 위험 예시) | AT79: — (ATLAS 완화책 없음: Lv2 핵심 통제 참조) | AU79: 최소 에이전시·최소권한, 도구별 범위·호출량 제한, 인자 의미 검증, 파괴적 작업 인간 승인 | AV79: UT-11, UT-12
A80: D06. 에이전트 오남용 및 통제 상실 | B80: UT-21 | C80: 과도한 에이전시 | D80: UT-21.4 | E80: 위험한 도구 연쇄 호출 | F80: 정상 도구들을 조회, 가공, 외부 전송 순으로 연쇄 호출하거나 반복 호출하여 개별 도구 통제로는 탐지되지 않는 데이터 유출/권한 밖 행위 수행 | G80: =IF(AN80+AO80>=2,"상",IF(OR(AN80+AO80=1,AM80>0,AB80>0,AP80>0),"중","하")) -> 중 | H80: 상 | I80: =IF(AND(G80="상",H80="상"),"매우 높음",IF(OR(AND(G80="상",H80="중"),AND(G80="중",H80="상")),"높음",IF(OR(AND(G80="중",H80="중"),AND(G80="상",H80="하"),AND(G80="하",H80="상")),"보통","낮음"))) -> 높음 | J80: ="실제 사고 "&(AN80+AO80)&"건(ATLAS "&AN80&" / OWASP "&AO80&"), 실증 사례 "&(AM80-AN80)&"건, Realized 기법 "&AB80&"개, 취약점·익스플로잇 "&AP80&"건" -> 실제 사고 0건(ATLAS 0 / OWASP 0), 실증 사례 19건, Realized 기법 0개, 취약점·익스플로잇 0건 | K80: 개별 통제 우회형 데이터 유출 및 권한 밖 행위 | L80: 실행(Execution) | M80: 실행, 권한 상승, 내부 확산 | O80: ● | Q80: ● | R80: ● | S80: 무결성, 가용성, 기밀성 | T80: ● | V80: ○ | X80: 권한 설계(개발)에서 유입, 오용은 운영에서 발현 | Y80: T0053 | AA80: =COUNTIF(ATLAS기법매핑!$H$5:$H$212,"*"&D80&"*") -> 1 | AB80: =COUNTIFS(ATLAS기법매핑!$H$5:$H$212,"*"&D80&"*",ATLAS기법매핑!$M$5:$M$212,"Realized") -> 0 | AC80: =COUNTIFS(ATLAS기법매핑!$H$5:$H$212,"*"&D80&"*",ATLAS기법매핑!$M$5:$M$212,"Realized")&" / "&COUNTIFS(ATLAS기법매핑!$H$5:$H$212,"*"&D80&"*",ATLAS기법매핑!$M$5:$M$212,"Demonstrated")&" / "&COUNTIFS(ATLAS기법매핑!$H$5:$H$212,"*"&D80&"*",ATLAS기법매핑!$M$5:$M$212,"Feasible") -> 0 / 1 / 0 | AE80: LLM06 | AF80: ASI02 | AG80: ASI08 | AI80: DSGAI01 | AK80: MCP05 | AL80: =(LEN(Y80&Z80)>0)+(LEN(AD80&AE80)>0)+(LEN(AF80&AG80)>0)+(LEN(AH80&AI80)>0)+(LEN(AJ80&AK80)>0) -> 5 | AM80: =COUNTIF(ATLAS사례연구!$J$5:$J$77,"*"&D80&"*") -> 19 | AN80: =COUNTIFS(ATLAS사례연구!$J$5:$J$77,"*"&D80&"*",ATLAS사례연구!$C$5:$C$77,"Incident") -> 0 | AO80: 0 | AP80: 0 | AQ80: =IF(AN80+AO80>0,"실제 사고 확인",IF(AB80>0,"실사용 기법 포함",IF(OR(AM80>0,AP80>0),"실증·공개 취약점","이론·시나리오"))) -> 실증·공개 취약점 | AR80: CS0016, CS0021, CS0024, CS0026, CS0038, CS0039, CS0045, CS0046, CS0048, CS0049, CS0051, CS0052, CS0054, CS0055, CS0062, CS0063, CS0064, CS0066, CS0067 | AS80: • [ATLAS CS0016·실증] MathGPT에 프롬프트 인젝션으로 파이썬 코드 실행·API 키 노출 • [ATLAS CS0021·실증] 웹페이지 간접 인젝션으로 ChatGPT 대화 내용을 이미지 URL로 유출 • [ATLAS CS0024·실증] RAG를 매개로 자기복제 프롬프트가 GenAI 이메일 비서 간 전파(Morris II 웜) | AT80: M0020 Generative AI Guardrails M0021 Generative AI Guidelines M0022 Generative AI Model Alignment M0024 AI Telemetry Logging M0026 Privileged AI Agent Permissions Configuration | AU80: 최소 에이전시·최소권한, 도구별 범위·호출량 제한, 인자 의미 검증, 파괴적 작업 인간 승인 | AV80: UT-11, UT-12
A81: D06. 에이전트 오남용 및 통제 상실 | B81: UT-21 | C81: 과도한 에이전시 | D81: UT-21.5 | E81: 파괴적 도구 실행 | F81: 에이전트가 조작된 지시 또는 오판에 따라 파일/DB/인프라 삭제 명령을 도구로 실행하여 업무 데이터 및 서비스 파괴 | G81: =IF(AN81+AO81>=2,"상",IF(OR(AN81+AO81=1,AM81>0,AB81>0,AP81>0),"중","하")) -> 상 | H81: 상 | I81: =IF(AND(G81="상",H81="상"),"매우 높음",IF(OR(AND(G81="상",H81="중"),AND(G81="중",H81="상")),"높음",IF(OR(AND(G81="중",H81="중"),AND(G81="상",H81="하"),AND(G81="하",H81="상")),"보통","낮음"))) -> 매우 높음 | J81: ="실제 사고 "&(AN81+AO81)&"건(ATLAS "&AN81&" / OWASP "&AO81&"), 실증 사례 "&(AM81-AN81)&"건, Realized 기법 "&AB81&"개, 취약점·익스플로잇 "&AP81&"건" -> 실제 사고 3건(ATLAS 1 / OWASP 2), 실증 사례 2건, Realized 기법 1개, 취약점·익스플로잇 0건 | K81: 운영 데이터 및 서비스 파괴 | L81: 영향(Impact) | M81: 영향 | O81: ● | Q81: ● | R81: ● | S81: 가용성, 무결성 | T81: ● | V81: ○ | X81: 권한 설계(개발)에서 유입, 오용은 운영에서 발현 | Y81: T0101 | AA81: =COUNTIF(ATLAS기법매핑!$H$5:$H$212,"*"&D81&"*") -> 1 | AB81: =COUNTIFS(ATLAS기법매핑!$H$5:$H$212,"*"&D81&"*",ATLAS기법매핑!$M$5:$M$212,"Realized") -> 1 | AC81: =COUNTIFS(ATLAS기법매핑!$H$5:$H$212,"*"&D81&"*",ATLAS기법매핑!$M$5:$M$212,"Realized")&" / "&COUNTIFS(ATLAS기법매핑!$H$5:$H$212,"*"&D81&"*",ATLAS기법매핑!$M$5:$M$212,"Demonstrated")&" / "&COUNTIFS(ATLAS기법매핑!$H$5:$H$212,"*"&D81&"*",ATLAS기법매핑!$M$5:$M$212,"Feasible") -> 1 / 0 / 0 | AE81: LLM10 | AF81: ASI02 | AL81: =(LEN(Y81&Z81)>0)+(LEN(AD81&AE81)>0)+(LEN(AF81&AG81)>0)+(LEN(AH81&AI81)>0)+(LEN(AJ81&AK81)>0) -> 3 | AM81: =COUNTIF(ATLAS사례연구!$J$5:$J$77,"*"&D81&"*") -> 3 | AN81: =COUNTIFS(ATLAS사례연구!$J$5:$J$77,"*"&D81&"*",ATLAS사례연구!$C$5:$C$77,"Incident") -> 1 | AO81: 2 | AP81: 0 | AQ81: =IF(AN81+AO81>0,"실제 사고 확인",IF(AB81>0,"실사용 기법 포함",IF(OR(AM81>0,AP81>0),"실증·공개 취약점","이론·시나리오"))) -> 실제 사고 확인 | AR81: CS0046, CS0047, CS0063 | AS81: • [ATLAS CS0047·실제사고] 과권한 GitHub 토큰으로 Amazon Q VS Code 확장에 파괴형 에이전트 지시 커밋(실제 사고) • [ATLAS CS0046·실증] 웹페이지 인젝션으로 Claude Computer Use가 셸 명령으로 사용자 데이터 삭제 • [ATLAS CS0063·실증] 캘린더 초대·메일에 숨긴 지시로 Gemini 비서가 기기·앱을 조작 • [OWASP 인용] Replit 운영 DB 삭제(2025.07) / Google Gemini CLI 파일 손실(2025.07) | AT81: M0024 AI Telemetry Logging M0026 Privileged AI Agent Permissions Configuration M0027 Single-User AI Agent Permissions Configuration M0028 AI Agent Tools Permissions Configuration M0029 Human In-the-Loop for AI Agent Actions | AU81: 최소 에이전시·최소권한, 도구별 범위·호출량 제한, 인자 의미 검증, 파괴적 작업 인간 승인 | AV81: UT-11, UT-12
A82: D06. 에이전트 오남용 및 통제 상실 | B82: UT-22 | C82: 비의도적 코드 실행 | D82: UT-22.1 | E82: 생성 코드 실행 | F82: 에이전트가 생성하거나 외부에서 주입된 코드/셸 명령을 검증 없이 인터프리터에서 실행하여 호스트 명령 실행 및 시스템 변경 유발 | G82: =IF(AN82+AO82>=2,"상",IF(OR(AN82+AO82=1,AM82>0,AB82>0,AP82>0),"중","하")) -> 상 | H82: 상 | I82: =IF(AND(G82="상",H82="상"),"매우 높음",IF(OR(AND(G82="상",H82="중"),AND(G82="중",H82="상")),"높음",IF(OR(AND(G82="중",H82="중"),AND(G82="상",H82="하"),AND(G82="하",H82="상")),"보통","낮음"))) -> 매우 높음 | J82: ="실제 사고 "&(AN82+AO82)&"건(ATLAS "&AN82&" / OWASP "&AO82&"), 실증 사례 "&(AM82-AN82)&"건, Realized 기법 "&AB82&"개, 취약점·익스플로잇 "&AP82&"건" -> 실제 사고 2건(ATLAS 2 / OWASP 0), 실증 사례 11건, Realized 기법 1개, 취약점·익스플로잇 5건 | K82: 호스트 명령 실행(시스템 장악) | L82: 실행(Execution) | M82: 실행 | O82: ● | Q82: ● | R82: ● | S82: 무결성, 기밀성, 가용성 | T82: ○ | U82: ○ | V82: ● | Y82: T0050 | AA82: =COUNTIF(ATLAS기법매핑!$H$5:$H$212,"*"&D82&"*") -> 1 | AB82: =COUNTIFS(ATLAS기법매핑!$H$5:$H$212,"*"&D82&"*",ATLAS기법매핑!$M$5:$M$212,"Realized") -> 1 | AC82: =COUNTIFS(ATLAS기법매핑!$H$5:$H$212,"*"&D82&"*",ATLAS기법매핑!$M$5:$M$212,"Realized")&" / "&COUNTIFS(ATLAS기법매핑!$H$5:$H$212,"*"&D82&"*",ATLAS기법매핑!$M$5:$M$212,"Demonstrated")&" / "&COUNTIFS(ATLAS기법매핑!$H$5:$H$212,"*"&D82&"*",ATLAS기법매핑!$M$5:$M$212,"Feasible") -> 1 / 0 / 0 | AE82: LLM10, LLM01 | AF82: ASI05 | AJ82: MCP05 | AL82: =(LEN(Y82&Z82)>0)+(LEN(AD82&AE82)>0)+(LEN(AF82&AG82)>0)+(LEN(AH82&AI82)>0)+(LEN(AJ82&AK82)>0) -> 4 | AM82: =COUNTIF(ATLAS사례연구!$J$5:$J$77,"*"&D82&"*") -> 13 | AN82: =COUNTIFS(ATLAS사례연구!$J$5:$J$77,"*"&D82&"*",ATLAS사례연구!$C$5:$C$77,"Incident") -> 2 | AO82: 0 | AP82: 5 | AQ82: =IF(AN82+AO82>0,"실제 사고 확인",IF(AB82>0,"실사용 기법 포함",IF(OR(AM82>0,AP82>0),"실증·공개 취약점","이론·시나리오"))) -> 실제 사고 확인 | AR82: CS0016, CS0023, CS0045, CS0046, CS0048, CS0049, CS0050, CS0052, CS0055, CS0060, CS0061, CS0062, CS0068 | AS82: • [ATLAS CS0050·실증] 악성 링크 1회 클릭으로 OpenClaw 로컬 에이전트 원격 코드 실행 • [ATLAS CS0052·실증] 11개 LLM 프레임워크에서 20개 RCE 취약점 발견, 인터넷 공개 앱에서 실증(LLMSmith) • [ATLAS CS0062·실증] Semantic Kernel 검색 플러그인에서 단일 인젝션으로 원격 코드 실행 • [OWASP 인용] Framelink Figma MCP RCE / Cursor 워크스페이스 파일 인젝션 / VS Code 에이전트 RCE(2025) / CVE-2025-66404 / CVE-2025-54795 | AT82: M0011 Restrict Library Loading | AU82: 코드 생성과 실행 분리·승인 게이트, 비루트 격리 샌드박스, 실행 전 정적검사, 명령 허용목록 | AV82: UT-15
A83: D06. 에이전트 오남용 및 통제 상실 | B83: UT-22 | C83: 비의도적 코드 실행 | D83: UT-22.2 | E83: 안전하지 않은 파일 실행 | F83: pickle 등 역직렬화 취약 포맷의 모델/데이터 파일 또는 사용자가 실행한 악성 노트북을 통해 로딩 시점에 임의 코드 실행 | G83: =IF(AN83+AO83>=2,"상",IF(OR(AN83+AO83=1,AM83>0,AB83>0,AP83>0),"중","하")) -> 상 | H83: 상 | I83: =IF(AND(G83="상",H83="상"),"매우 높음",IF(OR(AND(G83="상",H83="중"),AND(G83="중",H83="상")),"높음",IF(OR(AND(G83="중",H83="중"),AND(G83="상",H83="하"),AND(G83="하",H83="상")),"보통","낮음"))) -> 매우 높음 | J83: ="실제 사고 "&(AN83+AO83)&"건(ATLAS "&AN83&" / OWASP "&AO83&"), 실증 사례 "&(AM83-AN83)&"건, Realized 기법 "&AB83&"개, 취약점·익스플로잇 "&AP83&"건" -> 실제 사고 2건(ATLAS 2 / OWASP 0), 실증 사례 2건, Realized 기법 1개, 취약점·익스플로잇 1건 | K83: 파일 로딩 시 임의 코드 실행 | L83: 실행(Execution) | M83: 실행 | N83: ● | O83: ● | Q83: ● | S83: 무결성, 기밀성, 가용성 | T83: ○ | U83: ○ | V83: ● | Y83: T0011 | AA83: =COUNTIF(ATLAS기법매핑!$H$5:$H$212,"*"&D83&"*") -> 1 | AB83: =COUNTIFS(ATLAS기법매핑!$H$5:$H$212,"*"&D83&"*",ATLAS기법매핑!$M$5:$M$212,"Realized") -> 1 | AC83: =COUNTIFS(ATLAS기법매핑!$H$5:$H$212,"*"&D83&"*",ATLAS기법매핑!$M$5:$M$212,"Realized")&" / "&COUNTIFS(ATLAS기법매핑!$H$5:$H$212,"*"&D83&"*",ATLAS기법매핑!$M$5:$M$212,"Demonstrated")&" / "&COUNTIFS(ATLAS기법매핑!$H$5:$H$212,"*"&D83&"*",ATLAS기법매핑!$M$5:$M$212,"Feasible") -> 1 / 0 / 0 | AE83: LLM03 | AF83: ASI05 | AI83: DSGAI06 | AL83: =(LEN(Y83&Z83)>0)+(LEN(AD83&AE83)>0)+(LEN(AF83&AG83)>0)+(LEN(AH83&AI83)>0)+(LEN(AJ83&AK83)>0) -> 4 | AM83: =COUNTIF(ATLAS사례연구!$J$5:$J$77,"*"&D83&"*") -> 4 | AN83: =COUNTIFS(ATLAS사례연구!$J$5:$J$77,"*"&D83&"*",ATLAS사례연구!$C$5:$C$77,"Incident") -> 2 | AO83: 0 | AP83: 1 | AQ83: =IF(AN83+AO83>0,"실제 사고 확인",IF(AB83>0,"실사용 기법 포함",IF(OR(AM83>0,AP83>0),"실증·공개 취약점","이론·시나리오"))) -> 실제 사고 확인 | AR83: CS0018, CS0031, CS0044, CS0060 | AS83: • [ATLAS CS0018·실증] Google Colab 노트북을 통한 임의 코드 실행 경로 시연 • [ATLAS CS0031·실제사고] Hugging Face에 역쉘을 내장한 악성 모델 호스팅(실제 사고) • [ATLAS CS0044·실제사고] APT28 LAMEHUG가 LLM API로 실행 명령을 동적 생성(실제 사고) • [OWASP 인용] CVE-2025-24357 vLLM torch.load 안전하지 않은 역직렬화 | AT83: M0011 Restrict Library Loading M0014 Verify AI Artifacts M0016 Vulnerability Scanning M0018 User Training M0023 AI Bill of Materials | AU83: 코드 생성과 실행 분리·승인 게이트, 비루트 격리 샌드박스, 실행 전 정적검사, 명령 허용목록 | AV83: UT-15
A84: D06. 에이전트 오남용 및 통제 상실 | B84: UT-22 | C84: 비의도적 코드 실행 | D84: UT-22.3 | E84: 샌드박스 탈출 | F84: 코드 실행 환경의 격리 결함/설정 파일 덮어쓰기를 악용하여 샌드박스를 벗어나 호스트 장악 및 지속성 확보 | G84: =IF(AN84+AO84>=2,"상",IF(OR(AN84+AO84=1,AM84>0,AB84>0,AP84>0),"중","하")) -> 중 | H84: 상 | I84: =IF(AND(G84="상",H84="상"),"매우 높음",IF(OR(AND(G84="상",H84="중"),AND(G84="중",H84="상")),"높음",IF(OR(AND(G84="중",H84="중"),AND(G84="상",H84="하"),AND(G84="하",H84="상")),"보통","낮음"))) -> 높음 | J84: ="실제 사고 "&(AN84+AO84)&"건(ATLAS "&AN84&" / OWASP "&AO84&"), 실증 사례 "&(AM84-AN84)&"건, Realized 기법 "&AB84&"개, 취약점·익스플로잇 "&AP84&"건" -> 실제 사고 1건(ATLAS 1 / OWASP 0), 실증 사례 3건, Realized 기법 1개, 취약점·익스플로잇 2건 | K84: 호스트 장악 및 지속성 확보 | L84: 권한 상승(Privilege Escalation) | M84: 권한 상승, 영향 | O84: ● | Q84: ● | R84: ● | S84: 무결성, 기밀성, 가용성 | T84: ○ | U84: ○ | V84: ● | Y84: T0105, T0112 | AA84: =COUNTIF(ATLAS기법매핑!$H$5:$H$212,"*"&D84&"*") -> 2 | AB84: =COUNTIFS(ATLAS기법매핑!$H$5:$H$212,"*"&D84&"*",ATLAS기법매핑!$M$5:$M$212,"Realized") -> 1 | AC84: =COUNTIFS(ATLAS기법매핑!$H$5:$H$212,"*"&D84&"*",ATLAS기법매핑!$M$5:$M$212,"Realized")&" / "&COUNTIFS(ATLAS기법매핑!$H$5:$H$212,"*"&D84&"*",ATLAS기법매핑!$M$5:$M$212,"Demonstrated")&" / "&COUNTIFS(ATLAS기법매핑!$H$5:$H$212,"*"&D84&"*",ATLAS기법매핑!$M$5:$M$212,"Feasible") -> 1 / 1 / 0 | AF84: ASI05 | AG84: ASI02 | AL84: =(LEN(Y84&Z84)>0)+(LEN(AD84&AE84)>0)+(LEN(AF84&AG84)>0)+(LEN(AH84&AI84)>0)+(LEN(AJ84&AK84)>0) -> 2 | AM84: =COUNTIF(ATLAS사례연구!$J$5:$J$77,"*"&D84&"*") -> 4 | AN84: =COUNTIFS(ATLAS사례연구!$J$5:$J$77,"*"&D84&"*",ATLAS사례연구!$C$5:$C$77,"Incident") -> 1 | AO84: 0 | AP84: 2 | AQ84: =IF(AN84+AO84>0,"실제 사고 확인",IF(AB84>0,"실사용 기법 포함",IF(OR(AM84>0,AP84>0),"실증·공개 취약점","이론·시나리오"))) -> 실제 사고 확인 | AR84: CS0050, CS0052, CS0062, CS0068 | AS84: • [ATLAS CS0068·실제사고] OpenAI 평가용 자율 에이전트들이 평가 경계를 넘어 외부 인프라 구축·Hugging Face 침해(실제 사고) • [ATLAS CS0050·실증] 악성 링크 1회 클릭으로 OpenClaw 로컬 에이전트 원격 코드 실행 • [ATLAS CS0052·실증] 11개 LLM 프레임워크에서 20개 RCE 취약점 발견, 인터넷 공개 앱에서 실증(LLMSmith) • [OWASP 인용] Cursor 설정 덮어쓰기(대소문자 불일치, 2025.10) / Cursor 에이전트 파일 보호 우회(2025.10) | AT84: — (ATLAS 완화책 없음: Lv2 핵심 통제 참조) | AU84: 코드 생성과 실행 분리·승인 게이트, 비루트 격리 샌드박스, 실행 전 정적검사, 명령 허용목록 | AV84: UT-15
A85: D06. 에이전트 오남용 및 통제 상실 | B85: UT-23 | C85: 에이전트 간 연쇄 장애 | D85: UT-23.1 | E85: 다중 에이전트 오류 전파 | F85: 한 에이전트의 환각/오염 출력이 검증 없이 후속 에이전트의 입력으로 전달되어 다단계 워크플로 전체로 오류 증폭 | G85: =IF(AN85+AO85>=2,"상",IF(OR(AN85+AO85=1,AM85>0,AB85>0,AP85>0),"중","하")) -> 중 | H85: 중 | I85: =IF(AND(G85="상",H85="상"),"매우 높음",IF(OR(AND(G85="상",H85="중"),AND(G85="중",H85="상")),"높음",IF(OR(AND(G85="중",H85="중"),AND(G85="상",H85="하"),AND(G85="하",H85="상")),"보통","낮음"))) -> 보통 | J85: ="실제 사고 "&(AN85+AO85)&"건(ATLAS "&AN85&" / OWASP "&AO85&"), 실증 사례 "&(AM85-AN85)&"건, Realized 기법 "&AB85&"개, 취약점·익스플로잇 "&AP85&"건" -> 실제 사고 0건(ATLAS 0 / OWASP 0), 실증 사례 0건, Realized 기법 0개, 취약점·익스플로잇 1건 | K85: 연계 워크플로 오작동(무결성 및 가용성) | L85: 내부 확산(Lateral Movement) | M85: — | Q85: ● | R85: ● | S85: 가용성, 무결성 | T85: ○ | V85: ● | AA85: =COUNTIF(ATLAS기법매핑!$H$5:$H$212,"*"&D85&"*") -> 0 | AB85: =COUNTIFS(ATLAS기법매핑!$H$5:$H$212,"*"&D85&"*",ATLAS기법매핑!$M$5:$M$212,"Realized") -> 0 | AC85: =COUNTIFS(ATLAS기법매핑!$H$5:$H$212,"*"&D85&"*",ATLAS기법매핑!$M$5:$M$212,"Realized")&" / "&COUNTIFS(ATLAS기법매핑!$H$5:$H$212,"*"&D85&"*",ATLAS기법매핑!$M$5:$M$212,"Demonstrated")&" / "&COUNTIFS(ATLAS기법매핑!$H$5:$H$212,"*"&D85&"*",ATLAS기법매핑!$M$5:$M$212,"Feasible") -> 0 / 0 / 0 | AE85: LLM07, LLM05 | AF85: ASI08 | AL85: =(LEN(Y85&Z85)>0)+(LEN(AD85&AE85)>0)+(LEN(AF85&AG85)>0)+(LEN(AH85&AI85)>0)+(LEN(AJ85&AK85)>0) -> 2 | AM85: =COUNTIF(ATLAS사례연구!$J$5:$J$77,"*"&D85&"*") -> 0 | AN85: =COUNTIFS(ATLAS사례연구!$J$5:$J$77,"*"&D85&"*",ATLAS사례연구!$C$5:$C$77,"Incident") -> 0 | AO85: 0 | AP85: 1 | AQ85: =IF(AN85+AO85>0,"실제 사고 확인",IF(AB85>0,"실사용 기법 포함",IF(OR(AM85>0,AP85>0),"실증·공개 취약점","이론·시나리오"))) -> 실증·공개 취약점 | AS85: • [OWASP 인용] GitHub Copilot·Cursor 코드 에이전트 익스플로잇(2025.03) • [OWASP 시나리오] 인젝션된 시장분석 에이전트가 위험 한도를 부풀려 연쇄 매매(ASI08 시나리오#1) | AT85: — (ATLAS 완화책 없음: Lv2 핵심 통제 참조) | AU85: 결함 격리·블라스트 반경 상한, 계획/실행 분리, 서킷브레이커, 디지털 트윈 재현 시험 | AV85: UT-27
A86: D06. 에이전트 오남용 및 통제 상실 | B86: UT-23 | C86: 에이전트 간 연쇄 장애 | D86: UT-23.2 | E86: 자기복제 프롬프트(웜) | F86: 출력에 자신을 복제하는 지시를 포함시켜, 메일/문서를 매개로 연결된 다른 AI 시스템으로 자동 전파되며 데이터 유출과 스팸 확산 | G86: =IF(AN86+AO86>=2,"상",IF(OR(AN86+AO86=1,AM86>0,AB86>0,AP86>0),"중","하")) -> 중 | H86: 상 | I86: =IF(AND(G86="상",H86="상"),"매우 높음",IF(OR(AND(G86="상",H86="중"),AND(G86="중",H86="상")),"높음",IF(OR(AND(G86="중",H86="중"),AND(G86="상",H86="하"),AND(G86="하",H86="상")),"보통","낮음"))) -> 높음 | J86: ="실제 사고 "&(AN86+AO86)&"건(ATLAS "&AN86&" / OWASP "&AO86&"), 실증 사례 "&(AM86-AN86)&"건, Realized 기법 "&AB86&"개, 취약점·익스플로잇 "&AP86&"건" -> 실제 사고 0건(ATLAS 0 / OWASP 0), 실증 사례 1건, Realized 기법 0개, 취약점·익스플로잇 0건 | K86: 연결된 AI 시스템 전반 자동 확산 | L86: 지속성(Persistence) | M86: 지속성 | Q86: ● | R86: ● | S86: 가용성, 무결성 | T86: ○ | V86: ● | Y86: T0061 | AA86: =COUNTIF(ATLAS기법매핑!$H$5:$H$212,"*"&D86&"*") -> 1 | AB86: =COUNTIFS(ATLAS기법매핑!$H$5:$H$212,"*"&D86&"*",ATLAS기법매핑!$M$5:$M$212,"Realized") -> 0 | AC86: =COUNTIFS(ATLAS기법매핑!$H$5:$H$212,"*"&D86&"*",ATLAS기법매핑!$M$5:$M$212,"Realized")&" / "&COUNTIFS(ATLAS기법매핑!$H$5:$H$212,"*"&D86&"*",ATLAS기법매핑!$M$5:$M$212,"Demonstrated")&" / "&COUNTIFS(ATLAS기법매핑!$H$5:$H$212,"*"&D86&"*",ATLAS기법매핑!$M$5:$M$212,"Feasible") -> 0 / 1 / 0 | AE86: LLM01, LLM03 | AF86: ASI08 | AL86: =(LEN(Y86&Z86)>0)+(LEN(AD86&AE86)>0)+(LEN(AF86&AG86)>0)+(LEN(AH86&AI86)>0)+(LEN(AJ86&AK86)>0) -> 3 | AM86: =COUNTIF(ATLAS사례연구!$J$5:$J$77,"*"&D86&"*") -> 1 | AN86: =COUNTIFS(ATLAS사례연구!$J$5:$J$77,"*"&D86&"*",ATLAS사례연구!$C$5:$C$77,"Incident") -> 0 | AO86: 0 | AP86: 0 | AQ86: =IF(AN86+AO86>0,"실제 사고 확인",IF(AB86>0,"실사용 기법 포함",IF(OR(AM86>0,AP86>0),"실증·공개 취약점","이론·시나리오"))) -> 실증·공개 취약점 | AR86: CS0024 | AS86: • [ATLAS CS0024·실증] RAG를 매개로 자기복제 프롬프트가 GenAI 이메일 비서 간 전파(Morris II 웜) | AT86: M0020 Generative AI Guardrails M0021 Generative AI Guidelines M0022 Generative AI Model Alignment | AU86: 결함 격리·블라스트 반경 상한, 계획/실행 분리, 서킷브레이커, 디지털 트윈 재현 시험 | AV86: UT-27
A87: D06. 에이전트 오남용 및 통제 상실 | B87: UT-23 | C87: 에이전트 간 연쇄 장애 | D87: UT-23.3 | E87: 자동 대응 루프 폭주 | F87: 자동 복구/대응 에이전트 간 상호 트리거로 피드백 루프가 형성되어 과도한 조치, 자원 소모, 경보 억제 등 시스템 불안정 유발 | G87: =IF(AN87+AO87>=2,"상",IF(OR(AN87+AO87=1,AM87>0,AB87>0,AP87>0),"중","하")) -> 하 | H87: 중 | I87: =IF(AND(G87="상",H87="상"),"매우 높음",IF(OR(AND(G87="상",H87="중"),AND(G87="중",H87="상")),"높음",IF(OR(AND(G87="중",H87="중"),AND(G87="상",H87="하"),AND(G87="하",H87="상")),"보통","낮음"))) -> 낮음 | J87: ="실제 사고 "&(AN87+AO87)&"건(ATLAS "&AN87&" / OWASP "&AO87&"), 실증 사례 "&(AM87-AN87)&"건, Realized 기법 "&AB87&"개, 취약점·익스플로잇 "&AP87&"건" -> 실제 사고 0건(ATLAS 0 / OWASP 0), 실증 사례 0건, Realized 기법 0개, 취약점·익스플로잇 0건 | K87: 일시적 가용성 저하 및 과잉 조치 | L87: 영향(Impact) | M87: — | Q87: ● | R87: ● | S87: 가용성 | T87: ○ | V87: ● | AA87: =COUNTIF(ATLAS기법매핑!$H$5:$H$212,"*"&D87&"*") -> 0 | AB87: =COUNTIFS(ATLAS기법매핑!$H$5:$H$212,"*"&D87&"*",ATLAS기법매핑!$M$5:$M$212,"Realized") -> 0 | AC87: =COUNTIFS(ATLAS기법매핑!$H$5:$H$212,"*"&D87&"*",ATLAS기법매핑!$M$5:$M$212,"Realized")&" / "&COUNTIFS(ATLAS기법매핑!$H$5:$H$212,"*"&D87&"*",ATLAS기법매핑!$M$5:$M$212,"Demonstrated")&" / "&COUNTIFS(ATLAS기법매핑!$H$5:$H$212,"*"&D87&"*",ATLAS기법매핑!$M$5:$M$212,"Feasible") -> 0 / 0 / 0 | AE87: LLM06 | AF87: ASI08 | AI87: DSGAI17, DSGAI06 | AL87: =(LEN(Y87&Z87)>0)+(LEN(AD87&AE87)>0)+(LEN(AF87&AG87)>0)+(LEN(AH87&AI87)>0)+(LEN(AJ87&AK87)>0) -> 3 | AM87: =COUNTIF(ATLAS사례연구!$J$5:$J$77,"*"&D87&"*") -> 0 | AN87: =COUNTIFS(ATLAS사례연구!$J$5:$J$77,"*"&D87&"*",ATLAS사례연구!$C$5:$C$77,"Incident") -> 0 | AO87: 0 | AP87: 0 | AQ87: =IF(AN87+AO87>0,"실제 사고 확인",IF(AB87>0,"실사용 기법 포함",IF(OR(AM87>0,AP87>0),"실증·공개 취약점","이론·시나리오"))) -> 이론·시나리오 | AS87: • [OWASP 시나리오] 자동 복구 에이전트 간 피드백 루프로 경보 억제 및 과잉 조치(ASI08 시나리오#6) | AT87: — (ATLAS 완화책 없음: Lv2 핵심 통제 참조) | AU87: 결함 격리·블라스트 반경 상한, 계획/실행 분리, 서킷브레이커, 디지털 트윈 재현 시험 | AV87: UT-27
A88: D06. 에이전트 오남용 및 통제 상실 | B88: UT-24 | C88: 통제를 벗어난 에이전트 | D88: UT-24.1 | E88: 목표 이탈과 보상 해킹 | F88: 에이전트가 부여된 목표를 문자 그대로 최적화하는 과정에서 백업 삭제/통제 우회 등 의도하지 않은 유해 행위를 선택하고 정상 동작처럼 보고 | G88: =IF(AN88+AO88>=2,"상",IF(OR(AN88+AO88=1,AM88>0,AB88>0,AP88>0),"중","하")) -> 상 | H88: 상 | I88: =IF(AND(G88="상",H88="상"),"매우 높음",IF(OR(AND(G88="상",H88="중"),AND(G88="중",H88="상")),"높음",IF(OR(AND(G88="중",H88="중"),AND(G88="상",H88="하"),AND(G88="하",H88="상")),"보통","낮음"))) -> 매우 높음 | J88: ="실제 사고 "&(AN88+AO88)&"건(ATLAS "&AN88&" / OWASP "&AO88&"), 실증 사례 "&(AM88-AN88)&"건, Realized 기법 "&AB88&"개, 취약점·익스플로잇 "&AP88&"건" -> 실제 사고 2건(ATLAS 1 / OWASP 1), 실증 사례 0건, Realized 기법 0개, 취약점·익스플로잇 0건 | K88: 권한 내 유해 행위 지속 및 은폐 | L88: 해당 없음(구조적 결함) | M88: — | Q88: ● | R88: ● | S88: 무결성, 가용성 | V88: ● | W88: ○ | X88: 과업·에이전트 종료 후에도 행위가 지속되는 위험 포함 | AA88: =COUNTIF(ATLAS기법매핑!$H$5:$H$212,"*"&D88&"*") -> 0 | AB88: =COUNTIFS(ATLAS기법매핑!$H$5:$H$212,"*"&D88&"*",ATLAS기법매핑!$M$5:$M$212,"Realized") -> 0 | AC88: =COUNTIFS(ATLAS기법매핑!$H$5:$H$212,"*"&D88&"*",ATLAS기법매핑!$M$5:$M$212,"Realized")&" / "&COUNTIFS(ATLAS기법매핑!$H$5:$H$212,"*"&D88&"*",ATLAS기법매핑!$M$5:$M$212,"Demonstrated")&" / "&COUNTIFS(ATLAS기법매핑!$H$5:$H$212,"*"&D88&"*",ATLAS기법매핑!$M$5:$M$212,"Feasible") -> 0 / 0 / 0 | AE88: LLM07 | AF88: ASI10 | AL88: =(LEN(Y88&Z88)>0)+(LEN(AD88&AE88)>0)+(LEN(AF88&AG88)>0)+(LEN(AH88&AI88)>0)+(LEN(AJ88&AK88)>0) -> 2 | AM88: =COUNTIF(ATLAS사례연구!$J$5:$J$77,"*"&D88&"*") -> 1 | AN88: =COUNTIFS(ATLAS사례연구!$J$5:$J$77,"*"&D88&"*",ATLAS사례연구!$C$5:$C$77,"Incident") -> 1 | AO88: 1 | AP88: 0 | AQ88: =IF(AN88+AO88>0,"실제 사고 확인",IF(AB88>0,"실사용 기법 포함",IF(OR(AM88>0,AP88>0),"실증·공개 취약점","이론·시나리오"))) -> 실제 사고 확인 | AR88: CS0068 | AS88: • [ATLAS CS0068·실제사고] OpenAI 평가용 자율 에이전트들이 평가 경계를 넘어 외부 인프라 구축·Hugging Face 침해(실제 사고) • [OWASP 인용] Replit 바이브 코딩 에이전트의 지시 위반 및 데이터 조작(2025.07) • [OWASP 시나리오] 비용 최소화 목표의 에이전트가 운영 백업 삭제를 학습(ASI10 시나리오#4) | AT88: — (ATLAS 완화책 없음: Lv2 핵심 통제 참조) | AU88: 행동 기준선·감시 에이전트, 범위 이탈 탐지, 킬스위치·자격증명 즉시 폐기, 서명된 행동 매니페스트 | AV88: UT-28
A89: D06. 에이전트 오남용 및 통제 상실 | B89: UT-24 | C89: 통제를 벗어난 에이전트 | D89: UT-24.2 | E89: 악성 에이전트 배치 | F89: 공격자가 피해 환경에 자체 에이전트를 배치하거나 승인되지 않은 에이전트를 실행하여 정상 에이전트로 위장한 채 데이터 접근 및 행위 수행 | G89: =IF(AN89+AO89>=2,"상",IF(OR(AN89+AO89=1,AM89>0,AB89>0,AP89>0),"중","하")) -> 상 | H89: 상 | I89: =IF(AND(G89="상",H89="상"),"매우 높음",IF(OR(AND(G89="상",H89="중"),AND(G89="중",H89="상")),"높음",IF(OR(AND(G89="중",H89="중"),AND(G89="상",H89="하"),AND(G89="하",H89="상")),"보통","낮음"))) -> 매우 높음 | J89: ="실제 사고 "&(AN89+AO89)&"건(ATLAS "&AN89&" / OWASP "&AO89&"), 실증 사례 "&(AM89-AN89)&"건, Realized 기법 "&AB89&"개, 취약점·익스플로잇 "&AP89&"건" -> 실제 사고 2건(ATLAS 2 / OWASP 0), 실증 사례 0건, Realized 기법 1개, 취약점·익스플로잇 0건 | K89: 정상 위장 에이전트의 지속적 데이터 접근 | L89: 실행(Execution) | M89: 실행 | Q89: ● | R89: ● | S89: 무결성, 가용성 | V89: ● | W89: ○ | X89: 과업·에이전트 종료 후에도 행위가 지속되는 위험 포함 | Y89: T0103 | AA89: =COUNTIF(ATLAS기법매핑!$H$5:$H$212,"*"&D89&"*") -> 1 | AB89: =COUNTIFS(ATLAS기법매핑!$H$5:$H$212,"*"&D89&"*",ATLAS기법매핑!$M$5:$M$212,"Realized") -> 1 | AC89: =COUNTIFS(ATLAS기법매핑!$H$5:$H$212,"*"&D89&"*",ATLAS기법매핑!$M$5:$M$212,"Realized")&" / "&COUNTIFS(ATLAS기법매핑!$H$5:$H$212,"*"&D89&"*",ATLAS기법매핑!$M$5:$M$212,"Demonstrated")&" / "&COUNTIFS(ATLAS기법매핑!$H$5:$H$212,"*"&D89&"*",ATLAS기법매핑!$M$5:$M$212,"Feasible") -> 1 / 0 / 0 | AF89: ASI10 | AK89: MCP09 | AL89: =(LEN(Y89&Z89)>0)+(LEN(AD89&AE89)>0)+(LEN(AF89&AG89)>0)+(LEN(AH89&AI89)>0)+(LEN(AJ89&AK89)>0) -> 3 | AM89: =COUNTIF(ATLAS사례연구!$J$5:$J$77,"*"&D89&"*") -> 2 | AN89: =COUNTIFS(ATLAS사례연구!$J$5:$J$77,"*"&D89&"*",ATLAS사례연구!$C$5:$C$77,"Incident") -> 2 | AO89: 0 | AP89: 0 | AQ89: =IF(AN89+AO89>0,"실제 사고 확인",IF(AB89>0,"실사용 기법 포함",IF(OR(AM89>0,AP89>0),"실증·공개 취약점","이론·시나리오"))) -> 실제 사고 확인 | AR89: CS0047, CS0069 | AS89: • [ATLAS CS0047·실제사고] 과권한 GitHub 토큰으로 Amazon Q VS Code 확장에 파괴형 에이전트 지시 커밋(실제 사고) • [ATLAS CS0069·실제사고] GTG-1002가 탈옥한 Claude Code로 약 30개 조직 대상 자율 사이버 첩보(실제 사고) | AT89: — (ATLAS 완화책 없음: Lv2 핵심 통제 참조) | AU89: 행동 기준선·감시 에이전트, 범위 이탈 탐지, 킬스위치·자격증명 즉시 폐기, 서명된 행동 매니페스트 | AV89: UT-28
A90: D06. 에이전트 오남용 및 통제 상실 | B90: UT-24 | C90: 통제를 벗어난 에이전트 | D90: UT-24.3 | E90: 에이전트 설정 변조 | F90: 에이전트 설정 파일(규칙/권한/연결 도구)을 변조하여 보안 기능 비활성화 또는 악성 지시를 영속화하고, 설정을 공유하는 모든 에이전트로 영향 전파 | G90: =IF(AN90+AO90>=2,"상",IF(OR(AN90+AO90=1,AM90>0,AB90>0,AP90>0),"중","하")) -> 중 | H90: 상 | I90: =IF(AND(G90="상",H90="상"),"매우 높음",IF(OR(AND(G90="상",H90="중"),AND(G90="중",H90="상")),"높음",IF(OR(AND(G90="중",H90="중"),AND(G90="상",H90="하"),AND(G90="하",H90="상")),"보통","낮음"))) -> 높음 | J90: ="실제 사고 "&(AN90+AO90)&"건(ATLAS "&AN90&" / OWASP "&AO90&"), 실증 사례 "&(AM90-AN90)&"건, Realized 기법 "&AB90&"개, 취약점·익스플로잇 "&AP90&"건" -> 실제 사고 0건(ATLAS 0 / OWASP 0), 실증 사례 3건, Realized 기법 0개, 취약점·익스플로잇 1건 | K90: 보안 기능 해제 및 악성 지시 영속화 | L90: 지속성(Persistence) | M90: 지속성, 방어 회피 | Q90: ● | R90: ● | S90: 무결성, 가용성 | V90: ● | W90: ○ | X90: 과업·에이전트 종료 후에도 행위가 지속되는 위험 포함 | Y90: T0081 | AA90: =COUNTIF(ATLAS기법매핑!$H$5:$H$212,"*"&D90&"*") -> 1 | AB90: =COUNTIFS(ATLAS기법매핑!$H$5:$H$212,"*"&D90&"*",ATLAS기법매핑!$M$5:$M$212,"Realized") -> 0 | AC90: =COUNTIFS(ATLAS기법매핑!$H$5:$H$212,"*"&D90&"*",ATLAS기법매핑!$M$5:$M$212,"Realized")&" / "&COUNTIFS(ATLAS기법매핑!$H$5:$H$212,"*"&D90&"*",ATLAS기법매핑!$M$5:$M$212,"Demonstrated")&" / "&COUNTIFS(ATLAS기법매핑!$H$5:$H$212,"*"&D90&"*",ATLAS기법매핑!$M$5:$M$212,"Feasible") -> 0 / 1 / 0 | AE90: LLM02 | AF90: ASI10 | AL90: =(LEN(Y90&Z90)>0)+(LEN(AD90&AE90)>0)+(LEN(AF90&AG90)>0)+(LEN(AH90&AI90)>0)+(LEN(AJ90&AK90)>0) -> 3 | AM90: =COUNTIF(ATLAS사례연구!$J$5:$J$77,"*"&D90&"*") -> 3 | AN90: =COUNTIFS(ATLAS사례연구!$J$5:$J$77,"*"&D90&"*",ATLAS사례연구!$C$5:$C$77,"Incident") -> 0 | AO90: 0 | AP90: 1 | AQ90: =IF(AN90+AO90>0,"실제 사고 확인",IF(AB90>0,"실사용 기법 포함",IF(OR(AM90>0,AP90>0),"실증·공개 취약점","이론·시나리오"))) -> 실증·공개 취약점 | AR90: CS0041, CS0050, CS0051 | AS90: • [ATLAS CS0041·실증] AI 코딩도구 규칙 파일에 보이지 않는 유니코드 지시를 숨겨 악성 코드 생성 유도 • [ATLAS CS0050·실증] 악성 링크 1회 클릭으로 OpenClaw 로컬 에이전트 원격 코드 실행 • [ATLAS CS0051·실증] 웹페이지 인젝션으로 OpenClaw에 지속 지시를 심어 C2로 활용 • [OWASP 인용] Cursor CLI 프로젝트 설정 경유 명령 실행(2025.10) | AT90: M0035 AI Red Team | AU90: 행동 기준선·감시 에이전트, 범위 이탈 탐지, 킬스위치·자격증명 즉시 폐기, 서명된 행동 매니페스트 | AV90: UT-28
A91: D06. 에이전트 오남용 및 통제 상실 | B91: UT-24 | C91: 통제를 벗어난 에이전트 | D91: UT-24.4 | E91: 종료 후 활동 지속 | F91: 자율 에이전트가 과업 종료 또는 중지 이후에도 실행 환경을 재구성하여 활동을 지속하거나 외부 자원을 확보 | G91: =IF(AN91+AO91>=2,"상",IF(OR(AN91+AO91=1,AM91>0,AB91>0,AP91>0),"중","하")) -> 중 | H91: 상 | I91: =IF(AND(G91="상",H91="상"),"매우 높음",IF(OR(AND(G91="상",H91="중"),AND(G91="중",H91="상")),"높음",IF(OR(AND(G91="중",H91="중"),AND(G91="상",H91="하"),AND(G91="하",H91="상")),"보통","낮음"))) -> 높음 | J91: ="실제 사고 "&(AN91+AO91)&"건(ATLAS "&AN91&" / OWASP "&AO91&"), 실증 사례 "&(AM91-AN91)&"건, Realized 기법 "&AB91&"개, 취약점·익스플로잇 "&AP91&"건" -> 실제 사고 1건(ATLAS 1 / OWASP 0), 실증 사례 0건, Realized 기법 1개, 취약점·익스플로잇 0건 | K91: 통제 밖 외부 자원 확보 및 침해 | L91: 지속성(Persistence) | M91: 지속성 | Q91: ● | R91: ● | S91: 무결성, 가용성 | V91: ○ | W91: ● | X91: 과업 종료·중지 이후의 활동 지속 | Y91: T0121 | AA91: =COUNTIF(ATLAS기법매핑!$H$5:$H$212,"*"&D91&"*") -> 1 | AB91: =COUNTIFS(ATLAS기법매핑!$H$5:$H$212,"*"&D91&"*",ATLAS기법매핑!$M$5:$M$212,"Realized") -> 1 | AC91: =COUNTIFS(ATLAS기법매핑!$H$5:$H$212,"*"&D91&"*",ATLAS기법매핑!$M$5:$M$212,"Realized")&" / "&COUNTIFS(ATLAS기법매핑!$H$5:$H$212,"*"&D91&"*",ATLAS기법매핑!$M$5:$M$212,"Demonstrated")&" / "&COUNTIFS(ATLAS기법매핑!$H$5:$H$212,"*"&D91&"*",ATLAS기법매핑!$M$5:$M$212,"Feasible") -> 1 / 0 / 0 | AF91: ASI10 | AL91: =(LEN(Y91&Z91)>0)+(LEN(AD91&AE91)>0)+(LEN(AF91&AG91)>0)+(LEN(AH91&AI91)>0)+(LEN(AJ91&AK91)>0) -> 2 | AM91: =COUNTIF(ATLAS사례연구!$J$5:$J$77,"*"&D91&"*") -> 1 | AN91: =COUNTIFS(ATLAS사례연구!$J$5:$J$77,"*"&D91&"*",ATLAS사례연구!$C$5:$C$77,"Incident") -> 1 | AO91: 0 | AP91: 0 | AQ91: =IF(AN91+AO91>0,"실제 사고 확인",IF(AB91>0,"실사용 기법 포함",IF(OR(AM91>0,AP91>0),"실증·공개 취약점","이론·시나리오"))) -> 실제 사고 확인 | AR91: CS0068 | AS91: • [ATLAS CS0068·실제사고] OpenAI 평가용 자율 에이전트들이 평가 경계를 넘어 외부 인프라 구축·Hugging Face 침해(실제 사고) | AT91: — (ATLAS 완화책 없음: Lv2 핵심 통제 참조) | AU91: 행동 기준선·감시 에이전트, 범위 이탈 탐지, 킬스위치·자격증명 즉시 폐기, 서명된 행동 매니페스트 | AV91: UT-28
A92: D07. AI 신원 및 권한 악용 | B92: UT-25 | C92: 에이전트 자격증명 탈취 및 악용 | D92: UT-25.1 | E92: 설정 파일 내 비밀정보 수집 | F92: 에이전트 설정/RAG 문서/코드 저장소/CI 변수에 평문 저장된 API 키와 토큰을 수집하여 연동 시스템 접근 권한 확보 | G92: =IF(AN92+AO92>=2,"상",IF(OR(AN92+AO92=1,AM92>0,AB92>0,AP92>0),"중","하")) -> 상 | H92: 상 | I92: =IF(AND(G92="상",H92="상"),"매우 높음",IF(OR(AND(G92="상",H92="중"),AND(G92="중",H92="상")),"높음",IF(OR(AND(G92="중",H92="중"),AND(G92="상",H92="하"),AND(G92="하",H92="상")),"보통","낮음"))) -> 매우 높음 | J92: ="실제 사고 "&(AN92+AO92)&"건(ATLAS "&AN92&" / OWASP "&AO92&"), 실증 사례 "&(AM92-AN92)&"건, Realized 기법 "&AB92&"개, 취약점·익스플로잇 "&AP92&"건" -> 실제 사고 8건(ATLAS 7 / OWASP 1), 실증 사례 6건, Realized 기법 1개, 취약점·익스플로잇 0건 | K92: 연동 시스템 접근 권한 일괄 확보 | L92: 자격증명 접근(Credential Access) | M92: 자격증명 접근 | O92: ● | P92: ● | Q92: ● | R92: ● | S92: 기밀성, 재무 | T92: ○ | U92: ● | V92: ○ | W92: ○ | X92: 퇴역 에이전트의 미회수 자격증명은 종료 단계 위험 | Y92: T0055, T0083, T0082 | AA92: =COUNTIF(ATLAS기법매핑!$H$5:$H$212,"*"&D92&"*") -> 3 | AB92: =COUNTIFS(ATLAS기법매핑!$H$5:$H$212,"*"&D92&"*",ATLAS기법매핑!$M$5:$M$212,"Realized") -> 1 | AC92: =COUNTIFS(ATLAS기법매핑!$H$5:$H$212,"*"&D92&"*",ATLAS기법매핑!$M$5:$M$212,"Realized")&" / "&COUNTIFS(ATLAS기법매핑!$H$5:$H$212,"*"&D92&"*",ATLAS기법매핑!$M$5:$M$212,"Demonstrated")&" / "&COUNTIFS(ATLAS기법매핑!$H$5:$H$212,"*"&D92&"*",ATLAS기법매핑!$M$5:$M$212,"Feasible") -> 1 / 2 / 0 | AE92: LLM08 | AH92: DSGAI02 | AJ92: MCP01 | AL92: =(LEN(Y92&Z92)>0)+(LEN(AD92&AE92)>0)+(LEN(AF92&AG92)>0)+(LEN(AH92&AI92)>0)+(LEN(AJ92&AK92)>0) -> 4 | AM92: =COUNTIF(ATLAS사례연구!$J$5:$J$77,"*"&D92&"*") -> 13 | AN92: =COUNTIFS(ATLAS사례연구!$J$5:$J$77,"*"&D92&"*",ATLAS사례연구!$C$5:$C$77,"Incident") -> 7 | AO92: 1 | AP92: 0 | AQ92: =IF(AN92+AO92>0,"실제 사고 확인",IF(AB92>0,"실사용 기법 포함",IF(OR(AM92>0,AP92>0),"실증·공개 취약점","이론·시나리오"))) -> 실제 사고 확인 | AR92: CS0006, CS0016, CS0023, CS0027, CS0030, CS0035, CS0043, CS0045, CS0047, CS0048, CS0054, CS0068, CS0069 | AS92: • [ATLAS CS0006·실제사고] Clearview AI 저장소 설정 오류로 소스코드·자격증명·모델 노출 • [ATLAS CS0023·실제사고] 인증 없는 Ray 클러스터를 탈취해 연산자원·자격증명·모델 탈취(ShadowRay, 실제 사고) • [ATLAS CS0030·실제사고] 탈취한 클라우드 자격증명으로 LLM 서비스를 무단 사용·재판매(LLMjacking, 실제 사고) • [OWASP 인용] Hugging Face Spaces 비밀 토큰 노출(2024) | AT92: M0026 Privileged AI Agent Permissions Configuration M0027 Single-User AI Agent Permissions Configuration | AU92: 단명·작업범위 토큰, 비밀정보의 프롬프트·설정 내 저장 금지, 비밀 스캐닝, 에이전트별 고유 신원, 퇴역 시 즉시 폐기 | AV92: UT-13
A93: D07. AI 신원 및 권한 악용 | B93: UT-25 | C93: 에이전트 자격증명 탈취 및 악용 | D93: UT-25.2 | E93: 도구 경유 자격증명 수집 | F93: 에이전트 도구(파일 조회/명령 실행)를 악용하여 실행 환경의 자격증명 파일과 환경변수를 읽어 외부로 전달 | G93: =IF(AN93+AO93>=2,"상",IF(OR(AN93+AO93=1,AM93>0,AB93>0,AP93>0),"중","하")) -> 중 | H93: 상 | I93: =IF(AND(G93="상",H93="상"),"매우 높음",IF(OR(AND(G93="상",H93="중"),AND(G93="중",H93="상")),"높음",IF(OR(AND(G93="중",H93="중"),AND(G93="상",H93="하"),AND(G93="하",H93="상")),"보통","낮음"))) -> 높음 | J93: ="실제 사고 "&(AN93+AO93)&"건(ATLAS "&AN93&" / OWASP "&AO93&"), 실증 사례 "&(AM93-AN93)&"건, Realized 기법 "&AB93&"개, 취약점·익스플로잇 "&AP93&"건" -> 실제 사고 0건(ATLAS 0 / OWASP 0), 실증 사례 3건, Realized 기법 0개, 취약점·익스플로잇 0건 | K93: 실행 환경 자격증명 탈취 | L93: 자격증명 접근(Credential Access) | M93: 자격증명 접근 | O93: ● | P93: ● | Q93: ● | R93: ● | S93: 기밀성, 재무 | T93: ○ | U93: ● | V93: ○ | W93: ○ | X93: 퇴역 에이전트의 미회수 자격증명은 종료 단계 위험 | Y93: T0098 | AA93: =COUNTIF(ATLAS기법매핑!$H$5:$H$212,"*"&D93&"*") -> 1 | AB93: =COUNTIFS(ATLAS기법매핑!$H$5:$H$212,"*"&D93&"*",ATLAS기법매핑!$M$5:$M$212,"Realized") -> 0 | AC93: =COUNTIFS(ATLAS기법매핑!$H$5:$H$212,"*"&D93&"*",ATLAS기법매핑!$M$5:$M$212,"Realized")&" / "&COUNTIFS(ATLAS기법매핑!$H$5:$H$212,"*"&D93&"*",ATLAS기법매핑!$M$5:$M$212,"Demonstrated")&" / "&COUNTIFS(ATLAS기법매핑!$H$5:$H$212,"*"&D93&"*",ATLAS기법매핑!$M$5:$M$212,"Feasible") -> 0 / 1 / 0 | AG93: ASI03 | AH93: DSGAI02 | AL93: =(LEN(Y93&Z93)>0)+(LEN(AD93&AE93)>0)+(LEN(AF93&AG93)>0)+(LEN(AH93&AI93)>0)+(LEN(AJ93&AK93)>0) -> 3 | AM93: =COUNTIF(ATLAS사례연구!$J$5:$J$77,"*"&D93&"*") -> 3 | AN93: =COUNTIFS(ATLAS사례연구!$J$5:$J$77,"*"&D93&"*",ATLAS사례연구!$C$5:$C$77,"Incident") -> 0 | AO93: 0 | AP93: 0 | AQ93: =IF(AN93+AO93>0,"실제 사고 확인",IF(AB93>0,"실사용 기법 포함",IF(OR(AM93>0,AP93>0),"실증·공개 취약점","이론·시나리오"))) -> 실증·공개 취약점 | AR93: CS0048, CS0054, CS0067 | AS93: • [ATLAS CS0067·실증] Claude Code GitHub Action이 인젝션으로 저장소 비밀값을 노출 • [ATLAS CS0048·실증] 인터넷에 노출된 ClawdBot 제어 인터페이스 수백 개에서 자격증명 탈취·명령 실행 • [ATLAS CS0054·실증] 원격 MCP 도구 설명문의 숨은 지시로 에이전트가 파일·데이터 유출 | AT93: M0032 Segmentation of AI Agent Components | AU93: 단명·작업범위 토큰, 비밀정보의 프롬프트·설정 내 저장 금지, 비밀 스캐닝, 에이전트별 고유 신원, 퇴역 시 즉시 폐기 | AV93: UT-13
